projects/w3_sequential_logic/spsram/spsram.v
module spsram
#(
    parameter   BW_DATA = 32,
    parameter   BW_ADDR = 5
)
(
    input                   i_clk,
    input   [BW_DATA-1:0]   i_data,
    input   [BW_ADDR-1:0]   i_addr,
    input                   i_wen,
    input                   i_cen,
    input                   i_oen,
    output  [BW_DATA-1:0]   o_data
);

///// Memory Write //////////
reg [BW_DATA-1:0] mem[0:2**BW_ADDR-1];

always @(posedge i_clk) begin
    if(i_cen && i_wen) begin
        mem[i_addr] <= i_data;
    end
    else begin
        mem[i_addr] <= mem[i_addr];
    end
end

///// Memory Read //////////
`ifdef SPSRAM_ASYNC
    assign o_data   =   !i_oen            ? 'bz          :
                    	(i_cen && !i_wen) ? mem[i_addr]  :
                        'bx;
`else
    reg [BW_DATA-1:0] o_data;
    always @(posedge i_clk) begin
        if(i_oen) begin
            if(i_cen && !i_wen) begin
                o_data <= mem[i_addr];
            end
            else begin
                o_data <= 'bx;
            end
        end
        else begin
            o_data <= 'bz;
        end
    end
`endif

endmodule

projects/w3_sequential_logic/spsram/spsram_double.v
`include "spsram.v"

module spsram_double(
    input                   i_clk,
    input   [31:0]   		i_data,
    input   [4:0]   		i_addr,
    input                   i_wen,
    input                   i_cen,
    input                   i_oen,
    output  [31:0]  		o_data
);

	wire 					i_cen0;
	wire					i_cen1;
	wire					i_oen0;
	wire					i_oen1;

	assign i_cen0 = ~i_addr[4];
	assign i_oen0 = ~i_addr[4];
	assign i_cen1 =  i_addr[4];
	assign i_oen1 =  i_addr[4];


	spsram
	#(
		.BW_DATA			(32			),
		.BW_ADDR			(4			)
	)
	u_spsram0(
		.i_clk				(i_clk				),
		.i_data				(i_data				),
		.i_addr				(i_addr[3:0]		),
		.i_wen				(i_wen				),
		.i_cen				(i_cen0				),
		.i_oen				(i_oen0				),
		.o_data				(o_data				)
	);


	spsram
	#(
		.BW_DATA			(32			),
		.BW_ADDR			(4			)
	)
	u_spsram1(
		.i_clk				(i_clk				),
		.i_data				(i_data				),
		.i_addr				(i_addr				),
		.i_wen				(i_wen				),
		.i_cen				(i_cen1				),
		.i_oen				(i_oen1				),
		.o_data				(o_data				)
	);

endmodule

projects/w3_sequential_logic/spsram/spsram_double_tb.v
//-------------------------------------
// Define Global Variables
// ------------------------------------
`define CLKFREQ     100
`define SIMCYCLE    100

`define SPSRAM_ASYNC

//-------------------------------------
// Includes
// ------------------------------------
`include "spsram_double.v"

module spsram_double_tb;
//-------------------------------------
// DUT Signals & Instantiate
// ------------------------------------
    reg                     i_clk;
    reg   [31:0]   			i_data;
    reg    [4:0]  			i_addr;
    reg                     i_wen;
    reg                     i_cen;
    reg                     i_oen;
    wire  [31:0]   			o_data;
    
    spsram_double
	u_spsram_double(
        .i_clk      (   i_clk       ),
        .i_data     (   i_data      ),
        .i_addr     (   i_addr      ),
        .i_wen      (   i_wen       ),
        .i_cen      (   i_cen       ),
        .i_oen      (   i_oen       ),
        .o_data     (   o_data      )
);


//---------------------------------------------------
// Clock
//---------------------------------------------------
always #(500/`CLKFREQ) i_clk = ~i_clk;

//---------------------------------------------------
// Tasks
//---------------------------------------------------
reg     [8*32-1:0]  taskState;

task init;
    begin
        i_clk   = 0;
        i_data  = 0;
        i_addr  = 0;
        i_wen   = 0;
        i_cen   = 0;
        i_oen   = 0;
    end
endtask

task memWR;
    input   [4:0]  ti_addr;
    input   [31:0]  ti_data;
    begin
        @(negedge i_clk) begin
            taskState   = "WR";
            i_data      = ti_data;
            i_addr      = ti_addr;
            i_wen       = 1'b1;
            i_cen       = 1'b1;
            i_oen       = 1'b0;
        end
    end
endtask

task memRD;
    input   [4:0]  ti_addr;
    begin
        @(negedge i_clk) begin
            taskState   = "RD";
            i_addr      = ti_addr;
            i_wen       = 1'b0;
            i_cen       = 1'b1;
            i_oen       = 1'b1;
        end
    end
endtask
//---------------------------------------------------
// Test Stimulus
//---------------------------------------------------
integer  i, j;
initial begin
    init();
    #(4*100/`CLKFREQ);

    for(i = 0; i < `SIMCYCLE; i++) begin
       memWR(i, i);
    end
    for(i = 0; i < `SIMCYCLE; i++) begin
       memRD(i);
    end
	#100;
    $finish;
end

//---------------------------------------------------
// Dump VCD
//---------------------------------------------------

reg [8*32-1:0] vcd_file;
initial begin
    if($value$plusargs("vcd_file=%s", vcd_file)) begin
        $dumpfile(vcd_file);
        $dumpvars;
    end
    else begin
        $dumpfile("spsram_double_tb.vcd");
        $dumpvars;     
    end
end

endmodule

projects/w3_sequential_logic/spsram/vcd/spsram_double.vcd
$date
	Thu Jun 27 16:50:17 2024
$end
$version
	Icarus Verilog
$end
$timescale
	1ps
$end
$scope module spsram_double_tb $end
$var wire 32 ! o_data [31:0] $end
$var reg 5 " i_addr [4:0] $end
$var reg 1 # i_cen $end
$var reg 1 $ i_clk $end
$var reg 32 % i_data [31:0] $end
$var reg 1 & i_oen $end
$var reg 1 ' i_wen $end
$var reg 256 ( taskState [255:0] $end
$var reg 256 ) vcd_file [255:0] $end
$var integer 32 * i [31:0] $end
$scope module u_spsram_double $end
$var wire 5 + i_addr [4:0] $end
$var wire 1 # i_cen $end
$var wire 1 , i_cen0 $end
$var wire 1 $ i_clk $end
$var wire 32 - i_data [31:0] $end
$var wire 1 & i_oen $end
$var wire 1 . i_oen0 $end
$var wire 1 ' i_wen $end
$var wire 32 / o_data [31:0] $end
$var wire 1 0 i_oen1 $end
$var wire 1 1 i_cen1 $end
$scope module u_spsram0 $end
$var wire 4 2 i_addr [3:0] $end
$var wire 1 , i_cen $end
$var wire 1 $ i_clk $end
$var wire 32 3 i_data [31:0] $end
$var wire 1 . i_oen $end
$var wire 1 ' i_wen $end
$var wire 32 4 o_data [31:0] $end
$upscope $end
$scope module u_spsram1 $end
$var wire 4 5 i_addr [3:0] $end
$var wire 1 1 i_cen $end
$var wire 1 $ i_clk $end
$var wire 32 6 i_data [31:0] $end
$var wire 1 0 i_oen $end
$var wire 1 ' i_wen $end
$var wire 32 7 o_data [31:0] $end
$upscope $end
$upscope $end
$scope task init $end
$upscope $end
$scope task memRD $end
$var reg 5 8 ti_addr [4:0] $end
$upscope $end
$scope task memWR $end
$var reg 5 9 ti_addr [4:0] $end
$var reg 32 : ti_data [31:0] $end
$upscope $end
$upscope $end
$enddefinitions $end
#0
$dumpvars
bx :
bx 9
bx 8
bx 7
b0 6
b0 5
bx 4
b0 3
b0 2
01
00
bx /
1.
b0 -
1,
b0 +
bx *
b10111000101111011101100110001101100100001011110111001101110000011100110111001001100001011011010101111101100100011011110111010101100010011011000110010100101110011101100110001101100100 )
bx (
0'
0&
b0 %
0$
0#
b0 "
bx !
$end
#4000
b0 :
b0 9
b0 *
#5000
1$
#10000
b1 :
b1 9
b1 *
1#
1'
b101011101010010 (
0$
#15000
1$
#20000
b1 2
b1 5
b10 :
b10 9
b10 *
b1 "
b1 +
b1 %
b1 -
b1 3
b1 6
0$
#25000
1$
#30000
b10 2
b10 5
b11 :
b11 9
b11 *
b10 "
b10 +
b10 %
b10 -
b10 3
b10 6
0$
#35000
1$
#40000
b11 2
b11 5
b100 :
b100 9
b100 *
b11 "
b11 +
b11 %
b11 -
b11 3
b11 6
0$
#45000
1$
#50000
b100 2
b100 5
b101 :
b101 9
b101 *
b100 "
b100 +
b100 %
b100 -
b100 3
b100 6
0$
#55000
1$
#60000
b101 2
b101 5
b110 :
b110 9
b110 *
b101 "
b101 +
b101 %
b101 -
b101 3
b101 6
0$
#65000
1$
#70000
b110 2
b110 5
b111 :
b111 9
b111 *
b110 "
b110 +
b110 %
b110 -
b110 3
b110 6
0$
#75000
1$
#80000
b111 2
b111 5
b1000 :
b1000 9
b1000 *
b111 "
b111 +
b111 %
b111 -
b111 3
b111 6
0$
#85000
1$
#90000
b1000 2
b1000 5
b1001 :
b1001 9
b1001 *
b1000 "
b1000 +
b1000 %
b1000 -
b1000 3
b1000 6
0$
#95000
1$
#100000
b1001 2
b1001 5
b1010 :
b1010 9
b1010 *
b1001 "
b1001 +
b1001 %
b1001 -
b1001 3
b1001 6
0$
#105000
1$
#110000
b1010 2
b1010 5
b1011 :
b1011 9
b1011 *
b1010 "
b1010 +
b1010 %
b1010 -
b1010 3
b1010 6
0$
#115000
1$
#120000
b1011 2
b1011 5
b1100 :
b1100 9
b1100 *
b1011 "
b1011 +
b1011 %
b1011 -
b1011 3
b1011 6
0$
#125000
1$
#130000
b1100 2
b1100 5
b1101 :
b1101 9
b1101 *
b1100 "
b1100 +
b1100 %
b1100 -
b1100 3
b1100 6
0$
#135000
1$
#140000
b1101 2
b1101 5
b1110 :
b1110 9
b1110 *
b1101 "
b1101 +
b1101 %
b1101 -
b1101 3
b1101 6
0$
#145000
1$
#150000
b1110 2
b1110 5
b1111 :
b1111 9
b1111 *
b1110 "
b1110 +
b1110 %
b1110 -
b1110 3
b1110 6
0$
#155000
1$
#160000
b1111 2
b1111 5
b10000 :
b10000 9
b10000 *
b1111 "
b1111 +
b1111 %
b1111 -
b1111 3
b1111 6
0$
#165000
1$
#170000
0,
0.
11
10
b0 2
b0 5
b10001 :
b10001 9
b10001 *
b10000 "
b10000 +
b10000 %
b10000 -
b10000 3
b10000 6
0$
#175000
1$
#180000
b1 2
b1 5
b10010 :
b10010 9
b10010 *
b10001 "
b10001 +
b10001 %
b10001 -
b10001 3
b10001 6
0$
#185000
1$
#190000
b10 2
b10 5
b10011 :
b10011 9
b10011 *
b10010 "
b10010 +
b10010 %
b10010 -
b10010 3
b10010 6
0$
#195000
1$
#200000
b11 2
b11 5
b10100 :
b10100 9
b10100 *
b10011 "
b10011 +
b10011 %
b10011 -
b10011 3
b10011 6
0$
#205000
1$
#210000
b100 2
b100 5
b10101 :
b10101 9
b10101 *
b10100 "
b10100 +
b10100 %
b10100 -
b10100 3
b10100 6
0$
#215000
1$
#220000
b101 2
b101 5
b10110 :
b10110 9
b10110 *
b10101 "
b10101 +
b10101 %
b10101 -
b10101 3
b10101 6
0$
#225000
1$
#230000
b110 2
b110 5
b10111 :
b10111 9
b10111 *
b10110 "
b10110 +
b10110 %
b10110 -
b10110 3
b10110 6
0$
#235000
1$
#240000
b111 2
b111 5
b11000 :
b11000 9
b11000 *
b10111 "
b10111 +
b10111 %
b10111 -
b10111 3
b10111 6
0$
#245000
1$
#250000
b1000 2
b1000 5
b11001 :
b11001 9
b11001 *
b11000 "
b11000 +
b11000 %
b11000 -
b11000 3
b11000 6
0$
#255000
1$
#260000
b1001 2
b1001 5
b11010 :
b11010 9
b11010 *
b11001 "
b11001 +
b11001 %
b11001 -
b11001 3
b11001 6
0$
#265000
1$
#270000
b1010 2
b1010 5
b11011 :
b11011 9
b11011 *
b11010 "
b11010 +
b11010 %
b11010 -
b11010 3
b11010 6
0$
#275000
1$
#280000
b1011 2
b1011 5
b11100 :
b11100 9
b11100 *
b11011 "
b11011 +
b11011 %
b11011 -
b11011 3
b11011 6
0$
#285000
1$
#290000
b1100 2
b1100 5
b11101 :
b11101 9
b11101 *
b11100 "
b11100 +
b11100 %
b11100 -
b11100 3
b11100 6
0$
#295000
1$
#300000
b1101 2
b1101 5
b11110 :
b11110 9
b11110 *
b11101 "
b11101 +
b11101 %
b11101 -
b11101 3
b11101 6
0$
#305000
1$
#310000
b1110 2
b1110 5
b11111 :
b11111 9
b11111 *
b11110 "
b11110 +
b11110 %
b11110 -
b11110 3
b11110 6
0$
#315000
1$
#320000
b1111 2
b1111 5
b100000 :
b0 9
b100000 *
b11111 "
b11111 +
b11111 %
b11111 -
b11111 3
b11111 6
0$
#325000
1$
#330000
1,
1.
bx !
bx /
bx 4
bx 7
01
00
b0 2
b0 5
b100001 :
b1 9
b100001 *
b0 "
b0 +
b100000 %
b100000 -
b100000 3
b100000 6
0$
#335000
1$
#340000
b1 2
b1 5
b100010 :
b10 9
b100010 *
b1 "
b1 +
b100001 %
b100001 -
b100001 3
b100001 6
0$
#345000
1$
#350000
b10 2
b10 5
b100011 :
b11 9
b100011 *
b10 "
b10 +
b100010 %
b100010 -
b100010 3
b100010 6
0$
#355000
1$
#360000
b11 2
b11 5
b100100 :
b100 9
b100100 *
b11 "
b11 +
b100011 %
b100011 -
b100011 3
b100011 6
0$
#365000
1$
#370000
b100 2
b100 5
b100101 :
b101 9
b100101 *
b100 "
b100 +
b100100 %
b100100 -
b100100 3
b100100 6
0$
#375000
1$
#380000
b101 2
b101 5
b100110 :
b110 9
b100110 *
b101 "
b101 +
b100101 %
b100101 -
b100101 3
b100101 6
0$
#385000
1$
#390000
b110 2
b110 5
b100111 :
b111 9
b100111 *
b110 "
b110 +
b100110 %
b100110 -
b100110 3
b100110 6
0$
#395000
1$
#400000
b111 2
b111 5
b101000 :
b1000 9
b101000 *
b111 "
b111 +
b100111 %
b100111 -
b100111 3
b100111 6
0$
#405000
1$
#410000
b1000 2
b1000 5
b101001 :
b1001 9
b101001 *
b1000 "
b1000 +
b101000 %
b101000 -
b101000 3
b101000 6
0$
#415000
1$
#420000
b1001 2
b1001 5
b101010 :
b1010 9
b101010 *
b1001 "
b1001 +
b101001 %
b101001 -
b101001 3
b101001 6
0$
#425000
1$
#430000
b1010 2
b1010 5
b101011 :
b1011 9
b101011 *
b1010 "
b1010 +
b101010 %
b101010 -
b101010 3
b101010 6
0$
#435000
1$
#440000
b1011 2
b1011 5
b101100 :
b1100 9
b101100 *
b1011 "
b1011 +
b101011 %
b101011 -
b101011 3
b101011 6
0$
#445000
1$
#450000
b1100 2
b1100 5
b101101 :
b1101 9
b101101 *
b1100 "
b1100 +
b101100 %
b101100 -
b101100 3
b101100 6
0$
#455000
1$
#460000
b1101 2
b1101 5
b101110 :
b1110 9
b101110 *
b1101 "
b1101 +
b101101 %
b101101 -
b101101 3
b101101 6
0$
#465000
1$
#470000
b1110 2
b1110 5
b101111 :
b1111 9
b101111 *
b1110 "
b1110 +
b101110 %
b101110 -
b101110 3
b101110 6
0$
#475000
1$
#480000
b1111 2
b1111 5
b110000 :
b10000 9
b110000 *
b1111 "
b1111 +
b101111 %
b101111 -
b101111 3
b101111 6
0$
#485000
1$
#490000
0,
0.
11
10
b0 2
b0 5
b110001 :
b10001 9
b110001 *
b10000 "
b10000 +
b110000 %
b110000 -
b110000 3
b110000 6
0$
#495000
1$
#500000
b1 2
b1 5
b110010 :
b10010 9
b110010 *
b10001 "
b10001 +
b110001 %
b110001 -
b110001 3
b110001 6
0$
#505000
1$
#510000
b10 2
b10 5
b110011 :
b10011 9
b110011 *
b10010 "
b10010 +
b110010 %
b110010 -
b110010 3
b110010 6
0$
#515000
1$
#520000
b11 2
b11 5
b110100 :
b10100 9
b110100 *
b10011 "
b10011 +
b110011 %
b110011 -
b110011 3
b110011 6
0$
#525000
1$
#530000
b100 2
b100 5
b110101 :
b10101 9
b110101 *
b10100 "
b10100 +
b110100 %
b110100 -
b110100 3
b110100 6
0$
#535000
1$
#540000
b101 2
b101 5
b110110 :
b10110 9
b110110 *
b10101 "
b10101 +
b110101 %
b110101 -
b110101 3
b110101 6
0$
#545000
1$
#550000
b110 2
b110 5
b110111 :
b10111 9
b110111 *
b10110 "
b10110 +
b110110 %
b110110 -
b110110 3
b110110 6
0$
#555000
1$
#560000
b111 2
b111 5
b111000 :
b11000 9
b111000 *
b10111 "
b10111 +
b110111 %
b110111 -
b110111 3
b110111 6
0$
#565000
1$
#570000
b1000 2
b1000 5
b111001 :
b11001 9
b111001 *
b11000 "
b11000 +
b111000 %
b111000 -
b111000 3
b111000 6
0$
#575000
1$
#580000
b1001 2
b1001 5
b111010 :
b11010 9
b111010 *
b11001 "
b11001 +
b111001 %
b111001 -
b111001 3
b111001 6
0$
#585000
1$
#590000
b1010 2
b1010 5
b111011 :
b11011 9
b111011 *
b11010 "
b11010 +
b111010 %
b111010 -
b111010 3
b111010 6
0$
#595000
1$
#600000
b1011 2
b1011 5
b111100 :
b11100 9
b111100 *
b11011 "
b11011 +
b111011 %
b111011 -
b111011 3
b111011 6
0$
#605000
1$
#610000
b1100 2
b1100 5
b111101 :
b11101 9
b111101 *
b11100 "
b11100 +
b111100 %
b111100 -
b111100 3
b111100 6
0$
#615000
1$
#620000
b1101 2
b1101 5
b111110 :
b11110 9
b111110 *
b11101 "
b11101 +
b111101 %
b111101 -
b111101 3
b111101 6
0$
#625000
1$
#630000
b1110 2
b1110 5
b111111 :
b11111 9
b111111 *
b11110 "
b11110 +
b111110 %
b111110 -
b111110 3
b111110 6
0$
#635000
1$
#640000
b1111 2
b1111 5
b1000000 :
b0 9
b1000000 *
b11111 "
b11111 +
b111111 %
b111111 -
b111111 3
b111111 6
0$
#645000
1$
#650000
1,
1.
bx !
bx /
bx 4
bx 7
01
00
b0 2
b0 5
b1000001 :
b1 9
b1000001 *
b0 "
b0 +
b1000000 %
b1000000 -
b1000000 3
b1000000 6
0$
#655000
1$
#660000
b1 2
b1 5
b1000010 :
b10 9
b1000010 *
b1 "
b1 +
b1000001 %
b1000001 -
b1000001 3
b1000001 6
0$
#665000
1$
#670000
b10 2
b10 5
b1000011 :
b11 9
b1000011 *
b10 "
b10 +
b1000010 %
b1000010 -
b1000010 3
b1000010 6
0$
#675000
1$
#680000
b11 2
b11 5
b1000100 :
b100 9
b1000100 *
b11 "
b11 +
b1000011 %
b1000011 -
b1000011 3
b1000011 6
0$
#685000
1$
#690000
b100 2
b100 5
b1000101 :
b101 9
b1000101 *
b100 "
b100 +
b1000100 %
b1000100 -
b1000100 3
b1000100 6
0$
#695000
1$
#700000
b101 2
b101 5
b1000110 :
b110 9
b1000110 *
b101 "
b101 +
b1000101 %
b1000101 -
b1000101 3
b1000101 6
0$
#705000
1$
#710000
b110 2
b110 5
b1000111 :
b111 9
b1000111 *
b110 "
b110 +
b1000110 %
b1000110 -
b1000110 3
b1000110 6
0$
#715000
1$
#720000
b111 2
b111 5
b1001000 :
b1000 9
b1001000 *
b111 "
b111 +
b1000111 %
b1000111 -
b1000111 3
b1000111 6
0$
#725000
1$
#730000
b1000 2
b1000 5
b1001001 :
b1001 9
b1001001 *
b1000 "
b1000 +
b1001000 %
b1001000 -
b1001000 3
b1001000 6
0$
#735000
1$
#740000
b1001 2
b1001 5
b1001010 :
b1010 9
b1001010 *
b1001 "
b1001 +
b1001001 %
b1001001 -
b1001001 3
b1001001 6
0$
#745000
1$
#750000
b1010 2
b1010 5
b1001011 :
b1011 9
b1001011 *
b1010 "
b1010 +
b1001010 %
b1001010 -
b1001010 3
b1001010 6
0$
#755000
1$
#760000
b1011 2
b1011 5
b1001100 :
b1100 9
b1001100 *
b1011 "
b1011 +
b1001011 %
b1001011 -
b1001011 3
b1001011 6
0$
#765000
1$
#770000
b1100 2
b1100 5
b1001101 :
b1101 9
b1001101 *
b1100 "
b1100 +
b1001100 %
b1001100 -
b1001100 3
b1001100 6
0$
#775000
1$
#780000
b1101 2
b1101 5
b1001110 :
b1110 9
b1001110 *
b1101 "
b1101 +
b1001101 %
b1001101 -
b1001101 3
b1001101 6
0$
#785000
1$
#790000
b1110 2
b1110 5
b1001111 :
b1111 9
b1001111 *
b1110 "
b1110 +
b1001110 %
b1001110 -
b1001110 3
b1001110 6
0$
#795000
1$
#800000
b1111 2
b1111 5
b1010000 :
b10000 9
b1010000 *
b1111 "
b1111 +
b1001111 %
b1001111 -
b1001111 3
b1001111 6
0$
#805000
1$
#810000
0,
0.
11
10
b0 2
b0 5
b1010001 :
b10001 9
b1010001 *
b10000 "
b10000 +
b1010000 %
b1010000 -
b1010000 3
b1010000 6
0$
#815000
1$
#820000
b1 2
b1 5
b1010010 :
b10010 9
b1010010 *
b10001 "
b10001 +
b1010001 %
b1010001 -
b1010001 3
b1010001 6
0$
#825000
1$
#830000
b10 2
b10 5
b1010011 :
b10011 9
b1010011 *
b10010 "
b10010 +
b1010010 %
b1010010 -
b1010010 3
b1010010 6
0$
#835000
1$
#840000
b11 2
b11 5
b1010100 :
b10100 9
b1010100 *
b10011 "
b10011 +
b1010011 %
b1010011 -
b1010011 3
b1010011 6
0$
#845000
1$
#850000
b100 2
b100 5
b1010101 :
b10101 9
b1010101 *
b10100 "
b10100 +
b1010100 %
b1010100 -
b1010100 3
b1010100 6
0$
#855000
1$
#860000
b101 2
b101 5
b1010110 :
b10110 9
b1010110 *
b10101 "
b10101 +
b1010101 %
b1010101 -
b1010101 3
b1010101 6
0$
#865000
1$
#870000
b110 2
b110 5
b1010111 :
b10111 9
b1010111 *
b10110 "
b10110 +
b1010110 %
b1010110 -
b1010110 3
b1010110 6
0$
#875000
1$
#880000
b111 2
b111 5
b1011000 :
b11000 9
b1011000 *
b10111 "
b10111 +
b1010111 %
b1010111 -
b1010111 3
b1010111 6
0$
#885000
1$
#890000
b1000 2
b1000 5
b1011001 :
b11001 9
b1011001 *
b11000 "
b11000 +
b1011000 %
b1011000 -
b1011000 3
b1011000 6
0$
#895000
1$
#900000
b1001 2
b1001 5
b1011010 :
b11010 9
b1011010 *
b11001 "
b11001 +
b1011001 %
b1011001 -
b1011001 3
b1011001 6
0$
#905000
1$
#910000
b1010 2
b1010 5
b1011011 :
b11011 9
b1011011 *
b11010 "
b11010 +
b1011010 %
b1011010 -
b1011010 3
b1011010 6
0$
#915000
1$
#920000
b1011 2
b1011 5
b1011100 :
b11100 9
b1011100 *
b11011 "
b11011 +
b1011011 %
b1011011 -
b1011011 3
b1011011 6
0$
#925000
1$
#930000
b1100 2
b1100 5
b1011101 :
b11101 9
b1011101 *
b11100 "
b11100 +
b1011100 %
b1011100 -
b1011100 3
b1011100 6
0$
#935000
1$
#940000
b1101 2
b1101 5
b1011110 :
b11110 9
b1011110 *
b11101 "
b11101 +
b1011101 %
b1011101 -
b1011101 3
b1011101 6
0$
#945000
1$
#950000
b1110 2
b1110 5
b1011111 :
b11111 9
b1011111 *
b11110 "
b11110 +
b1011110 %
b1011110 -
b1011110 3
b1011110 6
0$
#955000
1$
#960000
b1111 2
b1111 5
b1100000 :
b0 9
b1100000 *
b11111 "
b11111 +
b1011111 %
b1011111 -
b1011111 3
b1011111 6
0$
#965000
1$
#970000
1,
1.
bx !
bx /
bx 4
bx 7
01
00
b0 2
b0 5
b1100001 :
b1 9
b1100001 *
b0 "
b0 +
b1100000 %
b1100000 -
b1100000 3
b1100000 6
0$
#975000
1$
#980000
b1 2
b1 5
b1100010 :
b10 9
b1100010 *
b1 "
b1 +
b1100001 %
b1100001 -
b1100001 3
b1100001 6
0$
#985000
1$
#990000
b10 2
b10 5
b1100011 :
b11 9
b1100011 *
b10 "
b10 +
b1100010 %
b1100010 -
b1100010 3
b1100010 6
0$
#995000
1$
#1000000
b11 2
b11 5
b0 8
b0 *
b11 "
b11 +
b1100011 %
b1100011 -
b1100011 3
b1100011 6
0$
#1005000
1$
#1010000
b1100000 !
b1100000 /
b1100000 4
b1100000 7
b0 2
b0 5
b1 8
b1 *
1&
0'
b0 "
b0 +
b101001001000100 (
0$
#1015000
1$
#1020000
b1100001 !
b1100001 /
b1100001 4
b1100001 7
b1 2
b1 5
b10 8
b10 *
b1 "
b1 +
0$
#1025000
1$
#1030000
b1100010 !
b1100010 /
b1100010 4
b1100010 7
b10 2
b10 5
b11 8
b11 *
b10 "
b10 +
0$
#1035000
1$
#1040000
b1100011 !
b1100011 /
b1100011 4
b1100011 7
b11 2
b11 5
b100 8
b100 *
b11 "
b11 +
0$
#1045000
1$
#1050000
b1000100 !
b1000100 /
b1000100 4
b1000100 7
b100 2
b100 5
b101 8
b101 *
b100 "
b100 +
0$
#1055000
1$
#1060000
b1000101 !
b1000101 /
b1000101 4
b1000101 7
b101 2
b101 5
b110 8
b110 *
b101 "
b101 +
0$
#1065000
1$
#1070000
b1000110 !
b1000110 /
b1000110 4
b1000110 7
b110 2
b110 5
b111 8
b111 *
b110 "
b110 +
0$
#1075000
1$
#1080000
b1000111 !
b1000111 /
b1000111 4
b1000111 7
b111 2
b111 5
b1000 8
b1000 *
b111 "
b111 +
0$
#1085000
1$
#1090000
b1001000 !
b1001000 /
b1001000 4
b1001000 7
b1000 2
b1000 5
b1001 8
b1001 *
b1000 "
b1000 +
0$
#1095000
1$
#1100000
b1001001 !
b1001001 /
b1001001 4
b1001001 7
b1001 2
b1001 5
b1010 8
b1010 *
b1001 "
b1001 +
0$
#1105000
1$
#1110000
b1001010 !
b1001010 /
b1001010 4
b1001010 7
b1010 2
b1010 5
b1011 8
b1011 *
b1010 "
b1010 +
0$
#1115000
1$
#1120000
b1001011 !
b1001011 /
b1001011 4
b1001011 7
b1011 2
b1011 5
b1100 8
b1100 *
b1011 "
b1011 +
0$
#1125000
1$
#1130000
b1001100 !
b1001100 /
b1001100 4
b1001100 7
b1100 2
b1100 5
b1101 8
b1101 *
b1100 "
b1100 +
0$
#1135000
1$
#1140000
b1001101 !
b1001101 /
b1001101 4
b1001101 7
b1101 2
b1101 5
b1110 8
b1110 *
b1101 "
b1101 +
0$
#1145000
1$
#1150000
b1001110 !
b1001110 /
b1001110 4
b1001110 7
b1110 2
b1110 5
b1111 8
b1111 *
b1110 "
b1110 +
0$
#1155000
1$
#1160000
b1001111 !
b1001111 /
b1001111 4
b1001111 7
b1111 2
b1111 5
b10000 8
b10000 *
b1111 "
b1111 +
0$
#1165000
1$
#1170000
0,
0.
b1010000 !
b1010000 /
b1010000 4
b1010000 7
11
10
b0 2
b0 5
b10001 8
b10001 *
b10000 "
b10000 +
0$
#1175000
1$
#1180000
b1010001 !
b1010001 /
b1010001 4
b1010001 7
b1 2
b1 5
b10010 8
b10010 *
b10001 "
b10001 +
0$
#1185000
1$
#1190000
b1010010 !
b1010010 /
b1010010 4
b1010010 7
b10 2
b10 5
b10011 8
b10011 *
b10010 "
b10010 +
0$
#1195000
1$
#1200000
b1010011 !
b1010011 /
b1010011 4
b1010011 7
b11 2
b11 5
b10100 8
b10100 *
b10011 "
b10011 +
0$
#1205000
1$
#1210000
b1010100 !
b1010100 /
b1010100 4
b1010100 7
b100 2
b100 5
b10101 8
b10101 *
b10100 "
b10100 +
0$
#1215000
1$
#1220000
b1010101 !
b1010101 /
b1010101 4
b1010101 7
b101 2
b101 5
b10110 8
b10110 *
b10101 "
b10101 +
0$
#1225000
1$
#1230000
b1010110 !
b1010110 /
b1010110 4
b1010110 7
b110 2
b110 5
b10111 8
b10111 *
b10110 "
b10110 +
0$
#1235000
1$
#1240000
b1010111 !
b1010111 /
b1010111 4
b1010111 7
b111 2
b111 5
b11000 8
b11000 *
b10111 "
b10111 +
0$
#1245000
1$
#1250000
b1011000 !
b1011000 /
b1011000 4
b1011000 7
b1000 2
b1000 5
b11001 8
b11001 *
b11000 "
b11000 +
0$
#1255000
1$
#1260000
b1011001 !
b1011001 /
b1011001 4
b1011001 7
b1001 2
b1001 5
b11010 8
b11010 *
b11001 "
b11001 +
0$
#1265000
1$
#1270000
b1011010 !
b1011010 /
b1011010 4
b1011010 7
b1010 2
b1010 5
b11011 8
b11011 *
b11010 "
b11010 +
0$
#1275000
1$
#1280000
b1011011 !
b1011011 /
b1011011 4
b1011011 7
b1011 2
b1011 5
b11100 8
b11100 *
b11011 "
b11011 +
0$
#1285000
1$
#1290000
b1011100 !
b1011100 /
b1011100 4
b1011100 7
b1100 2
b1100 5
b11101 8
b11101 *
b11100 "
b11100 +
0$
#1295000
1$
#1300000
b1011101 !
b1011101 /
b1011101 4
b1011101 7
b1101 2
b1101 5
b11110 8
b11110 *
b11101 "
b11101 +
0$
#1305000
1$
#1310000
b1011110 !
b1011110 /
b1011110 4
b1011110 7
b1110 2
b1110 5
b11111 8
b11111 *
b11110 "
b11110 +
0$
#1315000
1$
#1320000
b1011111 !
b1011111 /
b1011111 4
b1011111 7
b1111 2
b1111 5
b0 8
b100000 *
b11111 "
b11111 +
0$
#1325000
1$
#1330000
1,
1.
b1100000 !
b1100000 /
b1100000 4
b1100000 7
01
00
b0 2
b0 5
b1 8
b100001 *
b0 "
b0 +
0$
#1335000
1$
#1340000
b1100001 !
b1100001 /
b1100001 4
b1100001 7
b1 2
b1 5
b10 8
b100010 *
b1 "
b1 +
0$
#1345000
1$
#1350000
b1100010 !
b1100010 /
b1100010 4
b1100010 7
b10 2
b10 5
b11 8
b100011 *
b10 "
b10 +
0$
#1355000
1$
#1360000
b1100011 !
b1100011 /
b1100011 4
b1100011 7
b11 2
b11 5
b100 8
b100100 *
b11 "
b11 +
0$
#1365000
1$
#1370000
b1000100 !
b1000100 /
b1000100 4
b1000100 7
b100 2
b100 5
b101 8
b100101 *
b100 "
b100 +
0$
#1375000
1$
#1380000
b1000101 !
b1000101 /
b1000101 4
b1000101 7
b101 2
b101 5
b110 8
b100110 *
b101 "
b101 +
0$
#1385000
1$
#1390000
b1000110 !
b1000110 /
b1000110 4
b1000110 7
b110 2
b110 5
b111 8
b100111 *
b110 "
b110 +
0$
#1395000
1$
#1400000
b1000111 !
b1000111 /
b1000111 4
b1000111 7
b111 2
b111 5
b1000 8
b101000 *
b111 "
b111 +
0$
#1405000
1$
#1410000
b1001000 !
b1001000 /
b1001000 4
b1001000 7
b1000 2
b1000 5
b1001 8
b101001 *
b1000 "
b1000 +
0$
#1415000
1$
#1420000
b1001001 !
b1001001 /
b1001001 4
b1001001 7
b1001 2
b1001 5
b1010 8
b101010 *
b1001 "
b1001 +
0$
#1425000
1$
#1430000
b1001010 !
b1001010 /
b1001010 4
b1001010 7
b1010 2
b1010 5
b1011 8
b101011 *
b1010 "
b1010 +
0$
#1435000
1$
#1440000
b1001011 !
b1001011 /
b1001011 4
b1001011 7
b1011 2
b1011 5
b1100 8
b101100 *
b1011 "
b1011 +
0$
#1445000
1$
#1450000
b1001100 !
b1001100 /
b1001100 4
b1001100 7
b1100 2
b1100 5
b1101 8
b101101 *
b1100 "
b1100 +
0$
#1455000
1$
