w3_sequential_logic/fsm/seq_detect_moore.v
module seq_detect_moore(
    input           i_clk,
    input           i_rstn,
    input           i_seq,
    output  reg     o_out
);

reg [1:0] CurrentState;
reg [1:0] NextState;
reg       seq;

//-----------------------------------------
// State
//-----------------------------------------
localparam IDLE = 2'b00;
localparam LOW  = 2'b01;
localparam HIGH = 2'b10;

always @(posedge i_clk or negedge i_rstn) begin
    if(!i_rstn) begin
        CurrentState <= IDLE;
        seq <= 1'b0;
    end
    else begin
        CurrentState <= NextState;
        seq <= i_seq; // i_seq 1clk delay
    end
end

always @(*) begin
    if(seq == 1'b0) begin
        case (CurrentState)
            IDLE    : NextState = LOW;
            LOW     : NextState = LOW;
            HIGH    : NextState = LOW;
            default : NextState = IDLE; 
        endcase
    end
    else begin
        case (CurrentState)
            IDLE    : NextState = IDLE;
            LOW     : NextState = HIGH;
            HIGH    : NextState = IDLE; 
            default : NextState = IDLE; 
        endcase
    end
end

always @(*) begin
    case (CurrentState)
        HIGH    : o_out = 1'b1; 
        default : o_out = 1'b0; 
    endcase
end

endmodule

projects/w3_sequential_logic/fsm/seq_detect_moore_tb.v
`define     CLKFREQ     100
`define     SIMCYCLE    10

`include "seq_detect_moore.v"

module seq_detect_moore_tb;
//---------------------------------------------------
// DUT Signals & Instantiate
//---------------------------------------------------

reg           i_clk;
reg           i_rstn;
reg           i_seq;
wire          o_out;


seq_detect_moore 
u_seq_detect_moore(
    .i_clk  ( i_clk ),
    .i_rstn ( i_rstn),
    .i_seq  ( i_seq ),
    .o_out  ( o_out )
);

//---------------------------------------------------
// Clock
//---------------------------------------------------
always #(500/`CLKFREQ) i_clk = ~i_clk;

//---------------------------------------------------
// Tasks
//---------------------------------------------------
task init;
    begin
        i_clk = 0;
        i_rstn = 0;
        i_seq = 0;
        #(100/`CLKFREQ);
        i_rstn = 1'b1;
    end
endtask

//---------------------------------------------------
// Test Stimulus
//---------------------------------------------------
integer  i, j;
initial begin
    init();
    for(i = 0; i < `SIMCYCLE; i++) begin
        j       = $urandom_range(0, 10);
        #((  (j*0.1)) * 1000/`CLKFREQ);
        i_seq   = $urandom;
        #((1-(j*0.1)) * 1000/`CLKFREQ);
    end
    $finish;
end

//---------------------------------------------------
// Dump VCD
//---------------------------------------------------

reg [8*32-1:0] vcd_file;
initial begin
    if($value$plusargs("vcd_file=%s", vcd_file)) begin
        $dumpfile(vcd_file);
        $dumpvars;
    end
    else begin
        $dumpfile("seq_detect_moore_tb.vcd");
        $dumpvars;     
    end
end

endmodule

projects/w3_sequential_logic/fsm/vcd/seq_detect_moore.vcd
$date
	Wed Jun 26 15:29:31 2024
$end
$version
	Icarus Verilog
$end
$timescale
	1ps
$end
$scope module seq_detect_moore_tb $end
$var wire 1 ! o_out $end
$var reg 1 " i_clk $end
$var reg 1 # i_rstn $end
$var reg 1 $ i_seq $end
$var reg 256 % vcd_file [255:0] $end
$var integer 32 & i [31:0] $end
$var integer 32 ' j [31:0] $end
$scope module u_seq_detect_moore $end
$var wire 1 " i_clk $end
$var wire 1 # i_rstn $end
$var wire 1 $ i_seq $end
$var reg 2 ( CurrentState [1:0] $end
$var reg 2 ) NextState [1:0] $end
$var reg 1 ! o_out $end
$var reg 1 * seq $end
$upscope $end
$scope task init $end
$upscope $end
$upscope $end
$enddefinitions $end
#0
$dumpvars
0*
b1 )
b0 (
bx '
bx &
b10111000101111011101100110001101100100001011110111001101100101011100010101111101100100011001010111010001100101011000110111010001011111011011010110111101101111011100100110010100101110011101100110001101100100 %
0$
0#
0"
0!
$end
#1000
b110 '
b0 &
1#
#5000
b1 (
1"
#7000
1$
#10000
0"
#11000
b0 '
b1 &
#15000
b10 )
1*
1"
#20000
0"
#21000
b101 '
b10 &
#25000
1!
b0 )
b10 (
1"
#30000
0"
#31000
b10 '
b11 &
#33000
0$
#35000
0!
b1 )
0*
b0 (
1"
#40000
0"
#41000
b101 '
b100 &
#45000
b1 (
1"
#46000
1$
#50000
0"
#51000
b1000 '
b101 &
#55000
b10 )
1*
1"
#60000
0"
#61000
b1010 '
b110 &
#65000
1!
b0 )
b10 (
1"
#70000
0"
#71000
b111 &
0$
#75000
0!
b1 )
0*
b0 (
1"
#80000
0"
#81000
b100 '
b1000 &
#85000
b1 (
1"
#90000
0"
#91000
b1010 '
b1001 &
#95000
1"
#100000
0"
#101000
b1010 &
1$
