project_0/04_shift_register/shift_register.v
module shift_register(
	input				i_clk,
	input				i_rstn,
	input				i_load,
	input		[7:0]	i_d,
	input 				i_s,
	output		[7:0]	o_q,	
	output				o_s
);

	wire		[7:0] 	w_out;

	mux2to1
	u_mux2to1_0(
		.i_sel				(i_load				),
		.i_data0			(i_s				),
		.i_data1			(i_d[0]				),
		.o_data				(w_out[0]			)
	);

	dff
	u_dff0(
		.i_clk				(i_clk				),
		.i_rstn				(i_rstn				),
		.i_data				(w_out[0]			),
		.o_data				(o_q[0]				)
	);

genvar i;
generate
	for(i = 0; i < 7; i = i + 1) begin
	mux2to1
	u_mux2to1(
		.i_sel				(i_load				),
		.i_data0			(o_q[i]				),
		.i_data1			(i_d[i+1]			),
		.o_data				(w_out[i+1]			)
	);
		dff
	u_dff(
		.i_clk				(i_clk				),
		.i_rstn				(i_rstn				),
		.i_data				(w_out[i+1]			),
		.o_data				(o_q[i+1]			)
	);
end
endgenerate

	assign o_s = o_q[7];

endmodule


module mux2to1(
	input		i_sel,
	input		i_data0,
	input		i_data1,
	output		o_data
);

assign o_data = (i_sel) ? i_data1 : i_data0;

endmodule

module dff(
	input			i_clk,
	input			i_rstn,
	input			i_data,
	output reg		o_data
);

always @(posedge i_clk or negedge i_rstn) begin
	if(!i_rstn) begin
		o_data <= 0;
	end
	else begin
		o_data <= i_data;
	end
end

endmodule

project_0/04_shift_register/shift_register_tb.v
//-------------------------------------
// Define Global Variables
// ------------------------------------
`define CLKFREQ     100
`define SIMCYCLE    100

`include "shift_register.v"

module shift_register_tb;
//---------------------------------------------------
//DUT Signals & Instantiate
//---------------------------------------------------
	reg					i_clk;
	reg					i_rstn;
	reg					i_load;
	reg			[7:0]	i_d;
	reg 				i_s;
	wire		[7:0]	o_q;	
	wire				o_s;

	shift_register
	u_shift_register(
		.i_clk				(i_clk				),
		.i_rstn				(i_rstn				),
		.i_load				(i_load				),
		.i_d				(i_d				),
		.i_s				(i_s				),
		.o_q				(o_q				),
		.o_s				(o_s				)
	);

//---------------------------------------------------
// Clock
//---------------------------------------------------
always #(500/`CLKFREQ) i_clk = ~i_clk;

//---------------------------------------------------
// Tasks
//---------------------------------------------------
reg     [8*32-1:0]  taskState;

task init;
    begin
		taskState 	= "Init";
		i_clk		= 0;
		i_rstn		= 0;
		i_load		= 0;
		i_d			= 0;
		i_s			= 0;
		repeat (4) @(posedge i_clk);
		i_rstn		= 1;
    end
endtask

integer i;

task PISO;
	input 	[7:0] d;
	begin
		taskState = "PISO";
		i_load = 1;
		i_d = d;
		@(posedge i_clk);
		i_load = 0;
		repeat(7) @(posedge i_clk);
	end
endtask

task SIPO;
	input 	[7:0] d;
	begin
		taskState = "SIPO";
		i_load = 0;
		for(i = 0; i < 8; i = i + 1) begin
			i_s = d[7-i];
			@(posedge i_clk);
		end
		i_s = 0;
		@(posedge i_clk);
	end
endtask


//---------------------------------------------------
//Stimulus
//---------------------------------------------------
integer j;

reg		[7:0]	d;

initial begin
	init();
	for (j=0; j<`SIMCYCLE; j++) begin
		i_d = $urandom;
		d	= 0;
		PISO(i_d);
		@(posedge i_clk);
		i_d = 0;
		d	= $urandom;
		SIPO(d);
	end
	#(1000/`CLKFREQ);
	$finish;
end

// --------------------------------------------------
//	Dump VCD
// --------------------------------------------------
	reg	[8*32-1:0]	vcd_file;
	initial begin
		if ($value$plusargs("vcd_file=%s", vcd_file)) begin
			$dumpfile(vcd_file);
			$dumpvars;
		end else begin
			$dumpfile("shift_register_tb.vcd");
			$dumpvars;
		end
	end

endmodule

project_0/04_shift_register/vcd/shift_register.vcd
$date
	Mon Jul  1 16:55:57 2024
$end
$version
	Icarus Verilog
$end
$timescale
	1ps
$end
$scope module shift_register_tb $end
$var wire 1 ! o_s $end
$var wire 8 " o_q [7:0] $end
$var reg 8 # d [7:0] $end
$var reg 1 $ i_clk $end
$var reg 8 % i_d [7:0] $end
$var reg 1 & i_load $end
$var reg 1 ' i_rstn $end
$var reg 1 ( i_s $end
$var reg 256 ) taskState [255:0] $end
$var reg 256 * vcd_file [255:0] $end
$var integer 32 + i [31:0] $end
$var integer 32 , j [31:0] $end
$scope module u_shift_register $end
$var wire 1 $ i_clk $end
$var wire 8 - i_d [7:0] $end
$var wire 1 & i_load $end
$var wire 1 ' i_rstn $end
$var wire 1 ( i_s $end
$var wire 8 . w_out [7:0] $end
$var wire 1 ! o_s $end
$var wire 8 / o_q [7:0] $end
$scope begin genblk1[0] $end
$scope module u_dff $end
$var wire 1 $ i_clk $end
$var wire 1 0 i_data $end
$var wire 1 ' i_rstn $end
$var reg 1 1 o_data $end
$upscope $end
$scope module u_mux2to1 $end
$var wire 1 2 i_data0 $end
$var wire 1 3 i_data1 $end
$var wire 1 & i_sel $end
$var wire 1 4 o_data $end
$upscope $end
$upscope $end
$scope begin genblk1[1] $end
$scope module u_dff $end
$var wire 1 $ i_clk $end
$var wire 1 5 i_data $end
$var wire 1 ' i_rstn $end
$var reg 1 6 o_data $end
$upscope $end
$scope module u_mux2to1 $end
$var wire 1 7 i_data0 $end
$var wire 1 8 i_data1 $end
$var wire 1 & i_sel $end
$var wire 1 9 o_data $end
$upscope $end
$upscope $end
$scope begin genblk1[2] $end
$scope module u_dff $end
$var wire 1 $ i_clk $end
$var wire 1 : i_data $end
$var wire 1 ' i_rstn $end
$var reg 1 ; o_data $end
$upscope $end
$scope module u_mux2to1 $end
$var wire 1 < i_data0 $end
$var wire 1 = i_data1 $end
$var wire 1 & i_sel $end
$var wire 1 > o_data $end
$upscope $end
$upscope $end
$scope begin genblk1[3] $end
$scope module u_dff $end
$var wire 1 $ i_clk $end
$var wire 1 ? i_data $end
$var wire 1 ' i_rstn $end
$var reg 1 @ o_data $end
$upscope $end
$scope module u_mux2to1 $end
$var wire 1 A i_data0 $end
$var wire 1 B i_data1 $end
$var wire 1 & i_sel $end
$var wire 1 C o_data $end
$upscope $end
$upscope $end
$scope begin genblk1[4] $end
$scope module u_dff $end
$var wire 1 $ i_clk $end
$var wire 1 D i_data $end
$var wire 1 ' i_rstn $end
$var reg 1 E o_data $end
$upscope $end
$scope module u_mux2to1 $end
$var wire 1 F i_data0 $end
$var wire 1 G i_data1 $end
$var wire 1 & i_sel $end
$var wire 1 H o_data $end
$upscope $end
$upscope $end
$scope begin genblk1[5] $end
$scope module u_dff $end
$var wire 1 $ i_clk $end
$var wire 1 I i_data $end
$var wire 1 ' i_rstn $end
$var reg 1 J o_data $end
$upscope $end
$scope module u_mux2to1 $end
$var wire 1 K i_data0 $end
$var wire 1 L i_data1 $end
$var wire 1 & i_sel $end
$var wire 1 M o_data $end
$upscope $end
$upscope $end
$scope begin genblk1[6] $end
$scope module u_dff $end
$var wire 1 $ i_clk $end
$var wire 1 N i_data $end
$var wire 1 ' i_rstn $end
$var reg 1 O o_data $end
$upscope $end
$scope module u_mux2to1 $end
$var wire 1 P i_data0 $end
$var wire 1 Q i_data1 $end
$var wire 1 & i_sel $end
$var wire 1 R o_data $end
$upscope $end
$upscope $end
$scope module u_dff0 $end
$var wire 1 $ i_clk $end
$var wire 1 S i_data $end
$var wire 1 ' i_rstn $end
$var reg 1 T o_data $end
$upscope $end
$scope module u_mux2to1_0 $end
$var wire 1 ( i_data0 $end
$var wire 1 U i_data1 $end
$var wire 1 & i_sel $end
$var wire 1 V o_data $end
$upscope $end
$upscope $end
$scope task PISO $end
$var reg 8 W d [7:0] $end
$upscope $end
$scope task SIPO $end
$var reg 8 X d [7:0] $end
$upscope $end
$scope task init $end
$upscope $end
$upscope $end
$enddefinitions $end
#0
$dumpvars
bx X
bx W
0V
0U
0T
0S
0R
0Q
0P
0O
0N
0M
0L
0K
0J
0I
0H
0G
0F
0E
0D
0C
0B
0A
0@
0?
0>
0=
0<
0;
0:
09
08
07
06
05
04
03
02
01
00
b0 /
b0 .
b0 -
bx ,
bx +
b1011100010111101110110011000110110010000101111011100110110100001101001011001100111010001011111011100100110010101100111011010010111001101110100011001010111001000101110011101100110001101100100 *
b1001001011011100110100101110100 )
0(
0'
0&
b0 %
0$
bx #
b0 "
0!
$end
#5000
1$
#10000
0$
#15000
1$
#20000
0$
#25000
1$
#30000
0$
#35000
15
1D
19
b100100 .
1H
18
1G
1&
b1010000010010010101001101001111 )
b100100 W
b0 #
b100100 %
b100100 -
b0 ,
1'
1$
#40000
0$
#45000
1I
1:
1M
1>
1K
1<
1E
b100100 "
b100100 /
16
05
0D
09
b1001000 .
0H
0&
1$
#50000
0$
#55000
0:
1?
0I
1N
0>
1C
0M
b10010000 .
1R
0<
1A
0K
1P
06
1;
0E
b1001000 "
b1001000 /
1J
1$
#60000
0$
#65000
0N
1D
0?
0R
1H
b100000 .
0C
1!
0P
1F
0A
1O
0J
1@
b10010000 "
b10010000 /
0;
1$
#70000
0$
#75000
0D
1I
0H
b1000000 .
1M
0F
1K
0!
0@
1E
b100000 "
b100000 /
0O
1$
#80000
0$
#85000
1N
0I
1R
b10000000 .
0M
1P
0K
1J
b1000000 "
b1000000 /
0E
1$
#90000
0$
#95000
0N
b0 .
0R
0P
1!
0J
b10000000 "
b10000000 /
1O
1$
#100000
0$
#105000
0!
b0 "
b0 /
0O
1$
#110000
0$
#115000
1$
#120000
0$
#125000
1S
b1 .
1V
08
0G
1(
b0 +
b1010011010010010101000001001111 )
b10000001 X
b10000001 #
b0 %
b0 -
1$
#130000
0$
#135000
10
14
12
b1 "
b1 /
1T
0S
b10 .
0V
0(
b1 +
1$
#140000
0$
#145000
00
15
04
b100 .
19
02
17
0T
b10 "
b10 /
11
b10 +
1$
#150000
0$
#155000
05
1:
09
b1000 .
1>
07
1<
01
b100 "
b100 /
16
b11 +
1$
#160000
0$
#165000
1?
0:
1C
b10000 .
0>
1A
0<
1;
b1000 "
b1000 /
06
b100 +
1$
#170000
0$
#175000
0?
1D
0C
b100000 .
1H
0A
1F
0;
b10000 "
b10000 /
1@
b101 +
1$
#180000
0$
#185000
1I
0D
1M
b1000000 .
0H
1K
0F
1E
b100000 "
b100000 /
0@
b110 +
1$
#190000
0$
#195000
0I
1N
0M
1R
0K
1P
0E
b1000000 "
b1000000 /
1J
1S
b10000001 .
1V
1(
b111 +
1$
#200000
0$
#205000
10
0N
14
0R
12
1!
0P
1T
1O
b10000001 "
b10000001 /
0J
0S
b10 .
0V
0(
b1000 +
1$
#210000
0$
#215000
17
0!
02
11
0O
b10 "
b10 /
0T
00
1:
1S
04
1>
b1001 .
1V
1=
1U
1&
b1010000010010010101001101001111 )
b1001 W
b0 #
b1001 %
b1001 -
b1 ,
1$
#220000
0$
#225000
10
1?
14
1C
12
1A
07
1T
1;
b1001 "
b1001 /
01
05
0:
0S
09
0>
b10010 .
0V
0&
1$
#230000
0$
#235000
15
0?
1D
00
19
0C
1H
b100100 .
04
17
0A
1F
02
11
0;
1@
b10010 "
b10010 /
0T
1$
#240000
0$
#245000
1I
0D
1:
05
1M
0H
1>
b1001000 .
09
1K
0F
1<
07
1E
0@
16
b100100 "
b100100 /
01
1$
#250000
0$
#255000
0:
1?
0I
1N
0>
1C
0M
b10010000 .
1R
0<
1A
0K
1P
06
1;
0E
b1001000 "
b1001000 /
1J
1$
#260000
0$
#265000
0N
1D
0?
0R
1H
b100000 .
0C
1!
0P
1F
0A
1O
0J
1@
b10010000 "
b10010000 /
0;
1$
#270000
0$
#275000
0D
1I
0H
b1000000 .
1M
0F
1K
0!
0@
1E
b100000 "
b100000 /
0O
1$
#280000
0$
#285000
1N
0I
1R
b10000000 .
0M
1P
0K
1J
b1000000 "
b1000000 /
0E
1$
#290000
0$
#295000
0N
b0 .
0R
0P
1!
0J
b10000000 "
b10000000 /
1O
1$
#300000
0$
#305000
0!
b0 "
b0 /
0O
0=
0U
b0 +
b1010011010010010101000001001111 )
b1100011 X
b1100011 #
b0 %
b0 -
1$
#310000
0$
#315000
1S
b1 .
1V
1(
b1 +
1$
#320000
0$
#325000
10
b11 .
14
12
b1 "
b1 /
1T
b10 +
1$
#330000
0$
#335000
15
19
17
b11 "
b11 /
11
0S
b110 .
0V
0(
b11 +
1$
#340000
0$
#345000
00
1:
04
b1100 .
1>
02
1<
0T
b110 "
b110 /
16
b100 +
1$
#350000
0$
#355000
05
1?
09
b11000 .
1C
07
1A
01
b1100 "
b1100 /
1;
b101 +
1$
#360000
0$
#365000
1D
0:
1H
0>
1F
0<
1@
b11000 "
b11000 /
06
1S
b110001 .
1V
1(
b110 +
1$
#370000
0$
#375000
0?
1I
10
0C
1M
b1100011 .
14
0A
1K
12
0;
1E
b110001 "
b110001 /
1T
b111 +
1$
#380000
0$
#385000
1N
0D
15
1R
0H
19
1P
0F
17
1J
0@
b1100011 "
b1100011 /
11
0S
b11000110 .
0V
0(
b1000 +
1$
#390000
0$
#395000
1<
0K
1!
02
16
0E
1O
b11000110 "
b11000110 /
0T
00
1:
0I
0N
1S
04
1>
0M
0R
b1101 .
1V
18
1=
1U
1&
b1010000010010010101001101001111 )
b1101 W
b0 #
b1101 %
b1101 -
b10 ,
1$
#400000
0$
#405000
10
1?
05
14
1C
09
12
0!
0P
1A
07
1T
0O
0J
1;
b1101 "
b1101 /
01
0N
0S
0R
b11010 .
0V
0&
1$
#410000
0$
#415000
15
0:
1D
00
19
0>
1H
b110100 .
04
17
0<
1F
02
11
06
1@
b11010 "
b11010 /
0T
1$
#420000
0$
#425000
1I
0?
1:
05
1M
0C
1>
b1101000 .
09
1K
0A
1<
07
1E
0;
16
b110100 "
b110100 /
01
1$
#430000
0$
#435000
0:
1?
0D
1N
0>
1C
0H
b11010000 .
1R
0<
1A
0F
1P
06
1;
0@
b1101000 "
b1101000 /
1J
1$
#440000
0$
#445000
0I
1D
0?
0M
1H
b10100000 .
0C
1!
0K
1F
0A
1O
0E
1@
b11010000 "
b11010000 /
0;
1$
#450000
0$
#455000
0D
1I
0N
0H
1M
b1000000 .
0R
0F
1K
0P
0@
1E
b10100000 "
b10100000 /
0J
1$
#460000
0$
#465000
1N
0I
1R
b10000000 .
0M
0!
1P
0K
0O
1J
b1000000 "
b1000000 /
0E
1$
#470000
0$
#475000
0N
b0 .
0R
0P
1!
0J
b10000000 "
b10000000 /
1O
1$
#480000
0$
#485000
0!
b0 "
b0 /
0O
1S
b1 .
1V
08
0=
0U
1(
b0 +
b1010011010010010101000001001111 )
b10001101 X
b10001101 #
b0 %
b0 -
1$
#490000
0$
#495000
10
14
12
b1 "
b1 /
1T
0S
b10 .
0V
0(
b1 +
1$
#500000
0$
#505000
00
15
04
b100 .
19
02
17
0T
b10 "
b10 /
11
b10 +
1$
#510000
0$
#515000
05
1:
09
b1000 .
1>
07
1<
01
b100 "
b100 /
16
b11 +
1$
#520000
0$
#525000
1?
0:
1C
0>
1A
0<
1;
b1000 "
b1000 /
06
1S
b10001 .
1V
1(
b100 +
1$
#530000
0$
#535000
0?
1D
10
0C
1H
b100011 .
14
0A
1F
12
0;
1@
b10001 "
b10001 /
1T
b101 +
1$
#540000
0$
#545000
1I
0D
15
1M
0H
19
1K
0F
17
1E
0@
b100011 "
b100011 /
11
0S
b1000110 .
0V
0(
b110 +
1$
#550000
0$
#555000
1:
0I
1N
00
1>
0M
1R
04
1<
0K
1P
02
16
0E
1J
b1000110 "
b1000110 /
0T
1S
b10001101 .
1V
1(
b111 +
1$
#560000
0$
#565000
10
0N
1?
05
14
0R
1C
09
12
1!
0P
1A
07
1T
1O
0J
1;
b10001101 "
b10001101 /
01
0S
b11010 .
0V
0(
b1000 +
1$
#570000
0$
#575000
17
0<
1F
0!
02
11
06
1@
0O
b11010 "
b11010 /
0T
00
15
0:
0?
1D
1I
1S
04
19
0>
0C
1H
1M
b1100101 .
1V
18
1G
1L
1U
1&
b1010000010010010101001101001111 )
b1100101 W
b0 #
b1100101 %
b1100101 -
b11 ,
1$
#580000
0$
#585000
10
1N
0D
1:
05
14
1R
0H
1>
09
12
1P
1K
0F
0A
1<
07
1T
1J
1E
0@
0;
16
b1100101 "
b1100101 /
01
0?
1I
0S
0C
1M
b11001010 .
0V
0&
1$
#590000
0$
#595000
15
0:
1?
0I
00
19
0>
1C
0M
b10010100 .
04
17
0<
1A
0K
1!
02
11
06
1;
0E
1O
b11001010 "
b11001010 /
0T
1$
#600000
0$
#605000
0N
1D
0?
1:
05
0R
1H
0C
1>
b101000 .
09
0P
1F
0A
1<
07
0J
1@
0;
16
b10010100 "
b10010100 /
01
1$
#610000
0$
#615000
0:
1?
0D
1I
0>
1C
0H
b1010000 .
1M
0<
1A
0F
1K
0!
06
1;
0@
1E
b101000 "
b101000 /
0O
1$
#620000
0$
#625000
1N
0I
1D
0?
1R
0M
1H
b10100000 .
0C
1P
0K
1F
0A
1J
0E
1@
b1010000 "
b1010000 /
0;
1$
#630000
0$
#635000
0D
1I
0N
0H
1M
b1000000 .
0R
0F
1K
0P
1!
0@
1E
0J
b10100000 "
b10100000 /
1O
1$
#640000
0$
#645000
1N
0I
1R
b10000000 .
0M
0!
1P
0K
0O
1J
b1000000 "
b1000000 /
0E
1$
#650000
0$
#655000
0N
b0 .
0R
0P
1!
0J
b10000000 "
b10000000 /
1O
1$
#660000
0$
#665000
0!
b0 "
b0 /
0O
08
0G
0L
0U
b0 +
b1010011010010010101000001001111 )
b10010 X
b10010 #
b0 %
b0 -
1$
#670000
0$
#675000
b1 +
1$
#680000
0$
#685000
b10 +
1$
#690000
0$
#695000
1S
b1 .
1V
1(
b11 +
1$
#700000
0$
#705000
10
14
12
b1 "
b1 /
1T
0S
b10 .
0V
0(
b100 +
1$
#710000
0$
#715000
15
00
19
b100 .
04
17
02
11
b10 "
b10 /
0T
b101 +
1$
#720000
0$
#725000
1:
05
1>
09
1<
07
16
b100 "
b100 /
01
1S
b1001 .
1V
1(
b110 +
1$
#730000
0$
#735000
0:
1?
10
0>
1C
14
0<
1A
12
06
1;
b1001 "
b1001 /
1T
0S
b10010 .
0V
0(
b111 +
1$
#740000
0$
#745000
00
1D
0?
15
04
1H
0C
b100100 .
19
02
1F
0A
17
0T
1@
0;
b10010 "
b10010 /
11
b1000 +
1$
#750000
0$
#755000
07
1<
0F
1K
01
16
0@
b100100 "
b100100 /
1E
05
0D
1S
09
0H
b1 .
1V
1U
1&
b1010000010010010101001101001111 )
b1 W
b0 #
b1 %
b1 -
b100 ,
1$
#760000
0$
#765000
10
14
12
0K
0<
1T
0E
b1 "
b1 /
06
0:
0I
0S
0>
0M
b10 .
0V
0&
1$
#770000
0$
#775000
15
00
19
b100 .
04
17
02
11
b10 "
b10 /
0T
1$
#780000
0$
#785000
1:
05
1>
b1000 .
09
1<
07
16
b100 "
b100 /
01
1$
#790000
0$
#795000
0:
1?
0>
b10000 .
1C
0<
1A
06
b1000 "
b1000 /
1;
1$
#800000
0$
#805000
1D
0?
1H
b100000 .
0C
1F
0A
1@
b10000 "
b10000 /
0;
1$
#810000
0$
#815000
0D
1I
0H
b1000000 .
1M
0F
1K
0@
b100000 "
b100000 /
1E
1$
#820000
0$
#825000
1N
0I
1R
b10000000 .
0M
1P
0K
1J
b1000000 "
b1000000 /
0E
1$
#830000
0$
#835000
0N
b0 .
0R
0P
1!
0J
b10000000 "
b10000000 /
1O
1$
#840000
0$
#845000
0!
b0 "
b0 /
0O
0U
b0 +
b1010011010010010101000001001111 )
b1101 X
b1101 #
b0 %
b0 -
1$
#850000
0$
#855000
b1 +
1$
#860000
0$
#865000
b10 +
1$
#870000
0$
#875000
b11 +
1$
#880000
0$
#885000
1S
b1 .
1V
1(
b100 +
1$
#890000
0$
#895000
10
b11 .
14
12
b1 "
b1 /
1T
b101 +
1$
#900000
0$
#905000
15
19
17
b11 "
b11 /
11
0S
b110 .
0V
0(
b110 +
1$
#910000
0$
#915000
1:
00
1>
04
1<
02
16
b110 "
b110 /
0T
1S
b1101 .
1V
1(
b111 +
1$
#920000
0$
#925000
10
1?
05
14
1C
09
12
1A
07
1T
1;
b1101 "
b1101 /
01
0S
b11010 .
0V
0(
b1000 +
1$
#930000
0$
#935000
17
0<
1F
02
11
06
1@
b11010 "
b11010 /
0T
15
0:
1D
1I
19
0>
1H
b1110110 .
1M
13
18
1B
1G
1L
1&
b1010000010010010101001101001111 )
b1110110 W
b0 #
b1110110 %
b1110110 -
b101 ,
1$
#940000
0$
#945000
1N
0?
1:
1R
0C
1>
1P
1K
0A
1<
1J
1E
0;
b1110110 "
b1110110 /
16
00
1I
04
b11101100 .
1M
0&
1$
#950000
0$
#955000
05
1?
0D
09
1C
b11011000 .
0H
07
1A
0F
1!
01
1;
0@
b11101100 "
b11101100 /
1O
1$
#960000
0$
#965000
0I
1D
0:
0M
1H
b10110000 .
0>
0K
1F
0<
0E
1@
b11011000 "
b11011000 /
06
1$
#970000
0$
#975000
0?
1I
0N
0C
1M
b1100000 .
0R
0A
1K
0P
0;
1E
b10110000 "
b10110000 /
0J
1$
#980000
0$
#985000
1N
0D
1R
b11000000 .
0H
0!
1P
0F
0O
1J
b1100000 "
b1100000 /
0@
1$
#990000
0$
#995000
0I
b10000000 .
0M
0K
1!
0E
b11000000 "
b11000000 /
1O
1$
#1000000
0$
#1005000
0N
b0 .
0R
0P
b10000000 "
b10000000 /
0J
1$
#1010000
0$
#1015000
0!
b0 "
b0 /
0O
1$
#1020000
0$
#1025000
03
08
0B
0G
0L
b0 +
b1010011010010010101000001001111 )
b111101 X
b111101 #
b0 %
b0 -
1$
#1030000
0$
#1035000
b1 +
1$
#1040000
0$
#1045000
1S
b1 .
1V
1(
b10 +
1$
#1050000
0$
#1055000
10
b11 .
14
12
b1 "
b1 /
1T
b11 +
1$
#1060000
0$
#1065000
15
b111 .
19
17
b11 "
b11 /
11
b100 +
1$
#1070000
0$
#1075000
1:
b1111 .
1>
1<
b111 "
b111 /
16
b101 +
1$
#1080000
0$
#1085000
1?
1C
1A
b1111 "
b1111 /
1;
0S
b11110 .
0V
0(
b110 +
1$
#1090000
0$
#1095000
1D
00
1H
04
1F
02
1@
b11110 "
b11110 /
0T
1S
b111101 .
1V
1(
b111 +
1$
#1100000
0$
#1105000
10
1I
05
14
1M
09
12
1K
07
1T
1E
b111101 "
b111101 /
01
0S
b1111010 .
0V
0(
b1000 +
1$
#1110000
0$
#1115000
17
0<
1P
02
11
06
1J
b1111010 "
b1111010 /
0T
00
15
0?
1N
1S
04
19
0C
1R
b11101101 .
1V
18
1=
1G
1L
1Q
1U
1&
b1010000010010010101001101001111 )
b11101101 W
b0 #
b11101101 %
b11101101 -
b110 ,
1$
#1120000
0$
#1125000
10
0D
05
14
0H
09
12
1!
0F
1<
07
1T
1O
0@
16
b11101101 "
b11101101 /
01
1:
1?
0S
1>
1C
b11011010 .
0V
0&
1$
#1130000
0$
#1135000
15
0:
1D
0I
00
19
0>
1H
0M
b10110100 .
04
17
0<
1F
0K
02
11
06
1@
0E
b11011010 "
b11011010 /
0T
1$
#1140000
0$
#1145000
0N
1I
0?
1:
05
0R
1M
0C
1>
b1101000 .
09
0P
1K
0A
1<
07
0J
1E
0;
16
b10110100 "
b10110100 /
01
1$
#1150000
0$
#1155000
0:
1?
0D
1N
0>
1C
0H
b11010000 .
1R
0<
1A
0F
1P
0!
06
1;
0@
1J
b1101000 "
b1101000 /
0O
1$
#1160000
0$
#1165000
0I
1D
0?
0M
1H
b10100000 .
0C
1!
0K
1F
0A
1O
0E
1@
b11010000 "
b11010000 /
0;
1$
#1170000
0$
#1175000
0D
1I
0N
0H
1M
b1000000 .
0R
0F
1K
0P
0@
1E
b10100000 "
b10100000 /
0J
1$
#1180000
0$
#1185000
1N
0I
1R
b10000000 .
0M
0!
1P
0K
0O
1J
b1000000 "
b1000000 /
0E
1$
#1190000
0$
#1195000
0N
b0 .
0R
0P
1!
0J
b10000000 "
b10000000 /
1O
1$
#1200000
0$
#1205000
0!
b0 "
b0 /
0O
1S
b1 .
1V
08
0=
0G
0L
0Q
0U
1(
b0 +
b1010011010010010101000001001111 )
b10001100 X
b10001100 #
b0 %
b0 -
1$
#1210000
0$
#1215000
10
14
12
b1 "
b1 /
1T
0S
b10 .
0V
0(
b1 +
1$
#1220000
0$
#1225000
00
15
04
b100 .
19
02
17
0T
b10 "
b10 /
11
b10 +
1$
#1230000
0$
#1235000
05
1:
09
b1000 .
1>
07
1<
01
b100 "
b100 /
16
b11 +
1$
#1240000
0$
#1245000
1?
0:
1C
0>
1A
0<
1;
b1000 "
b1000 /
06
1S
b10001 .
1V
1(
b100 +
1$
#1250000
0$
#1255000
0?
1D
10
0C
1H
b100011 .
14
0A
1F
12
0;
1@
b10001 "
b10001 /
1T
b101 +
1$
#1260000
0$
#1265000
1I
0D
15
1M
0H
19
1K
0F
17
1E
0@
b100011 "
b100011 /
11
0S
b1000110 .
0V
0(
b110 +
1$
#1270000
0$
#1275000
1:
0I
1N
00
1>
0M
1R
b10001100 .
04
1<
0K
1P
02
16
0E
1J
b1000110 "
b1000110 /
0T
b111 +
1$
#1280000
0$
#1285000
0N
1?
05
0R
1C
b11000 .
09
1!
0P
1A
07
1O
0J
1;
b10001100 "
b10001100 /
01
b1000 +
1$
#1290000
0$
#1295000
0<
1F
0!
06
1@
b11000 "
b11000 /
0O
1D
1I
1N
1S
1H
1M
1R
b11111001 .
1V
1=
1B
1G
1L
1Q
1U
1&
b1010000010010010101001101001111 )
b11111001 W
b0 #
b11111001 %
b11111001 -
b111 ,
1$
#1300000
0$
#1305000
10
14
12
1!
1P
1K
1T
1O
1J
b11111001 "
b11111001 /
1E
0:
1I
1N
0S
0>
1M
1R
b11110010 .
0V
0&
1$
#1310000
0$
#1315000
15
0?
00
19
0C
b11100100 .
04
17
0A
02
11
0;
b11110010 "
b11110010 /
0T
1$
#1320000
0$
#1325000
0D
1:
05
0H
1>
b11001000 .
09
0F
1<
07
0@
16
b11100100 "
b11100100 /
01
1$
#1330000
0$
#1335000
0:
1?
0I
0>
1C
b10010000 .
0M
0<
1A
0K
06
1;
b11001000 "
b11001000 /
0E
1$
#1340000
0$
#1345000
0N
1D
0?
0R
1H
b100000 .
0C
0P
1F
0A
0J
1@
b10010000 "
b10010000 /
0;
1$
#1350000
0$
#1355000
0D
1I
0H
b1000000 .
1M
0F
1K
0!
0@
1E
b100000 "
b100000 /
0O
1$
#1360000
0$
#1365000
1N
0I
1R
b10000000 .
0M
1P
0K
1J
b1000000 "
b1000000 /
0E
1$
#1370000
0$
#1375000
0N
b0 .
0R
0P
1!
0J
b10000000 "
b10000000 /
1O
1$
#1380000
0$
#1385000
0!
b0 "
b0 /
0O
1S
b1 .
1V
0=
0B
0G
0L
0Q
0U
1(
b0 +
b1010011010010010101000001001111 )
b11000110 X
b11000110 #
b0 %
b0 -
1$
#1390000
0$
#1395000
10
b11 .
14
12
b1 "
b1 /
1T
b1 +
1$
#1400000
0$
#1405000
15
19
17
b11 "
b11 /
11
0S
b110 .
0V
0(
b10 +
1$
#1410000
0$
#1415000
1:
00
1>
b1100 .
04
1<
02
16
b110 "
b110 /
0T
b11 +
1$
#1420000
0$
#1425000
1?
05
1C
b11000 .
09
1A
07
1;
b1100 "
b1100 /
01
b100 +
1$
#1430000
0$
#1435000
0:
1D
0>
1H
0<
1F
06
b11000 "
b11000 /
1@
1S
b110001 .
1V
1(
b101 +
1$
#1440000
0$
#1445000
10
1I
0?
14
1M
b1100011 .
0C
12
1K
0A
1T
1E
b110001 "
b110001 /
0;
b110 +
1$
#1450000
0$
#1455000
15
0D
1N
19
0H
1R
17
0F
1P
11
0@
b1100011 "
b1100011 /
1J
0S
b11000110 .
0V
0(
b111 +
1$
#1460000
0$
#1465000
00
0I
1:
04
0M
b10001100 .
1>
02
1!
0K
1<
0T
1O
0E
b11000110 "
b11000110 /
16
b1000 +
1$
#1470000
0$
#1475000
07
1A
0P
01
1;
b10001100 "
b10001100 /
0J
0:
1I
1S
0>
1M
b11000101 .
1V
18
1L
1Q
1U
1&
b1010000010010010101001101001111 )
b11000101 W
b0 #
b11000101 %
b11000101 -
b1000 ,
1$
#1480000
0$
#1485000
10
14
12
1P
0A
1T
1J
b11000101 "
b11000101 /
0;
05
1:
0?
0I
1N
0S
09
1>
0C
0M
1R
b10001010 .
0V
0&
1$
#1490000
0$
#1495000
15
0:
1?
0N
00
19
0>
1C
0R
b10100 .
04
17
0<
1A
0P
02
11
06
1;
0J
b10001010 "
b10001010 /
0T
1$
#1500000
0$
#1505000
1D
0?
1:
05
1H
0C
1>
b101000 .
09
0!
1F
0A
1<
07
0O
1@
0;
16
b10100 "
b10100 /
01
1$
#1510000
0$
#1515000
0:
1?
0D
1I
0>
1C
0H
b1010000 .
1M
0<
1A
0F
1K
06
1;
0@
b101000 "
b101000 /
1E
1$
#1520000
0$
#1525000
1N
0I
1D
0?
1R
0M
1H
b10100000 .
0C
1P
0K
1F
0A
1J
0E
1@
b1010000 "
b1010000 /
0;
1$
#1530000
0$
#1535000
0D
1I
0N
0H
1M
b1000000 .
0R
0F
1K
0P
1!
0@
1E
0J
b10100000 "
b10100000 /
1O
1$
#1540000
0$
#1545000
1N
0I
1R
b10000000 .
0M
0!
1P
0K
0O
1J
b1000000 "
b1000000 /
0E
1$
#1550000
0$
#1555000
0N
b0 .
0R
0P
1!
0J
b10000000 "
b10000000 /
1O
1$
#1560000
0$
#1565000
0!
b0 "
b0 /
0O
1S
b1 .
1V
08
0L
0Q
0U
1(
b0 +
b1010011010010010101000001001111 )
b10101010 X
b10101010 #
b0 %
b0 -
1$
#1570000
0$
#1575000
10
14
12
b1 "
b1 /
1T
0S
b10 .
0V
0(
b1 +
1$
#1580000
0$
#1585000
00
15
04
19
02
17
0T
b10 "
b10 /
11
1S
b101 .
1V
1(
b10 +
1$
#1590000
0$
