project_0/02_alu/ALU.v
module ALU
#(
    parameter  BW_DATA = 32
)
(
    input   [BW_DATA-1:0]   i_a,
    input   [BW_DATA-1:0]   i_b,
    input   [        2:0]   i_f,
    output  [BW_DATA-1:0]   o_y
);

    wire    [BW_DATA-1:0]   w_y0;
    wire    [BW_DATA-1:0]   w_y1;
    wire    [BW_DATA-1:0]   w_y2;
    wire    [BW_DATA-1:0]   w_y3;
    wire    [BW_DATA-1:0]   w_y4;
	wire    [BW_DATA-1:0]   w_y5;
	wire					w_cout;

	NOT
	#(
		.BW_DATA			(BW_DATA			)
	)
	u_not(
		.i_a				(i_b				),
		.o_y				(w_y0				)
	);

	Mux2to1
	#(
		.BW_DATA			(BW_DATA			)
	)
	u_mux2to1(
		.i_sel				(i_f[2]				),
		.i_a				(i_b				),
		.i_b				(w_y0				),
		.o_y				(w_y1				)
	);

	AND
	#(
		.BW_DATA			(BW_DATA			)
	)
	u_and(
		.i_a				(i_a				),
		.i_b				(w_y1				),
		.o_y				(w_y2				)
	);

	OR
		#(
		.BW_DATA			(BW_DATA			)
	)
	u_or(
		.i_a				(i_a				),
		.i_b				(w_y1				),
		.o_y				(w_y3				)
	);

	ADDER
	#(
		.BW_DATA			(BW_DATA			)
	)
	u_adder(
		.i_a				(i_a				),
		.i_b				(w_y1				),
		.i_c				(i_f[2]				),
		.o_c				(w_cout				),
		.o_s				(w_y4				)
	);

	/////Zero Extension /////
	assign w_y5 = {{(BW_DATA-1){1'b0}}, w_y4[BW_DATA-1]};


	
	Mux4to1
	#(
		.BW_DATA			(BW_DATA			)
	)
	u_mux4to1(
		.i_sel				(i_f[1:0]			),
		.i_a				(w_y2				),
		.i_b				(w_y3				),
		.i_c				(w_y4				),
		.i_d				(w_y5				),
		.o_y				(o_y				)
	);
    
endmodule 

module NOT
#(
    parameter  BW_DATA = 32
)
(
    input   [BW_DATA-1:0]   i_a,
    output  [BW_DATA-1:0]   o_y
);

    assign o_y = ~(i_a);

endmodule

module AND
#(
    parameter  BW_DATA = 32
)
(
    input   [BW_DATA-1:0]   i_a,
    input   [BW_DATA-1:0]   i_b,
    output  [BW_DATA-1:0]   o_y
);

    assign o_y = i_a & i_b;

endmodule

module OR 
#(
    parameter  BW_DATA = 32
)
(
    input   [BW_DATA-1:0]   i_a,
    input   [BW_DATA-1:0]   i_b,
    output  [BW_DATA-1:0]   o_y
);

    assign o_y = i_a | i_b;

endmodule

module ADDER 
#(
    parameter  BW_DATA = 32
)
(
    input   [BW_DATA-1:0]   i_a,
    input   [BW_DATA-1:0]   i_b,
    input                   i_c,
    output                  o_c,
    output  [BW_DATA-1:0]   o_s
);

    assign  {o_c, o_s}  =   i_a + i_b + i_c;

endmodule

module Mux2to1 
#(
    parameter  BW_DATA = 32
)
(
    input   				i_sel,
    input   [BW_DATA-1:0]   i_a,
    input   [BW_DATA-1:0]   i_b,
    output  [BW_DATA-1:0]   o_y
);

assign o_y = (i_sel) ? i_b : i_a;
    
endmodule

module Mux4to1 
#(
    parameter  BW_DATA = 32
)
(
    input       [        1:0]   i_sel,
    input       [BW_DATA-1:0]   i_a,
    input       [BW_DATA-1:0]   i_b,
    input       [BW_DATA-1:0]   i_c,
    input       [BW_DATA-1:0]   i_d,
    output  reg [BW_DATA-1:0]   o_y
);

always @(*) begin
    case(i_sel)
        2'b00 : o_y = i_a;
        2'b01 : o_y = i_b;
        2'b10 : o_y = i_c;
        2'b11 : o_y = i_d;
    endcase
end

endmodule

project_0/02_alu/ALU_tb.v
//-------------------------------------
// Define Global Variables
// ------------------------------------
`define CLKFREQ     100
`define SIMCYCLE    100

`include "ALU.v"

module ALU_tb;
//---------------------------------------------------
//DUT Signals & Instantiate
//---------------------------------------------------

parameter	BW_DATA	= 32;	

reg   [BW_DATA-1:0]   i_a;
reg   [BW_DATA-1:0]   i_b;
reg   [        2:0]   i_f;
wire  [BW_DATA-1:0]   o_y;

ALU
#(
	.BW_DATA			(BW_DATA			)
)
u_ALU(
	.i_a				(i_a				),
	.i_b				(i_b				),
	.i_f				(i_f				),
	.o_y				(o_y				)
);

//---------------------------------------------------
//Tasks
//---------------------------------------------------
reg     [20*32-1:0]  taskState;

task init;
    begin
		taskState 	= "Init";
        i_a			= 0;
        i_b		    = 0;
        i_f		    = 0;
    end
endtask

integer i;

task ALU_function;
	input 	[BW_DATA-1:0] 	a;
	input	[BW_DATA-1:0]	b;
	begin
		taskState = "ALU_FUNC";
		i_a = a;
		i_b = b;
		i_f = 0;
		#(1000/`CLKFREQ);
		for(i = 0; i < 7; i = i +1) begin
			i_f = i_f + 3'b001;
			#(1000/`CLKFREQ);
		end
	end
endtask

task ALU_function_000;
	input 	[BW_DATA-1:0] 	a;
	input	[BW_DATA-1:0]	b;
	begin
		taskState = "AND";
		i_a = a;
		i_b = b;
		i_f = 3'b000;
	end
endtask

task ALU_function_001;
	input 	[BW_DATA-1:0] 	a;
	input	[BW_DATA-1:0]	b;
	begin
		taskState = "OR";
		i_a = a;
		i_b = b;
		i_f = 3'b001;
	end
endtask

task ALU_function_010;
	input 	[BW_DATA-1:0] 	a;
	input	[BW_DATA-1:0]	b;
	begin
		taskState = "ADD";
		i_a = a;
		i_b = b;
		i_f = 3'b010;
	end
endtask

task ALU_function_011;
	input 	[BW_DATA-1:0] 	a;
	input	[BW_DATA-1:0]	b;
	begin
		taskState  = "Reserved";
		i_a = a;
		i_b = b;
		i_f = 3'b011;
	end
endtask

task ALU_function_100;
	input 	[BW_DATA-1:0] 	a;
	input	[BW_DATA-1:0]	b;
	begin
		taskState = "Not_AND";
		i_a = a;
		i_b = b;
		i_f = 3'b100;
	end
endtask

task ALU_function_101;
	input 	[BW_DATA-1:0] 	a;
	input	[BW_DATA-1:0]	b;
	begin
		taskState = "Not_OR";
		i_a = a;
		i_b = b;
		i_f = 3'b101;
	end
endtask

task ALU_function_110;
	input 	[BW_DATA-1:0] 	a;
	input	[BW_DATA-1:0]	b;
	begin
		taskState = "Substract";
		i_a = a;
		i_b = b;
		i_f = 3'b110;
	end
endtask

task ALU_function_111;
	input 	[BW_DATA-1:0] 	a;
	input	[BW_DATA-1:0]	b;
	begin
		taskState = "SLT";
		i_a = a;
		i_b = b;
		i_f = 3'b111;
	end
endtask



//---------------------------------------------------
//Stimulus
//---------------------------------------------------
integer j;

initial begin
	init();
	for (j=0; j<`SIMCYCLE; j++) begin
		i_a = i_a + 1;
		i_b = i_b + 2;
		ALU_function(i_a, i_b);
		//#(1000/`CLKFREQ);
		ALU_function_000(i_a, i_b);
		#(1000/`CLKFREQ);
		ALU_function_100(i_a, i_b);
		#(1000/`CLKFREQ);
		ALU_function_001(i_a, i_b);
		#(1000/`CLKFREQ);
		ALU_function_101(i_a, i_b);
		#(1000/`CLKFREQ);
		ALU_function_010(i_a, i_b);
		#(1000/`CLKFREQ);
		ALU_function_110(i_a, i_b);
		#(1000/`CLKFREQ);
		ALU_function_111(i_a, i_b);
		#(1000/`CLKFREQ);

	end
	#(1000/`CLKFREQ);
	$finish;
end

// --------------------------------------------------
//	Dump VCD
// --------------------------------------------------
	reg	[8*32-1:0]	vcd_file;
	initial begin
		if ($value$plusargs("vcd_file=%s", vcd_file)) begin
			$dumpfile(vcd_file);
			$dumpvars;
		end else begin
			$dumpfile("AUL_tb.vcd");
			$dumpvars;
		end
	end

endmodule

project_0/02_alu/vcd/ALU.vcd
$date
	Thu Jul  4 09:23:37 2024
$end
$version
	Icarus Verilog
$end
$timescale
	1ps
$end
$scope module ALU_tb $end
$var wire 32 ! o_y [31:0] $end
$var reg 32 " i_a [31:0] $end
$var reg 32 # i_b [31:0] $end
$var reg 3 $ i_f [2:0] $end
$var reg 640 % taskState [639:0] $end
$var reg 256 & vcd_file [255:0] $end
$var integer 32 ' i [31:0] $end
$var integer 32 ( j [31:0] $end
$scope module u_ALU $end
$var wire 32 ) i_a [31:0] $end
$var wire 32 * i_b [31:0] $end
$var wire 3 + i_f [2:0] $end
$var wire 32 , w_y5 [31:0] $end
$var wire 32 - w_y4 [31:0] $end
$var wire 32 . w_y3 [31:0] $end
$var wire 32 / w_y2 [31:0] $end
$var wire 32 0 w_y1 [31:0] $end
$var wire 32 1 w_y0 [31:0] $end
$var wire 1 2 w_cout $end
$var wire 32 3 o_y [31:0] $end
$scope module u_adder $end
$var wire 32 4 i_a [31:0] $end
$var wire 1 5 i_c $end
$var wire 32 6 o_s [31:0] $end
$var wire 1 2 o_c $end
$var wire 32 7 i_b [31:0] $end
$upscope $end
$scope module u_and $end
$var wire 32 8 i_a [31:0] $end
$var wire 32 9 o_y [31:0] $end
$var wire 32 : i_b [31:0] $end
$upscope $end
$scope module u_mux2to1 $end
$var wire 32 ; i_a [31:0] $end
$var wire 1 < i_sel $end
$var wire 32 = o_y [31:0] $end
$var wire 32 > i_b [31:0] $end
$upscope $end
$scope module u_mux4to1 $end
$var wire 32 ? i_a [31:0] $end
$var wire 32 @ i_c [31:0] $end
$var wire 32 A i_d [31:0] $end
$var wire 2 B i_sel [1:0] $end
$var wire 32 C i_b [31:0] $end
$var reg 32 D o_y [31:0] $end
$upscope $end
$scope module u_not $end
$var wire 32 E i_a [31:0] $end
$var wire 32 F o_y [31:0] $end
$upscope $end
$scope module u_or $end
$var wire 32 G i_a [31:0] $end
$var wire 32 H i_b [31:0] $end
$var wire 32 I o_y [31:0] $end
$upscope $end
$upscope $end
$scope task ALU_function $end
$var reg 32 J a [31:0] $end
$var reg 32 K b [31:0] $end
$upscope $end
$scope task ALU_function_000 $end
$var reg 32 L a [31:0] $end
$var reg 32 M b [31:0] $end
$upscope $end
$scope task ALU_function_001 $end
$var reg 32 N a [31:0] $end
$var reg 32 O b [31:0] $end
$upscope $end
$scope task ALU_function_010 $end
$var reg 32 P a [31:0] $end
$var reg 32 Q b [31:0] $end
$upscope $end
$scope task ALU_function_011 $end
$var reg 32 R a [31:0] $end
$var reg 32 S b [31:0] $end
$upscope $end
$scope task ALU_function_100 $end
$var reg 32 T a [31:0] $end
$var reg 32 U b [31:0] $end
$upscope $end
$scope task ALU_function_101 $end
$var reg 32 V a [31:0] $end
$var reg 32 W b [31:0] $end
$upscope $end
$scope task ALU_function_110 $end
$var reg 32 X a [31:0] $end
$var reg 32 Y b [31:0] $end
$upscope $end
$scope task ALU_function_111 $end
$var reg 32 Z a [31:0] $end
$var reg 32 [ b [31:0] $end
$upscope $end
$scope task init $end
$upscope $end
$upscope $end
$enddefinitions $end
#0
$dumpvars
bx [
bx Z
bx Y
bx X
bx W
bx V
bx U
bx T
bx S
bx R
bx Q
bx P
bx O
bx N
bx M
bx L
bx K
bx J
b0 I
b0 H
b0 G
b11111111111111111111111111111111 F
b0 E
b0 D
b0 C
b0 B
b0 A
b0 @
b0 ?
b11111111111111111111111111111111 >
b0 =
0<
b0 ;
b0 :
b0 9
b0 8
b0 7
b0 6
05
b0 4
b0 3
02
b11111111111111111111111111111111 1
b0 0
b0 /
b0 .
b0 -
b0 ,
b0 +
b0 *
b0 )
bx (
bx '
b101110001011110111011001100011011001000010111101000001010011000101010100101110011101100110001101100100 &
b1001001011011100110100101110100 %
b0 $
b0 #
b0 "
b0 !
$end
#10000
b10 0
b10 7
b10 :
b10 =
b10 H
b11111111111111111111111111111101 1
b11111111111111111111111111111101 >
b11111111111111111111111111111101 F
b11 -
b11 6
b11 @
b11 .
b11 C
b11 I
b100000101001100010101010101111101000110010101010100111001000011 %
b10 K
b1 J
b10 #
b10 *
b10 ;
b10 E
b1 "
b1 )
b1 4
b1 8
b1 G
b0 (
#20000
b1 ,
b1 A
b1 !
b1 3
b1 D
b11111111111111111111111111111101 .
b11111111111111111111111111111101 C
b11111111111111111111111111111101 I
b1 /
b1 9
b1 ?
b11111111111111111111111111111101 0
b11111111111111111111111111111101 7
b11111111111111111111111111111101 :
b11111111111111111111111111111101 =
b11111111111111111111111111111101 H
b11111111111111111111111111111111 -
b11111111111111111111111111111111 6
b11111111111111111111111111111111 @
1<
15
b100 $
b100 +
b0 '
#30000
b0 ,
b0 A
b11 .
b11 C
b11 I
b0 /
b0 9
b0 ?
b10 0
b10 7
b10 :
b10 =
b10 H
b11 -
b11 6
b11 @
b11 !
b11 3
b11 D
0<
05
b1 B
b1 $
b1 +
b1 '
#40000
b10 '
#50000
b0 !
b0 3
b0 D
b11 B
b11 $
b11 +
b11 '
#60000
b1 ,
b1 A
b11111111111111111111111111111101 .
b11111111111111111111111111111101 C
b11111111111111111111111111111101 I
b1 /
b1 9
b1 ?
b11111111111111111111111111111101 0
b11111111111111111111111111111101 7
b11111111111111111111111111111101 :
b11111111111111111111111111111101 =
b11111111111111111111111111111101 H
b11111111111111111111111111111111 -
b11111111111111111111111111111111 6
b11111111111111111111111111111111 @
b11111111111111111111111111111101 !
b11111111111111111111111111111101 3
b11111111111111111111111111111101 D
1<
15
b1 B
b101 $
b101 +
b100 '
#70000
b101 '
#80000
b110 '
#90000
b0 ,
b0 A
b11 .
b11 C
b11 I
b0 /
b0 9
b0 ?
b10 0
b10 7
b10 :
b10 =
b10 H
b11 -
b11 6
b11 @
b0 !
b0 3
b0 D
0<
05
b0 B
b0 $
b0 +
b10000010100111001000100 %
b10 M
b1 L
b111 '
#100000
b1 ,
b1 A
b1 !
b1 3
b1 D
b11111111111111111111111111111101 .
b11111111111111111111111111111101 C
b11111111111111111111111111111101 I
b1 /
b1 9
b1 ?
b11111111111111111111111111111101 0
b11111111111111111111111111111101 7
b11111111111111111111111111111101 :
b11111111111111111111111111111101 =
b11111111111111111111111111111101 H
b11111111111111111111111111111111 -
b11111111111111111111111111111111 6
b11111111111111111111111111111111 @
1<
15
b100 $
b100 +
b1001110011011110111010001011111010000010100111001000100 %
b10 U
b1 T
#110000
b0 ,
b0 A
b11 .
b11 C
b11 I
b0 /
b0 9
b0 ?
b10 0
b10 7
b10 :
b10 =
b10 H
b11 -
b11 6
b11 @
b11 !
b11 3
b11 D
0<
05
b1 B
b1 $
b1 +
b100111101010010 %
b10 O
b1 N
#120000
b1 ,
b1 A
b11111111111111111111111111111101 !
b11111111111111111111111111111101 3
b11111111111111111111111111111101 D
b11111111111111111111111111111101 .
b11111111111111111111111111111101 C
b11111111111111111111111111111101 I
b1 /
b1 9
b1 ?
b11111111111111111111111111111101 0
b11111111111111111111111111111101 7
b11111111111111111111111111111101 :
b11111111111111111111111111111101 =
b11111111111111111111111111111101 H
b11111111111111111111111111111111 -
b11111111111111111111111111111111 6
b11111111111111111111111111111111 @
1<
15
b101 $
b101 +
b10011100110111101110100010111110100111101010010 %
b10 W
b1 V
#130000
b0 ,
b0 A
b11 .
b11 C
b11 I
b0 /
b0 9
b0 ?
b10 0
b10 7
b10 :
b10 =
b10 H
b11 -
b11 6
b11 @
b11 !
b11 3
b11 D
0<
05
b10 B
b10 $
b10 +
b10000010100010001000100 %
b10 Q
b1 P
#140000
b1 ,
b1 A
b11111111111111111111111111111101 .
b11111111111111111111111111111101 C
b11111111111111111111111111111101 I
b1 /
b1 9
b1 ?
b11111111111111111111111111111111 !
b11111111111111111111111111111111 3
b11111111111111111111111111111111 D
b11111111111111111111111111111101 0
b11111111111111111111111111111101 7
b11111111111111111111111111111101 :
b11111111111111111111111111111101 =
b11111111111111111111111111111101 H
b11111111111111111111111111111111 -
b11111111111111111111111111111111 6
b11111111111111111111111111111111 @
1<
15
b110 $
b110 +
b10100110111010101100010011100110111010001110010011000010110001101110100 %
b10 Y
b1 X
#150000
b1 !
b1 3
b1 D
b11 B
b111 $
b111 +
b10100110100110001010100 %
b10 [
b1 Z
#160000
b100 0
b100 7
b100 :
b100 =
b100 H
b0 ,
b0 A
b0 !
b0 3
b0 D
0<
05
b0 B
b11111111111111111111111111111011 1
b11111111111111111111111111111011 >
b11111111111111111111111111111011 F
b110 -
b110 6
b110 @
02
b0 /
b0 9
b0 ?
b110 .
b110 C
b110 I
b0 $
b0 +
b100000101001100010101010101111101000110010101010100111001000011 %
b100 K
b10 J
b100 #
b100 *
b100 ;
b100 E
b10 "
b10 )
b10 4
b10 8
b10 G
b1 (
#170000
b110 !
b110 3
b110 D
b10 B
b10 $
b10 +
b0 '
#180000
b1 B
b1 $
b1 +
b1 '
#190000
b1 ,
b1 A
b11111111111111111111111111111011 !
b11111111111111111111111111111011 3
b11111111111111111111111111111011 D
b11111111111111111111111111111011 .
b11111111111111111111111111111011 C
b11111111111111111111111111111011 I
b10 /
b10 9
b10 ?
b11111111111111111111111111111011 0
b11111111111111111111111111111011 7
b11111111111111111111111111111011 :
b11111111111111111111111111111011 =
b11111111111111111111111111111011 H
b11111111111111111111111111111110 -
b11111111111111111111111111111110 6
b11111111111111111111111111111110 @
1<
15
b101 $
b101 +
b10 '
#200000
b11111111111111111111111111111110 !
b11111111111111111111111111111110 3
b11111111111111111111111111111110 D
b10 B
b110 $
b110 +
b11 '
#210000
b11111111111111111111111111111011 !
b11111111111111111111111111111011 3
b11111111111111111111111111111011 D
b1 B
b101 $
b101 +
b100 '
#220000
b101 '
#230000
b10 !
b10 3
b10 D
b0 B
b100 $
b100 +
b110 '
#240000
b0 ,
b0 A
b0 !
b0 3
b0 D
b110 .
b110 C
b110 I
b0 /
b0 9
b0 ?
b100 0
b100 7
b100 :
b100 =
b100 H
b110 -
b110 6
b110 @
0<
05
b0 $
b0 +
b10000010100111001000100 %
b100 M
b10 L
b111 '
#250000
b1 ,
b1 A
b10 !
b10 3
b10 D
b11111111111111111111111111111011 .
b11111111111111111111111111111011 C
b11111111111111111111111111111011 I
b10 /
b10 9
b10 ?
b11111111111111111111111111111011 0
b11111111111111111111111111111011 7
b11111111111111111111111111111011 :
b11111111111111111111111111111011 =
b11111111111111111111111111111011 H
b11111111111111111111111111111110 -
b11111111111111111111111111111110 6
b11111111111111111111111111111110 @
1<
15
b100 $
b100 +
b1001110011011110111010001011111010000010100111001000100 %
b100 U
b10 T
#260000
b0 ,
b0 A
b110 .
b110 C
b110 I
b0 /
b0 9
b0 ?
b100 0
b100 7
b100 :
b100 =
b100 H
b110 -
b110 6
b110 @
b110 !
b110 3
b110 D
0<
05
b1 B
b1 $
b1 +
b100111101010010 %
b100 O
b10 N
#270000
b1 ,
b1 A
b11111111111111111111111111111011 !
b11111111111111111111111111111011 3
b11111111111111111111111111111011 D
b11111111111111111111111111111011 .
b11111111111111111111111111111011 C
b11111111111111111111111111111011 I
b10 /
b10 9
b10 ?
b11111111111111111111111111111011 0
b11111111111111111111111111111011 7
b11111111111111111111111111111011 :
b11111111111111111111111111111011 =
b11111111111111111111111111111011 H
b11111111111111111111111111111110 -
b11111111111111111111111111111110 6
b11111111111111111111111111111110 @
1<
15
b101 $
b101 +
b10011100110111101110100010111110100111101010010 %
b100 W
b10 V
#280000
b0 ,
b0 A
b110 .
b110 C
b110 I
b0 /
b0 9
b0 ?
b100 0
b100 7
b100 :
b100 =
b100 H
b110 -
b110 6
b110 @
b110 !
b110 3
b110 D
0<
05
b10 B
b10 $
b10 +
b10000010100010001000100 %
b100 Q
b10 P
#290000
b1 ,
b1 A
b11111111111111111111111111111011 .
b11111111111111111111111111111011 C
b11111111111111111111111111111011 I
b10 /
b10 9
b10 ?
b11111111111111111111111111111110 !
b11111111111111111111111111111110 3
b11111111111111111111111111111110 D
b11111111111111111111111111111011 0
b11111111111111111111111111111011 7
b11111111111111111111111111111011 :
b11111111111111111111111111111011 =
b11111111111111111111111111111011 H
b11111111111111111111111111111110 -
b11111111111111111111111111111110 6
b11111111111111111111111111111110 @
1<
15
b110 $
b110 +
b10100110111010101100010011100110111010001110010011000010110001101110100 %
b100 Y
b10 X
#300000
b1 !
b1 3
b1 D
b11 B
b111 $
b111 +
b10100110100110001010100 %
b100 [
b10 Z
#310000
b0 ,
b0 A
b111 .
b111 C
b111 I
b110 0
b110 7
b110 :
b110 =
b110 H
b10 !
b10 3
b10 D
0<
05
b0 B
b11111111111111111111111111111001 1
b11111111111111111111111111111001 >
b11111111111111111111111111111001 F
b1001 -
b1001 6
b1001 @
b10 /
b10 9
b10 ?
b0 $
b0 +
b100000101001100010101010101111101000110010101010100111001000011 %
b110 K
b11 J
b110 #
b110 *
b110 ;
b110 E
b11 "
b11 )
b11 4
b11 8
b11 G
b10 (
#320000
b111 !
b111 3
b111 D
b1 B
b1 $
b1 +
b0 '
#330000
b1 ,
b1 A
b11111111111111111111111111111011 .
b11111111111111111111111111111011 C
b11111111111111111111111111111011 I
b1 /
b1 9
b1 ?
b11111111111111111111111111111001 0
b11111111111111111111111111111001 7
b11111111111111111111111111111001 :
b11111111111111111111111111111001 =
b11111111111111111111111111111001 H
b11111111111111111111111111111101 -
b11111111111111111111111111111101 6
b11111111111111111111111111111101 @
b11111111111111111111111111111101 !
b11111111111111111111111111111101 3
b11111111111111111111111111111101 D
1<
15
b10 B
b110 $
b110 +
b1 '
#340000
b11111111111111111111111111111011 !
b11111111111111111111111111111011 3
b11111111111111111111111111111011 D
b1 B
b101 $
b101 +
b10 '
#350000
b0 ,
b0 A
b111 .
b111 C
b111 I
b10 /
b10 9
b10 ?
b110 0
b110 7
b110 :
b110 =
b110 H
b1001 -
b1001 6
b1001 @
b1001 !
b1001 3
b1001 D
0<
05
b10 B
b10 $
b10 +
b11 '
#360000
b1 ,
b1 A
b11111111111111111111111111111011 .
b11111111111111111111111111111011 C
b11111111111111111111111111111011 I
b1 /
b1 9
b1 ?
b11111111111111111111111111111001 0
b11111111111111111111111111111001 7
b11111111111111111111111111111001 :
b11111111111111111111111111111001 =
b11111111111111111111111111111001 H
b11111111111111111111111111111101 -
b11111111111111111111111111111101 6
b11111111111111111111111111111101 @
b11111111111111111111111111111011 !
b11111111111111111111111111111011 3
b11111111111111111111111111111011 D
1<
15
b1 B
b101 $
b101 +
b100 '
#370000
b1 !
b1 3
b1 D
b11 B
b111 $
b111 +
b101 '
#380000
b0 ,
b0 A
b111 .
b111 C
b111 I
b10 /
b10 9
b10 ?
b110 0
b110 7
b110 :
b110 =
b110 H
b1001 -
b1001 6
b1001 @
b1001 !
b1001 3
b1001 D
0<
05
b10 B
b10 $
b10 +
b110 '
#390000
b10 !
b10 3
b10 D
b0 B
b0 $
b0 +
b10000010100111001000100 %
b110 M
b11 L
b111 '
#400000
b1 ,
b1 A
b1 !
b1 3
b1 D
b11111111111111111111111111111011 .
b11111111111111111111111111111011 C
b11111111111111111111111111111011 I
b1 /
b1 9
b1 ?
b11111111111111111111111111111001 0
b11111111111111111111111111111001 7
b11111111111111111111111111111001 :
b11111111111111111111111111111001 =
b11111111111111111111111111111001 H
b11111111111111111111111111111101 -
b11111111111111111111111111111101 6
b11111111111111111111111111111101 @
1<
15
b100 $
b100 +
b1001110011011110111010001011111010000010100111001000100 %
b110 U
b11 T
#410000
b0 ,
b0 A
b111 .
b111 C
b111 I
b10 /
b10 9
b10 ?
b110 0
b110 7
b110 :
b110 =
b110 H
b1001 -
b1001 6
b1001 @
b111 !
b111 3
b111 D
0<
05
b1 B
b1 $
b1 +
b100111101010010 %
b110 O
b11 N
#420000
b1 ,
b1 A
b11111111111111111111111111111011 !
b11111111111111111111111111111011 3
b11111111111111111111111111111011 D
b11111111111111111111111111111011 .
b11111111111111111111111111111011 C
b11111111111111111111111111111011 I
b1 /
b1 9
b1 ?
b11111111111111111111111111111001 0
b11111111111111111111111111111001 7
b11111111111111111111111111111001 :
b11111111111111111111111111111001 =
b11111111111111111111111111111001 H
b11111111111111111111111111111101 -
b11111111111111111111111111111101 6
b11111111111111111111111111111101 @
1<
15
b101 $
b101 +
b10011100110111101110100010111110100111101010010 %
b110 W
b11 V
#430000
b0 ,
b0 A
b111 .
b111 C
b111 I
b10 /
b10 9
b10 ?
b110 0
b110 7
b110 :
b110 =
b110 H
b1001 -
b1001 6
b1001 @
b1001 !
b1001 3
b1001 D
0<
05
b10 B
b10 $
b10 +
b10000010100010001000100 %
b110 Q
b11 P
#440000
b1 ,
b1 A
b11111111111111111111111111111011 .
b11111111111111111111111111111011 C
b11111111111111111111111111111011 I
b1 /
b1 9
b1 ?
b11111111111111111111111111111101 !
b11111111111111111111111111111101 3
b11111111111111111111111111111101 D
b11111111111111111111111111111001 0
b11111111111111111111111111111001 7
b11111111111111111111111111111001 :
b11111111111111111111111111111001 =
b11111111111111111111111111111001 H
b11111111111111111111111111111101 -
b11111111111111111111111111111101 6
b11111111111111111111111111111101 @
1<
15
b110 $
b110 +
b10100110111010101100010011100110111010001110010011000010110001101110100 %
b110 Y
b11 X
#450000
b1 !
b1 3
b1 D
b11 B
b111 $
b111 +
b10100110100110001010100 %
b110 [
b11 Z
#460000
b0 ,
b0 A
b1000 0
b1000 7
b1000 :
b1000 =
b1000 H
b0 !
b0 3
b0 D
0<
05
b0 B
b11111111111111111111111111110111 1
b11111111111111111111111111110111 >
b11111111111111111111111111110111 F
b1100 -
b1100 6
b1100 @
b0 /
b0 9
b0 ?
b1100 .
b1100 C
b1100 I
b0 $
b0 +
b100000101001100010101010101111101000110010101010100111001000011 %
b1000 K
b100 J
b1000 #
b1000 *
b1000 ;
b1000 E
b100 "
b100 )
b100 4
b100 8
b100 G
b11 (
#470000
b1 !
b1 3
b1 D
b1 ,
b1 A
b11111111111111111111111111110111 .
b11111111111111111111111111110111 C
b11111111111111111111111111110111 I
b100 /
b100 9
b100 ?
b11111111111111111111111111110111 0
b11111111111111111111111111110111 7
b11111111111111111111111111110111 :
b11111111111111111111111111110111 =
b11111111111111111111111111110111 H
b11111111111111111111111111111100 -
b11111111111111111111111111111100 6
b11111111111111111111111111111100 @
1<
15
b11 B
b111 $
b111 +
b0 '
#480000
b0 ,
b0 A
b1100 .
b1100 C
b1100 I
b0 /
b0 9
b0 ?
b1000 0
b1000 7
b1000 :
b1000 =
b1000 H
b1100 -
b1100 6
b1100 @
b1100 !
b1100 3
b1100 D
0<
05
b10 B
b10 $
b10 +
b1 '
#490000
b1 ,
b1 A
b11111111111111111111111111110111 .
b11111111111111111111111111110111 C
b11111111111111111111111111110111 I
b100 /
b100 9
b100 ?
b11111111111111111111111111111100 !
b11111111111111111111111111111100 3
b11111111111111111111111111111100 D
b11111111111111111111111111110111 0
b11111111111111111111111111110111 7
b11111111111111111111111111110111 :
b11111111111111111111111111110111 =
b11111111111111111111111111110111 H
b11111111111111111111111111111100 -
b11111111111111111111111111111100 6
b11111111111111111111111111111100 @
1<
15
b110 $
b110 +
b10 '
#500000
b0 ,
b0 A
b1100 .
b1100 C
b1100 I
b0 /
b0 9
b0 ?
b1000 0
b1000 7
b1000 :
b1000 =
b1000 H
b1100 -
b1100 6
b1100 @
b0 !
b0 3
b0 D
0<
05
b0 B
b0 $
b0 +
b11 '
#510000
b1 ,
b1 A
b11111111111111111111111111110111 .
b11111111111111111111111111110111 C
b11111111111111111111111111110111 I
b100 /
b100 9
b100 ?
b11111111111111111111111111110111 0
b11111111111111111111111111110111 7
b11111111111111111111111111110111 :
b11111111111111111111111111110111 =
b11111111111111111111111111110111 H
b11111111111111111111111111111100 -
b11111111111111111111111111111100 6
b11111111111111111111111111111100 @
b11111111111111111111111111110111 !
b11111111111111111111111111110111 3
b11111111111111111111111111110111 D
1<
15
b1 B
b101 $
b101 +
b100 '
#520000
b100 !
b100 3
b100 D
b0 B
b100 $
b100 +
b101 '
#530000
b11111111111111111111111111110111 !
b11111111111111111111111111110111 3
b11111111111111111111111111110111 D
b1 B
b101 $
b101 +
b110 '
#540000
b0 ,
b0 A
b1100 .
b1100 C
b1100 I
b0 /
b0 9
b0 ?
b1000 0
b1000 7
b1000 :
b1000 =
b1000 H
b1100 -
b1100 6
b1100 @
b0 !
b0 3
b0 D
0<
05
b0 B
b0 $
b0 +
b10000010100111001000100 %
b1000 M
b100 L
b111 '
#550000
b1 ,
b1 A
b100 !
b100 3
b100 D
b11111111111111111111111111110111 .
b11111111111111111111111111110111 C
b11111111111111111111111111110111 I
b100 /
b100 9
b100 ?
b11111111111111111111111111110111 0
b11111111111111111111111111110111 7
b11111111111111111111111111110111 :
b11111111111111111111111111110111 =
b11111111111111111111111111110111 H
b11111111111111111111111111111100 -
b11111111111111111111111111111100 6
b11111111111111111111111111111100 @
1<
15
b100 $
b100 +
b1001110011011110111010001011111010000010100111001000100 %
b1000 U
b100 T
#560000
b0 ,
b0 A
b1100 .
b1100 C
b1100 I
b0 /
b0 9
b0 ?
b1000 0
b1000 7
b1000 :
b1000 =
b1000 H
b1100 -
b1100 6
b1100 @
b1100 !
b1100 3
b1100 D
0<
05
b1 B
b1 $
b1 +
b100111101010010 %
b1000 O
b100 N
#570000
b1 ,
b1 A
b11111111111111111111111111110111 !
b11111111111111111111111111110111 3
b11111111111111111111111111110111 D
b11111111111111111111111111110111 .
b11111111111111111111111111110111 C
b11111111111111111111111111110111 I
b100 /
b100 9
b100 ?
b11111111111111111111111111110111 0
b11111111111111111111111111110111 7
b11111111111111111111111111110111 :
b11111111111111111111111111110111 =
b11111111111111111111111111110111 H
b11111111111111111111111111111100 -
b11111111111111111111111111111100 6
b11111111111111111111111111111100 @
1<
15
b101 $
b101 +
b10011100110111101110100010111110100111101010010 %
b1000 W
b100 V
#580000
b0 ,
b0 A
b1100 .
b1100 C
b1100 I
b0 /
b0 9
b0 ?
b1000 0
b1000 7
b1000 :
b1000 =
b1000 H
b1100 -
b1100 6
b1100 @
b1100 !
b1100 3
b1100 D
0<
05
b10 B
b10 $
b10 +
b10000010100010001000100 %
b1000 Q
b100 P
