project_0/00_gray_code_converter/gray_to_bin.v
module gray_to_bin
(
	input	[2:0]	i_data,
	output	[2:0]	o_data
);


assign o_data[0] = o_data[1] ^ i_data[0];
assign o_data[1] = o_data[2] ^ i_data[1];
assign o_data[2] = i_data[2];
endmodule

project_0/00_gray_code_converter/bin_to_gray.v
module bin_to_gray
(
	input	[2:0]	i_data,
	output	[2:0]	o_data
);

assign o_data[0] = i_data[1] ^ i_data[0];
assign o_data[1] = i_data[2] ^ i_data[1];
assign o_data[2] = i_data[2];

endmodule

project_0/00_gray_code_converter/bin_to_gray_tb.v
`define		CLKFREQ		100
`define		SIMCYCLE	100

`include "bin_to_gray.v"
`include "gray_to_bin.v"

module test;
//---------------------------------------------------
// DUT Signals & Intanciate
//---------------------------------------------------
	reg		[2:0]	i_data;
	wire	[2:0]	o_data_bin;
	wire	[2:0]	o_data_gray;

	bin_to_gray
	u_bin_to_gray(
		.i_data				(i_data				),
		.o_data				(o_data_gray		)
	);


	gray_to_bin
	u_gray_to_bin(
		.i_data				(o_data_gray		),
		.o_data				(o_data_bin			)
	);


//---------------------------------------------------
//Stimulus
//---------------------------------------------------
integer i, j;

initial begin
	for (i=0; i<`SIMCYCLE; i++) begin
		i_data = $urandom;
		#(500/`CLKFREQ);
	end
	#(1000/`CLKFREQ);
	$finish;
end

// --------------------------------------------------
//	Dump VCD
// --------------------------------------------------
	reg	[8*32-1:0]	vcd_file;
	initial begin
		if ($value$plusargs("vcd_file=%s", vcd_file)) begin
			$dumpfile(vcd_file);
			$dumpvars;
		end else begin
			$dumpfile("bin_to_gray_tb.vcd");
			$dumpvars;
		end
	end

endmodule

project_0/00_gray_code_converter/vcd/bin_to_gray.vcd
$date
	Fri Jun 28 13:19:31 2024
$end
$version
	Icarus Verilog
$end
$timescale
	1ps
$end
$scope module test $end
$var wire 3 ! o_data_gray [2:0] $end
$var wire 3 " o_data_bin [2:0] $end
$var reg 3 # i_data [2:0] $end
$var reg 256 $ vcd_file [255:0] $end
$var integer 32 % i [31:0] $end
$scope module u_bin_to_gray $end
$var wire 3 & i_data [2:0] $end
$var wire 3 ' o_data [2:0] $end
$upscope $end
$scope module u_gray_to_bin $end
$var wire 3 ( i_data [2:0] $end
$var wire 3 ) o_data [2:0] $end
$upscope $end
$upscope $end
$enddefinitions $end
#0
$dumpvars
b100 )
b110 (
b110 '
b100 &
b0 %
b1011100010111101110110011000110110010000101111011000100110100101101110010111110111010001101111010111110110011101110010011000010111100100101110011101100110001101100100 $
b100 #
b100 "
b110 !
$end
#5000
b1 "
b1 )
b1 !
b1 '
b1 (
b1 #
b1 &
b1 %
#10000
b10 %
#15000
b11 "
b11 )
b10 !
b10 '
b10 (
b11 #
b11 &
b11 %
#20000
b101 "
b101 )
b111 !
b111 '
b111 (
b101 #
b101 &
b100 %
#25000
b101 %
#30000
b110 %
#35000
b10 "
b10 )
b11 !
b11 '
b11 (
b10 #
b10 &
b111 %
#40000
b1 "
b1 )
b1 !
b1 '
b1 (
b1 #
b1 &
b1000 %
#45000
b101 "
b101 )
b111 !
b111 '
b111 (
b101 #
b101 &
b1001 %
#50000
b110 "
b110 )
b101 !
b101 '
b101 (
b110 #
b110 &
b1010 %
#55000
b101 "
b101 )
b111 !
b111 '
b111 (
b101 #
b101 &
b1011 %
#60000
b1100 %
#65000
b100 "
b100 )
b110 !
b110 '
b110 (
b100 #
b100 &
b1101 %
#70000
b1 "
b1 )
b1 !
b1 '
b1 (
b1 #
b1 &
b1110 %
#75000
b110 "
b110 )
b101 !
b101 '
b101 (
b110 #
b110 &
b1111 %
#80000
b101 "
b101 )
b111 !
b111 '
b111 (
b101 #
b101 &
b10000 %
#85000
b10 "
b10 )
b11 !
b11 '
b11 (
b10 #
b10 &
b10001 %
#90000
b101 "
b101 )
b111 !
b111 '
b111 (
b101 #
b101 &
b10010 %
#95000
b111 "
b111 )
b100 !
b100 '
b100 (
b111 #
b111 &
b10011 %
#100000
b10 "
b10 )
b11 !
b11 '
b11 (
b10 #
b10 &
b10100 %
#105000
b111 "
b111 )
b100 !
b100 '
b100 (
b111 #
b111 &
b10101 %
#110000
b10 "
b10 )
b11 !
b11 '
b11 (
b10 #
b10 &
b10110 %
#115000
b110 "
b110 )
b101 !
b101 '
b101 (
b110 #
b110 &
b10111 %
#120000
b0 "
b0 )
b0 !
b0 '
b0 (
b0 #
b0 &
b11000 %
#125000
b101 "
b101 )
b111 !
b111 '
b111 (
b101 #
b101 &
b11001 %
#130000
b100 "
b100 )
b110 !
b110 '
b110 (
b100 #
b100 &
b11010 %
#135000
b101 "
b101 )
b111 !
b111 '
b111 (
b101 #
b101 &
b11011 %
#140000
b11100 %
#145000
b11101 %
#150000
b11 "
b11 )
b10 !
b10 '
b10 (
b11 #
b11 &
b11110 %
#155000
b10 "
b10 )
b11 !
b11 '
b11 (
b10 #
b10 &
b11111 %
#160000
b0 "
b0 )
b0 !
b0 '
b0 (
b0 #
b0 &
b100000 %
#165000
b100001 %
#170000
b10 "
b10 )
b11 !
b11 '
b11 (
b10 #
b10 &
b100010 %
#175000
b101 "
b101 )
b111 !
b111 '
b111 (
b101 #
b101 &
b100011 %
#180000
b110 "
b110 )
b101 !
b101 '
b101 (
b110 #
b110 &
b100100 %
#185000
b11 "
b11 )
b10 !
b10 '
b10 (
b11 #
b11 &
b100101 %
#190000
b101 "
b101 )
b111 !
b111 '
b111 (
b101 #
b101 &
b100110 %
#195000
b11 "
b11 )
b10 !
b10 '
b10 (
b11 #
b11 &
b100111 %
#200000
b101000 %
#205000
b101 "
b101 )
b111 !
b111 '
b111 (
b101 #
b101 &
b101001 %
#210000
b10 "
b10 )
b11 !
b11 '
b11 (
b10 #
b10 &
b101010 %
#215000
b110 "
b110 )
b101 !
b101 '
b101 (
b110 #
b110 &
b101011 %
#220000
b101 "
b101 )
b111 !
b111 '
b111 (
b101 #
b101 &
b101100 %
#225000
b111 "
b111 )
b100 !
b100 '
b100 (
b111 #
b111 &
b101101 %
#230000
b11 "
b11 )
b10 !
b10 '
b10 (
b11 #
b11 &
b101110 %
#235000
b10 "
b10 )
b11 !
b11 '
b11 (
b10 #
b10 &
b101111 %
#240000
b110000 %
#245000
b100 "
b100 )
b110 !
b110 '
b110 (
b100 #
b100 &
b110001 %
#250000
b10 "
b10 )
b11 !
b11 '
b11 (
b10 #
b10 &
b110010 %
#255000
b110011 %
#260000
b1 "
b1 )
b1 !
b1 '
b1 (
b1 #
b1 &
b110100 %
#265000
b0 "
b0 )
b0 !
b0 '
b0 (
b0 #
b0 &
b110101 %
#270000
b110110 %
#275000
b1 "
b1 )
b1 !
b1 '
b1 (
b1 #
b1 &
b110111 %
#280000
b11 "
b11 )
b10 !
b10 '
b10 (
b11 #
b11 &
b111000 %
#285000
b110 "
b110 )
b101 !
b101 '
b101 (
b110 #
b110 &
b111001 %
#290000
b111010 %
#295000
b111011 %
#300000
b100 "
b100 )
b110 !
b110 '
b110 (
b100 #
b100 &
b111100 %
#305000
b10 "
b10 )
b11 !
b11 '
b11 (
b10 #
b10 &
b111101 %
#310000
b11 "
b11 )
b10 !
b10 '
b10 (
b11 #
b11 &
b111110 %
#315000
b1 "
b1 )
b1 !
b1 '
b1 (
b1 #
b1 &
b111111 %
#320000
b101 "
b101 )
b111 !
b111 '
b111 (
b101 #
b101 &
b1000000 %
#325000
b111 "
b111 )
b100 !
b100 '
b100 (
b111 #
b111 &
b1000001 %
#330000
b11 "
b11 )
b10 !
b10 '
b10 (
b11 #
b11 &
b1000010 %
#335000
b10 "
b10 )
b11 !
b11 '
b11 (
b10 #
b10 &
b1000011 %
#340000
b110 "
b110 )
b101 !
b101 '
b101 (
b110 #
b110 &
b1000100 %
#345000
b101 "
b101 )
b111 !
b111 '
b111 (
b101 #
b101 &
b1000101 %
#350000
b1 "
b1 )
b1 !
b1 '
b1 (
b1 #
b1 &
b1000110 %
#355000
b1000111 %
#360000
b10 "
b10 )
b11 !
b11 '
b11 (
b10 #
b10 &
b1001000 %
#365000
b100 "
b100 )
b110 !
b110 '
b110 (
b100 #
b100 &
b1001001 %
#370000
b111 "
b111 )
b100 !
b100 '
b100 (
b111 #
b111 &
b1001010 %
#375000
b1001011 %
#380000
b0 "
b0 )
b0 !
b0 '
b0 (
b0 #
b0 &
b1001100 %
#385000
b111 "
b111 )
b100 !
b100 '
b100 (
b111 #
b111 &
b1001101 %
#390000
b1001110 %
#395000
b100 "
b100 )
b110 !
b110 '
b110 (
b100 #
b100 &
b1001111 %
#400000
b11 "
b11 )
b10 !
b10 '
b10 (
b11 #
b11 &
b1010000 %
#405000
b1 "
b1 )
b1 !
b1 '
b1 (
b1 #
b1 &
b1010001 %
#410000
b1010010 %
#415000
b0 "
b0 )
b0 !
b0 '
b0 (
b0 #
b0 &
b1010011 %
#420000
b111 "
b111 )
b100 !
b100 '
b100 (
b111 #
b111 &
b1010100 %
#425000
b1 "
b1 )
b1 !
b1 '
b1 (
b1 #
b1 &
b1010101 %
#430000
b110 "
b110 )
b101 !
b101 '
b101 (
b110 #
b110 &
b1010110 %
#435000
b100 "
b100 )
b110 !
b110 '
b110 (
b100 #
b100 &
b1010111 %
#440000
b10 "
b10 )
b11 !
b11 '
b11 (
b10 #
b10 &
b1011000 %
#445000
b0 "
b0 )
b0 !
b0 '
b0 (
b0 #
b0 &
b1011001 %
#450000
b111 "
b111 )
b100 !
b100 '
b100 (
b111 #
b111 &
b1011010 %
#455000
b101 "
b101 )
b111 !
b111 '
b111 (
b101 #
b101 &
b1011011 %
#460000
b10 "
b10 )
b11 !
b11 '
b11 (
b10 #
b10 &
b1011100 %
#465000
b110 "
b110 )
b101 !
b101 '
b101 (
b110 #
b110 &
b1011101 %
#470000
b101 "
b101 )
b111 !
b111 '
b111 (
b101 #
b101 &
b1011110 %
#475000
b1 "
b1 )
b1 !
b1 '
b1 (
b1 #
b1 &
b1011111 %
#480000
b111 "
b111 )
b100 !
b100 '
b100 (
b111 #
b111 &
b1100000 %
#485000
b11 "
b11 )
b10 !
b10 '
b10 (
b11 #
b11 &
b1100001 %
#490000
b101 "
b101 )
b111 !
b111 '
b111 (
b101 #
b101 &
b1100010 %
#495000
b0 "
b0 )
b0 !
b0 '
b0 (
b0 #
b0 &
b1100011 %
#500000
b1100100 %
