RV32I/core/common/riscv_configs.v
// ---------------------------------------------------
// RISC-V Integer Bit & Memory Specification
// ---------------------------------------------------
`define XLEN					32
`define	DMEM_ADDR_BIT			8
`define IMEM_ADDR_BIT			8

`define DMEM_INIT	
`define	DMEM_INIT_FILE			"riscv_dmem.mif"
`define	IMEM_INIT
`define	IMEM_INIT_FILE			"riscv_imem.mif"


// ---------------------------------------------------
// Immidiate Source
// ---------------------------------------------------
`define	SRC_IMM_R				3'b000
`define	SRC_IMM_I				3'b001
`define	SRC_IMM_S				3'b010
`define	SRC_IMM_B				3'b011
`define	SRC_IMM_U				3'b100
`define	SRC_IMM_J				3'b101


// ---------------------------------------------------
// ALU State
// ---------------------------------------------------
// 										{funct[7], funct3}
`define	ALU_CTRL_ADD 					4'b0000
`define	ALU_CTRL_SUB					4'b1000 
`define	ALU_CTRL_XOR					4'b0100 
`define	ALU_CTRL_OR 					4'b0110 
`define	ALU_CTRL_AND					4'b0111
`define	ALU_CTRL_SLL					4'b0001 
`define	ALU_CTRL_SRL					4'b0101 
`define	ALU_CTRL_SRA					4'b1101 
`define	ALU_CTRL_SLT					4'b0010 
`define	ALU_CTRL_SLTU					4'b0011

// ---------------------------------------------------
// Instructions opcodes
// ---------------------------------------------------
`define OPCODE_R_OP						7'b0110011
`define OPCODE_I_OP						7'b0010011
`define OPCODE_I_LOAD					7'b0000011
`define OPCODE_S_STORE					7'b0100011
`define OPCODE_B_BRANCH					7'b1100011
`define OPCODE_J_JAL					7'b1101111
`define OPCODE_I_JALR					7'b1100111
`define OPCODE_U_LUI					7'b0110111
`define OPCODE_U_AUIPC					7'b0010111

// ---------------------------------------------------
// Source (NEXT)PC 
// ---------------------------------------------------
`define SRC_PC_PC_4						2'b00
`define SRC_PC_PC_IMM					2'b01
`define SRC_PC_RS_IMM					2'b10

// ---------------------------------------------------
//	Source RD(Register file Write Data) 
// ---------------------------------------------------
`define SRC_RD_ALU						2'b00
`define SRC_RD_DME						2'b01
`define SRC_RD_PC4						2'b10
`define SRC_RD_IMM						2'b11

// ---------------------------------------------------
//	Source ALU
// ---------------------------------------------------
`define SRC_ALU_A_RS1					1'b0
`define SRC_ALU_A_PC					1'b1
`define SRC_ALU_B_RS2					1'b0
`define SRC_ALU_B_IMM					1'b1 

// ---------------------------------------------------
//	Funct3	for ALU
// ---------------------------------------------------
`define FUNCT3_ALU_ADD_SUB				3'b000 
`define FUNCT3_ALU_XOR					3'b001
`define FUNCT3_ALU_OR					3'b110
`define FUNCT3_ALU_AND					3'b111
`define FUNCT3_ALU_SLL					3'b001
`define FUNCT3_ALU_SRL_SRA				3'b101
`define FUNCT3_ALU_SLT					3'b010
`define FUNCT3_ALU_SLTU					3'b011

// ---------------------------------------------------
//	Funct3	for Branch
// ---------------------------------------------------
`define FUNCT3_BRANCH_BEQ				3'b000 
`define FUNCT3_BRANCH_BNE				3'b001 
`define FUNCT3_BRANCH_BLT				3'b100 
`define FUNCT3_BRANCH_BGE				3'b101 
`define FUNCT3_BRANCH_BLUT				3'b110 
`define FUNCT3_BRANCH_BGEU				3'b111 

// ---------------------------------------------------
//	Funct3	for LOAD/STORE
// ---------------------------------------------------
`define FUNCT3_MEM_BYTE					3'b000 				
`define FUNCT3_MEM_HALF					3'b001 
`define FUNCT3_MEM_WORD					3'b010 
`define FUNCT3_MEM_BYTEU				3'b100
`define FUNCT3_MEM_HALFU				3'b101

RV32I/core/common/riscv_alu.v
`include		"riscv_configs.v"

module	riscv_alu(
	input		[`XLEN-1:0] i_alu_a,
	input		[`XLEN-1:0] i_alu_b,
	input		[	   4:0] i_alu_ctrl,
	output					o_alu_zero,
	output	reg	[`XLEN-1:0]	o_alu_result
);

always @(*) begin
	case(i_alu_ctrl)
		`ALU_CTRL_ADD	:	o_alu_result = i_alu_a + i_alu_b;
		`ALU_CTRL_SUB	:	o_alu_result = i_alu_a - i_alu_b;
		`ALU_CTRL_XOR	:	o_alu_result = i_alu_a ^ i_alu_b;
		`ALU_CTRL_OR	: 	o_alu_result = i_alu_a | i_alu_b;
		`ALU_CTRL_AND	:	o_alu_result = i_alu_a & i_alu_b;
		`ALU_CTRL_SLL	:	o_alu_result = i_alu_a << i_alu_b[4:0];
		`ALU_CTRL_SRL	:	o_alu_result = i_alu_a >> i_alu_b[4:0];
		`ALU_CTRL_SRA	:	o_alu_result = $signed(i_alu_a) >>> $signed(i_alu_b[4:0]);
		`ALU_CTRL_SLT	:	o_alu_result = $signed(i_alu_a) < $signed(i_alu_b);
		`ALU_CTRL_SLTU	:	o_alu_result = i_alu_a < i_alu_b;
	endcase
end 

assign	o_alu_zero = (o_alu_result == 0) ? 1'b1 : 1'b0;

`ifdef	DEBUG
	reg			[8*8-1:0]	DEBUG_ALU_OP;
always @(*) begin
	case(i_alu_ctrl)
		`ALU_CTRL_ADD	:	DEBUG_ALU_OP	= "ADD ";
		`ALU_CTRL_SUB	:	DEBUG_ALU_OP	= "SUB ";
		`ALU_CTRL_XOR	:	DEBUG_ALU_OP	= "XOR ";
		`ALU_CTRL_OR	:	DEBUG_ALU_OP	= "OR ";
		`ALU_CTRL_AND	:	DEBUG_ALU_OP	= "AND ";
		`ALU_CTRL_SLL	:	DEBUG_ALU_OP	= "SLL ";
		`ALU_CTRL_SRL	:	DEBUG_ALU_OP	= "SRL ";
		`ALU_CTRL_SRA	:	DEBUG_ALU_OP	= "SRA ";
		`ALU_CTRL_SLT	:	DEBUG_ALU_OP	= "SLT ";
		`ALU_CTRL_SLTU	:	DEBUG_ALU_OP	= "SLTU ";
	endcase
end 
`endif 

endmodule

RV32I/core/common/riscv_alu_tb.v
//---------------------------------------------------
// Define Global Variable
//---------------------------------------------------
`define DEBUG
`define CLKFREQ			100
`define	SIMCYCLE		4

//---------------------------------------------------
// Includes
//---------------------------------------------------
`include "riscv_alu.v"

module riscv_alu_tb;
//---------------------------------------------------
// DUT Signals & Instantiate
//---------------------------------------------------
	reg			[`XLEN-1:0] i_alu_a;
	reg			[`XLEN-1:0] i_alu_b;
	reg			[	   4:0] i_alu_ctrl;
	wire					o_alu_zero;
	wire		[`XLEN-1:0]	o_alu_result;

	riscv_alu
	u_riscv_alu(
		.i_alu_a			(i_alu_a			),
		.i_alu_b			(i_alu_b			),
		.i_alu_ctrl			(i_alu_ctrl			),
		.o_alu_zero			(o_alu_zero			),
		.o_alu_result		(o_alu_result		)
	);

//---------------------------------------------------
// Task
//---------------------------------------------------
	reg		[8*32-1:0]	taskState;

	task init;
		begin
			i_alu_a		= 0;
			i_alu_b		= 0;
			i_alu_ctrl	= 0;
		end 
	endtask 

	task ADD;
		input [`XLEN-1:0] ti_alu_a; 
        input [`XLEN-1:0] ti_alu_b;
		begin
			taskState = "ADD";
			i_alu_ctrl = `ALU_CTRL_ADD;
			i_alu_a = ti_alu_a;
            i_alu_b = ti_alu_b;
		end 
	endtask 

	task SUB;
		input [`XLEN-1:0] ti_alu_a; 
        input [`XLEN-1:0] ti_alu_b;
		begin
			taskState = "SUB";
			i_alu_ctrl = `ALU_CTRL_SUB;
			i_alu_a = ti_alu_a;
            i_alu_b = ti_alu_b;
		end 
	endtask 

	task XOR;
		input [`XLEN-1:0] ti_alu_a; 
        input [`XLEN-1:0] ti_alu_b;
		begin
			taskState = "XOR";
			i_alu_ctrl = `ALU_CTRL_XOR;
			i_alu_a = ti_alu_a;
            i_alu_b = ti_alu_b;
		end 
	endtask 

	task OR;
		input [`XLEN-1:0] ti_alu_a; 
        input [`XLEN-1:0] ti_alu_b;
		begin
			taskState = "OR";
			i_alu_ctrl = `ALU_CTRL_OR;
			i_alu_a = ti_alu_a;
            i_alu_b = ti_alu_b;
		end 
	endtask 

	task AND;
		input [`XLEN-1:0] ti_alu_a; 
        input [`XLEN-1:0] ti_alu_b;
		begin
			taskState = "AND";
			i_alu_ctrl = `ALU_CTRL_AND;
			i_alu_a = ti_alu_a;
            i_alu_b = ti_alu_b;
		end 
	endtask 

	task SLL;
		input [`XLEN-1:0] ti_alu_a; 
        input [`XLEN-1:0] ti_alu_b;
		begin
			taskState = "SLL";
			i_alu_ctrl = `ALU_CTRL_SLL;
			i_alu_a = ti_alu_a;
            i_alu_b = ti_alu_b;
		end 
	endtask 

	task SRA;
		input [`XLEN-1:0] ti_alu_a; 
        input [`XLEN-1:0] ti_alu_b;
		begin
			taskState = "SRA";
			i_alu_ctrl = `ALU_CTRL_SRA;
			i_alu_a = ti_alu_a;
            i_alu_b = ti_alu_b;
		end 
	endtask 

	task SRL;
		input [`XLEN-1:0] ti_alu_a; 
        input [`XLEN-1:0] ti_alu_b;
		begin
			taskState = "SRL";
			i_alu_ctrl = `ALU_CTRL_SRL;
			i_alu_a = ti_alu_a;
            i_alu_b = ti_alu_b;
		end 
	endtask 

	task SLT;
		input [`XLEN-1:0] ti_alu_a; 
        input [`XLEN-1:0] ti_alu_b;
		begin
			taskState = "SLT";
			i_alu_ctrl = `ALU_CTRL_SLT;
			i_alu_a = ti_alu_a;
            i_alu_b = ti_alu_b;
		end 
	endtask

	task SLTU;
		input [`XLEN-1:0] ti_alu_a; 
        input [`XLEN-1:0] ti_alu_b;
		begin
			taskState = "SLTU";
			i_alu_ctrl = `ALU_CTRL_SLTU;
			i_alu_a = ti_alu_a;
            i_alu_b = ti_alu_b;
		end 
	endtask
//---------------------------------------------------
// Test Stimulus
//---------------------------------------------------
	integer		i, j;
	initial begin
		init();

		#(4*1000/`CLKFREQ);

		for(i=0; i<`SIMCYCLE; i++) begin
			#(1000/`CLKFREQ); ADD($urandom, $urandom);
			#(1000/`CLKFREQ); SUB($urandom, $urandom);
		end
		for(i=0; i<`SIMCYCLE; i++) begin
			#(1000/`CLKFREQ); XOR($urandom, $urandom);
			#(1000/`CLKFREQ); OR ($urandom, $urandom);
			#(1000/`CLKFREQ); AND($urandom, $urandom);
		end
		for(i=0; i<`SIMCYCLE; i++) begin
			#(1000/`CLKFREQ); SLT ($urandom, $urandom);
			#(1000/`CLKFREQ); SLTU($urandom, $urandom);
		end
		for(i=0; i<`SIMCYCLE; i++) begin
			#(1000/`CLKFREQ); SLL($urandom, i);
			#(1000/`CLKFREQ); SRL($urandom, i);
			#(1000/`CLKFREQ); SRA($urandom, i);
		end
		$finish;
	end 

//---------------------------------------------------
// Dump VCD
//---------------------------------------------------
	reg	[8*32-1:0]	vcd_file;
	initial begin
		if($value$plusargs("vcd_file=%s", vcd_file)) begin
			$dumpfile(vcd_file);
			$dumpvars;
		end
		else begin
			$dumpfile("alu_tb.vcd");
			$dumpvars;
		end 
	end 

endmodule

RV32I/core/common/vcd/riscv_alu.vcd
$date
	Thu Jul 18 16:55:54 2024
$end
$version
	Icarus Verilog
$end
$timescale
	1ps
$end
$scope module riscv_alu_tb $end
$var wire 1 ! o_alu_zero $end
$var wire 32 " o_alu_result [31:0] $end
$var reg 32 # i_alu_a [31:0] $end
$var reg 32 $ i_alu_b [31:0] $end
$var reg 5 % i_alu_ctrl [4:0] $end
$var reg 256 & taskState [255:0] $end
$var reg 256 ' vcd_file [255:0] $end
$var integer 32 ( i [31:0] $end
$scope module u_riscv_alu $end
$var wire 32 ) i_alu_a [31:0] $end
$var wire 32 * i_alu_b [31:0] $end
$var wire 5 + i_alu_ctrl [4:0] $end
$var wire 1 ! o_alu_zero $end
$var reg 64 , DEBUG_ALU_OP [63:0] $end
$var reg 32 - o_alu_result [31:0] $end
$upscope $end
$scope task ADD $end
$var reg 32 . ti_alu_a [31:0] $end
$var reg 32 / ti_alu_b [31:0] $end
$upscope $end
$scope task AND $end
$var reg 32 0 ti_alu_a [31:0] $end
$var reg 32 1 ti_alu_b [31:0] $end
$upscope $end
$scope task OR $end
$var reg 32 2 ti_alu_a [31:0] $end
$var reg 32 3 ti_alu_b [31:0] $end
$upscope $end
$scope task SLL $end
$var reg 32 4 ti_alu_a [31:0] $end
$var reg 32 5 ti_alu_b [31:0] $end
$upscope $end
$scope task SLT $end
$var reg 32 6 ti_alu_a [31:0] $end
$var reg 32 7 ti_alu_b [31:0] $end
$upscope $end
$scope task SLTU $end
$var reg 32 8 ti_alu_a [31:0] $end
$var reg 32 9 ti_alu_b [31:0] $end
$upscope $end
$scope task SRA $end
$var reg 32 : ti_alu_a [31:0] $end
$var reg 32 ; ti_alu_b [31:0] $end
$upscope $end
$scope task SRL $end
$var reg 32 < ti_alu_a [31:0] $end
$var reg 32 = ti_alu_b [31:0] $end
$upscope $end
$scope task SUB $end
$var reg 32 > ti_alu_a [31:0] $end
$var reg 32 ? ti_alu_b [31:0] $end
$upscope $end
$scope task XOR $end
$var reg 32 @ ti_alu_a [31:0] $end
$var reg 32 A ti_alu_b [31:0] $end
$upscope $end
$scope task init $end
$upscope $end
$upscope $end
$enddefinitions $end
#0
$dumpvars
bx A
bx @
bx ?
bx >
bx =
bx <
bx ;
bx :
bx 9
bx 8
bx 7
bx 6
bx 5
bx 4
bx 3
bx 2
bx 1
bx 0
bx /
bx .
b0 -
b1000001010001000100010000100000 ,
b0 +
b0 *
b0 )
bx (
b101110001011110111011001100011011001000010111101110010011010010111001101100011011101100101111101100001011011000111010100101110011101100110001101100100 '
bx &
b0 %
b0 $
b0 #
b0 "
1!
$end
#40000
b0 (
#50000
0!
b11010010100111101001001110100101 "
b11010010100111101001001110100101 -
b1000000100010010101111010000001 $
b1000000100010010101111010000001 *
b10010010000101010011010100100100 #
b10010010000101010011010100100100 )
b10000010100010001000100 &
b1000000100010010101111010000001 /
b10010010000101010011010100100100 .
#60000
b1010011010101010100001000100000 ,
b11010010100101000111111110100110 "
b11010010100101000111111110100110 -
b1 (
b110001111100000101011001100011 $
b110001111100000101011001100011 *
b100100001001101011000001001 #
b100100001001101011000001001 )
b1000 %
b1000 +
b10100110101010101000010 &
b110001111100000101011001100011 ?
b100100001001101011000001001 >
#70000
b1000001010001000100010000100000 ,
b1001101100110010001010010011010 "
b1001101100110010001010010011010 -
b11000110110111111001100110001101 $
b11000110110111111001100110001101 *
b10000110101110010111101100001101 #
b10000110101110010111101100001101 )
b0 %
b0 +
b10000010100010001000100 &
b11000110110111111001100110001101 /
b10000110101110010111101100001101 .
#80000
b1010011010101010100001000100000 ,
b101001100010110011001001010011 "
b101001100010110011001001010011 -
b10 (
b1001001101110101001000010010 $
b1001001101110101001000010010 *
b110010110000101000010001100101 #
b110010110000101000010001100101 )
b1000 %
b1000 +
b10100110101010101000010 &
b1001001101110101001000010010 ?
b110010110000101000010001100101 >
#90000
b1000001010001000100010000100000 ,
b111110010111011000000001110 "
b111110010111011000000001110 -
b10000110110101111100110100001101 $
b10000110110101111100110100001101 *
b10000000111100111110001100000001 #
b10000000111100111110001100000001 )
b0 %
b0 +
b10000010100010001000100 &
b10000110110101111100110100001101 /
b10000000111100111110001100000001 .
#100000
b1010011010101010100001000100000 ,
b11100100101100010010000111001 "
b11100100101100010010000111001 -
b11 (
b10011110100011011100110100111101 $
b10011110100011011100110100111101 *
b10111011001000111111000101110110 #
b10111011001000111111000101110110 )
b1000 %
b1000 +
b10100110101010101000010 &
b10011110100011011100110100111101 ?
b10111011001000111111000101110110 >
#110000
b1000001010001000100010000100000 ,
b10111101000000100100111101111001 "
b10111101000000100100111101111001 -
b11000110001011011111011110001100 $
b11000110001011011111011110001100 *
b11110110110101000101011111101101 #
b11110110110101000101011111101101 )
b0 %
b0 +
b10000010100010001000100 &
b11000110001011011111011110001100 /
b11110110110101000101011111101101 .
#120000
b1010011010101010100001000100000 ,
b10011001110001101100010100110011 "
b10011001110001101100010100110011 -
b0 (
b1100011001101110010010011000110 $
b1100011001101110010010011000110 *
b11111100111111011110100111111001 #
b11111100111111011110100111111001 )
b1000 %
b1000 +
b10100110101010101000010 &
b1100011001101110010010011000110 ?
b11111100111111011110100111111001 >
#130000
b1011000010011110101001000100000 ,
b110111111001000101011001101111 "
b110111111001000101011001101111 -
b1010101000100111101001010101010 $
b1010101000100111101001010101010 *
b1100010111101111000010011000101 #
b1100010111101111000010011000101 )
b100 %
b100 +
b10110000100111101010010 &
b1010101000100111101001010101010 A
b1100010111101111000010011000101 @
#140000
b10011110101001000100000 ,
b11111011111111111111011111110111 "
b11111011111111111111011111110111 -
b111011110100100111001001110111 $
b111011110100100111001001110111 *
b11110010101011111111011111100101 #
b11110010101011111111011111100101 )
b110 %
b110 +
b100111101010010 &
b111011110100100111001001110111 3
b11110010101011111111011111100101 2
#150000
b1000001010011100100010000100000 ,
b1001000001101001000000010 "
b1001000001101001000000010 -
b1 (
b11000111111011001101101110001111 $
b11000111111011001101101110001111 *
b1001001100101101011000010010 #
b1001001100101101011000010010 )
b111 %
b111 +
b10000010100111001000100 &
b11000111111011001101101110001111 1
b1001001100101101011000010010 0
#160000
b1011000010011110101001000100000 ,
b10011110010001101111111100111100 "
b10011110010001101111111100111100 -
b1100111011101101001011011001110 $
b1100111011101101001011011001110 *
b11111001001100000110100111110010 #
b11111001001100000110100111110010 )
b100 %
b100 +
b10110000100111101010010 &
b1100111011101101001011011001110 A
b11111001001100000110100111110010 @
#170000
b10011110101001000100000 ,
b1110110110010100111111011101101 "
b1110110110010100111111011101101 -
b1100010110010100100111011000101 $
b1100010110010100100111011000101 *
b1110100000000000111101011101000 #
b1110100000000000111101011101000 )
b110 %
b110 +
b100111101010010 &
b1100010110010100100111011000101 3
b1110100000000000111101011101000 2
#180000
b1000001010011100100010000100000 ,
b1110000010000000100000011100 "
b1110000010000000100000011100 -
b10 (
b1011110100011100010100010111101 $
b1011110100011100010100010111101 *
b10101110010110000100100101011100 #
b10101110010110000100100101011100 )
b111 %
b111 +
b10000010100111001000100 &
b1011110100011100010100010111101 1
b10101110010110000100100101011100 0
#190000
b1011000010011110101001000100000 ,
b100100000011000111111001001000 "
b100100000011000111111001001000 -
b110010101001110010011001100101 $
b110010101001110010011001100101 *
b10110101010110101100000101101 #
b10110101010110101100000101101 )
b100 %
b100 +
b10110000100111101010010 &
b110010101001110010011001100101 A
b10110101010110101100000101101 @
#200000
b10011110101001000100000 ,
b10110101111111111110011101101011 "
b10110101111111111110011101101011 -
b10000101011100111000011100001010 $
b10000101011100111000011100001010 *
b110001111011110110001001100011 #
b110001111011110110001001100011 )
b110 %
b110 +
b100111101010010 &
b10000101011100111000011100001010 3
b110001111011110110001001100011 2
#210000
b1000001010011100100010000100000 ,
b1000000010000000000000 "
b1000000010000000000000 -
b11 (
b10010000011001000010000100100000 $
b10010000011001000010000100100000 *
b1000000001110110010001010000000 #
b1000000001110110010001010000000 )
b111 %
b111 +
b10000010100111001000100 &
b10010000011001000010000100100000 1
b1000000001110110010001010000000 0
#220000
b1011000010011110101001000100000 ,
b10011011101101001000100100110111 "
b10011011101101001000100100110111 -
b1001110110011001100110010011101 $
b1001110110011001100110010011101 *
b11010101011110000100010110101010 #
b11010101011110000100010110101010 )
b100 %
b100 +
b10110000100111101010010 &
b1001110110011001100110010011101 A
b11010101011110000100010110101010 @
#230000
b10011110101001000100000 ,
b1001011101000111011111010010111 "
b1001011101000111011111010010111 -
b1001100000111011100000010011 $
b1001100000111011100000010011 *
b1001011001000000011111010010110 #
b1001011001000000011111010010110 )
b110 %
b110 +
b100111101010010 &
b1001100000111011100000010011 3
b1001011001000000011111010010110 2
#240000
b1000001010011100100010000100000 ,
b101001000001000000000001 "
b101001000001000000000001 -
b0 (
b101001101001111101011001010011 $
b101001101001111101011001010011 *
b110101111000011100000001101 #
b110101111000011100000001101 )
b111 %
b111 +
b10000010100111001000100 &
b101001101001111101011001010011 1
b110101111000011100000001101 0
#250000
b1010011010011000101010000100000 ,
b1 "
b1 -
b1101010101001100010101011010101 $
b1101010101001100010101011010101 *
b10110101100111111101110101101011 #
b10110101100111111101110101101011 )
b10 %
b10 +
b10100110100110001010100 &
b1101010101001100010101011010101 7
b10110101100111111101110101101011 6
#260000
b101001101001100010101000101010100100000 ,
b1 (
b1010111010101100011111010101110 $
b1010111010101100011111010101110 *
b1000101110100101000000010 #
b1000101110100101000000010 )
b11 %
b11 +
b1010011010011000101010001010101 &
b1010111010101100011111010101110 9
b1000101110100101000000010 8
#270000
b1010011010011000101010000100000 ,
b1100111110001010111001011001111 $
b1100111110001010111001011001111 *
b10001110111111111110100100011101 #
b10001110111111111110100100011101 )
b10 %
b10 +
b10100110100110001010100 &
b1100111110001010111001011001111 7
b10001110111111111110100100011101 6
#280000
1!
b101001101001100010101000101010100100000 ,
b0 "
b0 -
b10 (
b10000101000010010110010100001010 $
b10000101000010010110010100001010 *
b10010001100001000100100100100011 #
b10010001100001000100100100100011 )
b11 %
b11 +
b1010011010011000101010001010101 &
b10000101000010010110010100001010 9
b10010001100001000100100100100011 8
#290000
b1010011010011000101010000100000 ,
b11110001100010100110000111100 $
b11110001100010100110000111100 *
b1100101011100110000101011001010 #
b1100101011100110000101011001010 )
b10 %
b10 +
b10100110100110001010100 &
b11110001100010100110000111100 7
b1100101011100110000101011001010 6
#300000
b101001101001100010101000101010100100000 ,
b11 (
b11000101001011100110000110001010 $
b11000101001011100110000110001010 *
b11111001011010001011110111110010 #
b11111001011010001011110111110010 )
b11 %
b11 +
b1010011010011000101010001010101 &
b11000101001011100110000110001010 9
b11111001011010001011110111110010 8
#310000
0!
b1010011010011000101010000100000 ,
b1 "
b1 -
b1101100010010110011010011011000 $
b1101100010010110011010011011000 *
b10100000110001001011001101000001 #
b10100000110001001011001101000001 )
b10 %
b10 +
b10100110100110001010100 &
b1101100010010110011010011011000 7
b10100000110001001011001101000001 6
#320000
1!
b101001101001100010101000101010100100000 ,
b0 "
b0 -
b0 (
b1000100100010100001001010001001 $
b1000100100010100001001010001001 *
b10111100001000001111001101111000 #
b10111100001000001111001101111000 )
b11 %
b11 +
b1010011010011000101010001010101 &
b1000100100010100001001010001001 9
b10111100001000001111001101111000 8
#330000
0!
b1010011010011000100110000100000 ,
b11110101110001010000110111101011 "
b11110101110001010000110111101011 -
b0 $
b0 *
b11110101110001010000110111101011 #
b11110101110001010000110111101011 )
b1 %
b1 +
b10100110100110001001100 &
b0 5
b11110101110001010000110111101011 4
#340000
b1010011010100100100110000100000 ,
b11011011000000100110010110110110 "
b11011011000000100110010110110110 -
b11011011000000100110010110110110 #
b11011011000000100110010110110110 )
b101 %
b101 +
b10100110101001001001100 &
b0 =
b11011011000000100110010110110110 <
#350000
b1010011010100100100000100100000 ,
b11100011010010111111100111000110 "
b11100011010010111111100111000110 -
b1 (
b11100011010010111111100111000110 #
b11100011010010111111100111000110 )
b1101 %
b1101 +
b10100110101001001000001 &
b0 ;
b11100011010010111111100111000110 :
#360000
b1010011010011000100110000100000 ,
b10101110001010100010011101011100 "
b10101110001010100010011101011100 -
b1 $
b1 *
b11010111000101010001001110101110 #
b11010111000101010001001110101110 )
b1 %
b1 +
b10100110100110001001100 &
b1 5
b11010111000101010001001110101110 4
#370000
b1010011010100100100110000100000 ,
b101111001110101000000101011110 "
b101111001110101000000101011110 -
b1011110011101010000001010111100 #
b1011110011101010000001010111100 )
b101 %
b101 +
b10100110101001001001100 &
b1 =
b1011110011101010000001010111100 <
#380000
b1010011010100100100000100100000 ,
b11001010100001111110111010010101 "
b11001010100001111110111010010101 -
b10 (
b10010101000011111101110100101010 #
b10010101000011111101110100101010 )
b1101 %
b1101 +
b10100110101001001000001 &
b1 ;
b10010101000011111101110100101010 :
#390000
b1010011010011000100110000100000 ,
b10111010111100110100000101100 "
b10111010111100110100000101100 -
b10 $
b10 *
b101110101111001101000001011 #
b101110101111001101000001011 )
b1 %
b1 +
b10100110100110001001100 &
b10 5
b101110101111001101000001011 4
#400000
b1010011010100100100110000100000 ,
b1110001001011110111110011100 "
b1110001001011110111110011100 -
b111000100101111011111001110001 #
b111000100101111011111001110001 )
b101 %
b101 +
b10100110101001001001100 &
b10 =
b111000100101111011111001110001 <
#410000
b1010011010100100100000100100000 ,
b11110000101111001001000001100001 "
b11110000101111001001000001100001 -
b11 (
b11000010111100100100000110000101 #
b11000010111100100100000110000101 )
b1101 %
b1101 +
b10100110101001001000001 &
b10 ;
b11000010111100100100000110000101 :
#420000
b1010011010011000100110000100000 ,
b111111100100101010101001111000 "
b111111100100101010101001111000 -
b11 $
b11 *
b10100111111100100101010101001111 #
b10100111111100100101010101001111 )
b1 %
b1 +
b10100110100110001001100 &
b11 5
b10100111111100100101010101001111 4
#430000
b1010011010100100100110000100000 ,
b11101110011000110000000111 "
b11101110011000110000000111 -
b11101110011000110000000111011 #
b11101110011000110000000111011 )
b101 %
b101 +
b10100110101001001001100 &
b11 =
b11101110011000110000000111011 <
#440000
b1010011010100100100000100100000 ,
b11110011101000001100011001100111 "
b11110011101000001100011001100111 -
b100 (
b10011101000001100011001100111010 #
b10011101000001100011001100111010 )
b1101 %
b1101 +
b10100110101001001000001 &
b11 ;
b10011101000001100011001100111010 :
