projects/w3_sequential_logic/dff/resettable_dff.v
module dff_sync(
	output	reg	[3:0]		o_q,
	input		[3:0]		i_d,
	input					i_clk,
	input					i_rstn
);

always @(posedge i_clk) begin
	if(!i_rstn) begin
		o_q <= 4'h0;
	end
	else begin
		o_q <= i_d;
	end
end

endmodule

module dff_async(
	output	reg		[3:0]	o_q,
	input			[3:0]	i_d,
	input					i_clk,
	input					i_rstn
);

always @(posedge i_clk or negedge i_rstn) begin
	if(!i_rstn) begin
		o_q <= 4'h0;
	end
	else begin
		o_q <= i_d;
	end
end

endmodule

w3_sequential_logic/resettable_dff_tb.v
`define		CLKFREQ		100
`define		SIMCYCLE	100

`include "resettable_dff.v"

module resettable_dff_tb;


	wire	[3:0]		o_q_sync;
	wire	[3:0] 		o_q_async;
	reg		[3:0]		i_d;
	reg					i_clk;
	reg					i_rstn;

	dff_sync
	u_dff_sync(
		.o_q				(o_q_sync			),
		.i_d				(i_d				),
		.i_clk				(i_clk				),
		.i_rstn				(i_rstn				)
	);

	dff_async
	u_dff_async(
		.o_q				(o_q_async			),
		.i_d				(i_d				),
		.i_clk				(i_clk				),
		.i_rstn				(i_rstn				)
	);
//------------------------------------------------------------------------------------------------------
// Clock
//------------------------------------------------------------------------------------------------------
always #(500/`CLKFREQ) i_clk = ~i_clk;


//------------------------------------------------------------------------------------------------------
// Task
//------------------------------------------------------------


	task init;
		begin
			i_d = 0;
			i_clk = 0;
			i_rstn = 0;
		end
	endtask

	task resetReleaseAfterNCycles;
		input	[9:0]	n;
		begin
			#(n*1000/`CLKFREQ);
			i_rstn = 1'b1;
		end
	endtask	

integer i, j;

	initial begin
		init();
		resetReleaseAfterNCycles(4);

		for(i = 0; i < `SIMCYCLE; i++) begin
			j	= $urandom_range(0, 10);
			#(((j * 0.1)) * 1000/`CLKFREQ);
			i_d		= $urandom;
			i_rstn 	= $urandom;
			#((1-(j * 0.1)) * 1000/`CLKFREQ);
		end
		$finish;
	end

// --------------------------------------------------
//	Dump VCD
// --------------------------------------------------
	reg	[8*32-1:0]	vcd_file;
	initial begin
		if ($value$plusargs("vcd_file=%s", vcd_file)) begin
			$dumpfile(vcd_file);
			$dumpvars;
		end 
		else begin
			$dumpfile("resettable_dff_tb.vcd");
			$dumpvars;
		end
	end

endmodule

w3_sequential_logic/vcd/resettable_dff.vcd
$date
	Mon Jun 24 15:08:18 2024
$end
$version
	Icarus Verilog
$end
$timescale
	1ps
$end
$scope module resettable_dff_tb $end
$var wire 4 ! o_q_sync [3:0] $end
$var wire 4 " o_q_async [3:0] $end
$var reg 1 # i_clk $end
$var reg 4 $ i_d [3:0] $end
$var reg 1 % i_rstn $end
$var reg 256 & vcd_file [255:0] $end
$var integer 32 ' i [31:0] $end
$var integer 32 ( j [31:0] $end
$scope module u_dff_async $end
$var wire 1 # i_clk $end
$var wire 4 ) i_d [3:0] $end
$var wire 1 % i_rstn $end
$var reg 4 * o_q [3:0] $end
$upscope $end
$scope module u_dff_sync $end
$var wire 1 # i_clk $end
$var wire 4 + i_d [3:0] $end
$var wire 1 % i_rstn $end
$var reg 4 , o_q [3:0] $end
$upscope $end
$scope task init $end
$upscope $end
$scope task resetReleaseAfterNCycles $end
$var reg 10 - n [9:0] $end
$upscope $end
$upscope $end
$enddefinitions $end
#0
$dumpvars
b100 -
bx ,
b0 +
b0 *
b0 )
bx (
bx '
b1011100010111101110110011000110110010000101111011100100110010101110011011001010111010001110100011000010110001001101100011001010101111101100100011001100110011000101110011101100110001101100100 &
0%
b0 $
0#
b0 "
bx !
$end
#5000
b0 !
b0 ,
1#
#10000
0#
#15000
1#
#20000
0#
#25000
1#
#30000
0#
#35000
1#
#40000
0#
b110 (
b0 '
1%
#45000
1#
#46000
b1 $
b1 )
b1 +
#50000
b10 (
b1 '
0#
#52000
b1101 $
b1101 )
b1101 +
#55000
b1101 "
b1101 *
b1101 !
b1101 ,
1#
#60000
0#
b10 '
#62000
b10 $
b10 )
b10 +
#65000
b10 "
b10 *
b10 !
b10 ,
1#
#70000
0#
b101 (
b11 '
#75000
b110 "
b110 *
b110 !
b110 ,
1#
b110 $
b110 )
b110 +
#80000
0#
b1010 (
b100 '
#85000
1#
#90000
b100 (
b101 '
0#
b1100 $
b1100 )
b1100 +
#94000
b0 "
b0 *
0%
b101 $
b101 )
b101 +
#95000
b0 !
b0 ,
1#
#100000
0#
b1010 (
b110 '
#105000
1#
#110000
b1000 (
b111 '
0#
b111 $
b111 )
b111 +
#115000
1#
#118000
b10 $
b10 )
b10 +
#120000
b100 (
b1000 '
0#
#124000
b101 $
b101 )
b101 +
#125000
1#
#130000
0#
b1001 '
#134000
1%
b1101 $
b1101 )
b1101 +
#135000
b1101 "
b1101 *
b1101 !
b1101 ,
1#
#140000
0#
b10 (
b1010 '
#142000
b0 "
b0 *
0%
b1010 $
b1010 )
b1010 +
#145000
b0 !
b0 ,
1#
#150000
0#
b110 (
b1011 '
#155000
1#
#156000
1%
#160000
b11 (
b1100 '
0#
#163000
b11 $
b11 )
b11 +
#165000
b11 "
b11 *
b11 !
b11 ,
1#
#170000
0#
b1 (
b1101 '
#171000
b1011 $
b1011 )
b1011 +
#175000
b1011 "
b1011 *
b1011 !
b1011 ,
1#
#180000
b1110 $
b1110 )
b1110 +
0#
b0 (
b1110 '
#185000
b1110 "
b1110 *
b1110 !
b1110 ,
1#
#190000
0#
b100 (
b1111 '
#194000
b0 "
b0 *
0%
b11 $
b11 )
b11 +
#195000
b0 !
b0 ,
1#
#200000
0#
b10000 '
#204000
b1100 $
b1100 )
b1100 +
#205000
1#
#210000
0#
b1000 (
b10001 '
#215000
1#
#218000
b1 $
b1 )
b1 +
#220000
b10010 '
0#
#225000
1#
#228000
1%
b1001 $
b1001 )
b1001 +
#230000
b1001 (
b10011 '
0#
#235000
b1001 "
b1001 *
b1001 !
b1001 ,
1#
#239000
b0 "
b0 *
0%
b110 $
b110 )
b110 +
#240000
b100 (
b10100 '
0#
#244000
1%
b1010 $
b1010 )
b1010 +
#245000
b1010 "
b1010 *
b1010 !
b1010 ,
1#
#250000
0#
b10 (
b10101 '
#252000
b101 $
b101 )
b101 +
#255000
b101 "
b101 *
b101 !
b101 ,
1#
#260000
0#
b1 (
b10110 '
#261000
b0 "
b0 *
0%
b1010 $
b1010 )
b1010 +
#265000
b0 !
b0 ,
1#
#270000
0#
b101 (
b10111 '
#275000
b1 "
b1 *
b1 !
b1 ,
1#
1%
b1 $
b1 )
b1 +
#280000
0#
b111 (
b11000 '
#285000
1#
#287000
b1100 $
b1100 )
b1100 +
#290000
b1000 (
b11001 '
0#
#295000
b1100 "
b1100 *
b1100 !
b1100 ,
1#
#298000
b1000 $
b1000 )
b1000 +
#300000
b11 (
b11010 '
0#
#303000
b1100 $
b1100 )
b1100 +
#305000
1#
#310000
0#
b1000 (
b11011 '
#315000
1#
#318000
b0 "
b0 *
0%
b1001 $
b1001 )
b1001 +
#320000
b100 (
b11100 '
0#
#324000
b1 $
b1 )
b1 +
#325000
b0 !
b0 ,
1#
#330000
0#
b101 (
b11101 '
#335000
1#
b10 $
b10 )
b10 +
#340000
0#
b10 (
b11110 '
#342000
b1101 $
b1101 )
b1101 +
#345000
1#
#350000
0#
b11111 '
#352000
1%
#355000
b1101 "
b1101 *
b1101 !
b1101 ,
1#
#360000
0#
b110 (
b100000 '
#365000
1#
#366000
b11 $
b11 )
b11 +
#370000
b10 (
b100001 '
0#
#372000
b1011 $
b1011 )
b1011 +
#375000
b1011 "
b1011 *
b1011 !
b1011 ,
1#
#380000
0#
b1 (
b100010 '
#381000
b0 "
b0 *
0%
b1010 $
b1010 )
b1010 +
#385000
b0 !
b0 ,
1#
#390000
0#
b10 (
b100011 '
#392000
b1110 $
b1110 )
b1110 +
#395000
1#
#400000
0#
b1010 (
b100100 '
#405000
1#
#410000
b11 (
b100101 '
0#
1%
b110 $
b110 )
b110 +
#413000
b1111 $
b1111 )
b1111 +
#415000
b1111 "
b1111 *
b1111 !
b1111 ,
1#
#420000
0#
b10 (
b100110 '
#422000
b100 $
b100 )
b100 +
#425000
b100 "
b100 *
b100 !
b100 ,
1#
#430000
0#
b100 (
b100111 '
#434000
b0 "
b0 *
0%
b110 $
b110 )
b110 +
#435000
b0 !
b0 ,
1#
#440000
0#
b110 (
b101000 '
#445000
1#
#446000
b1101 $
b1101 )
b1101 +
#450000
b10 (
b101001 '
0#
#452000
1%
b101 $
b101 )
b101 +
#455000
b101 "
b101 *
b101 !
b101 ,
1#
#460000
0#
b1000 (
b101010 '
#465000
1#
#468000
b0 "
b0 *
0%
b100 $
b100 )
b100 +
#470000
b110 (
b101011 '
0#
#475000
b0 !
b0 ,
1#
#476000
b1011 $
b1011 )
b1011 +
#480000
b1010 (
b101100 '
0#
#485000
1#
#490000
b100 (
b101101 '
0#
1%
b1010 $
b1010 )
b1010 +
#494000
0%
b110 $
b110 )
b110 +
#495000
1#
#500000
0#
b10 (
b101110 '
#502000
b1010 $
b1010 )
b1010 +
#505000
1#
#510000
0#
b1 (
b101111 '
#511000
b1001 $
b1001 )
b1001 +
#515000
1#
#520000
0#
b1000 (
b110000 '
#525000
1#
#528000
b11 $
b11 )
b11 +
#530000
b1 (
b110001 '
0#
#531000
1%
b1011 $
b1011 )
b1011 +
#535000
b1011 "
b1011 *
b1011 !
b1011 ,
1#
#540000
0#
b1010 (
b110010 '
#545000
1#
#550000
b0 "
b0 *
b1001 (
b110011 '
0#
0%
b1101 $
b1101 )
b1101 +
#555000
b0 !
b0 ,
1#
#559000
1%
b110 $
b110 )
b110 +
#560000
b1 (
b110100 '
0#
#561000
b100 $
b100 )
b100 +
#565000
b100 "
b100 *
b100 !
b100 ,
1#
#570000
0#
b111 (
b110101 '
#575000
1#
#577000
b0 "
b0 *
0%
#580000
b110 (
b110110 '
0#
#585000
b0 !
b0 ,
1#
#586000
1%
b1101 $
b1101 )
b1101 +
#590000
b1 (
b110111 '
0#
#591000
0%
b1000 $
b1000 )
b1000 +
#595000
1#
#600000
0#
b101 (
b111000 '
#605000
1#
b1001 $
b1001 )
b1001 +
#610000
0#
b1000 (
b111001 '
#615000
1#
#618000
1%
b1010 $
b1010 )
b1010 +
#620000
b111 (
b111010 '
0#
#625000
b1010 "
b1010 *
b1010 !
b1010 ,
1#
#627000
b0 $
b0 )
b0 +
#630000
b1001 (
b111011 '
0#
#635000
b0 "
b0 *
b0 !
b0 ,
1#
#639000
0%
b1110 $
b1110 )
b1110 +
#640000
b1010 (
b111100 '
0#
#645000
1#
#650000
b110 (
b111101 '
0#
1%
b1010 $
b1010 )
b1010 +
#655000
b1010 "
b1010 *
b1010 !
b1010 ,
1#
#656000
b0 "
b0 *
0%
b110 $
b110 )
b110 +
#660000
b111110 '
0#
#665000
b0 !
b0 ,
1#
#666000
1%
#670000
b1010 (
b111111 '
0#
#675000
b110 "
b110 *
b110 !
b110 ,
1#
#680000
b0 "
b0 *
b1000 (
b1000000 '
0#
0%
#685000
b0 !
b0 ,
1#
#688000
1%
b1011 $
b1011 )
b1011 +
#690000
b1000001 '
0#
#695000
b1011 "
b1011 *
b1011 !
b1011 ,
1#
#698000
b1010 $
b1010 )
b1010 +
#700000
b101 (
b1000010 '
0#
#705000
b0 "
b0 *
b0 !
b0 ,
0%
b1 $
b1 )
b1 +
1#
#710000
b1 (
b1000011 '
0#
#711000
1%
b101 $
b101 )
b101 +
#715000
b101 "
b101 *
b101 !
b101 ,
1#
#720000
b1 $
b1 )
b1 +
0#
b0 (
b1000100 '
#725000
b1 "
b1 *
b1 !
b1 ,
1#
#730000
0#
b11 (
b1000101 '
#733000
b1011 $
b1011 )
b1011 +
#735000
b1011 "
b1011 *
b1011 !
b1011 ,
1#
#740000
0#
b101 (
b1000110 '
#745000
b0 !
b0 ,
b0 "
b0 *
1#
0%
b1010 $
b1010 )
b1010 +
#750000
0#
b11 (
b1000111 '
#753000
1%
b1001 $
b1001 )
b1001 +
#755000
b1001 "
b1001 *
b1001 !
b1001 ,
1#
#760000
0#
b101 (
b1001000 '
#765000
b110 "
b110 *
b110 !
b110 ,
1#
b110 $
b110 )
b110 +
#770000
0#
b110 (
b1001001 '
#775000
1#
#776000
b1010 $
b1010 )
b1010 +
#780000
b1000 (
b1001010 '
0#
#785000
b1010 "
b1010 *
b1010 !
b1010 ,
1#
#788000
b1000 $
b1000 )
b1000 +
#790000
b1001 (
b1001011 '
0#
#795000
b1000 "
b1000 *
b1000 !
b1000 ,
1#
#799000
b1010 $
b1010 )
b1010 +
#800000
b111 (
b1001100 '
0#
#805000
b1010 "
b1010 *
b1010 !
b1010 ,
1#
#807000
b0 "
b0 *
0%
b111 $
b111 )
b111 +
#810000
b1001 (
b1001101 '
0#
#815000
b0 !
b0 ,
1#
#819000
1%
b100 $
b100 )
b100 +
#820000
b1000 (
b1001110 '
0#
#825000
b100 "
b100 *
b100 !
b100 ,
1#
#830000
b10 (
b1001111 '
0#
#832000
b0 "
b0 *
0%
b1010 $
b1010 )
b1010 +
#835000
b0 !
b0 ,
1#
#840000
0#
b110 (
b1010000 '
#845000
1#
#846000
b1101 $
b1101 )
b1101 +
#850000
b100 (
b1010001 '
0#
#854000
1%
b1010 $
b1010 )
b1010 +
#855000
b1010 "
b1010 *
b1010 !
b1010 ,
1#
#860000
0#
b11 (
b1010010 '
#863000
b1110 $
b1110 )
b1110 +
#865000
b1110 "
b1110 *
b1110 !
b1110 ,
1#
#870000
b1111 $
b1111 )
b1111 +
0#
b0 (
b1010011 '
#875000
b1111 "
b1111 *
b1111 !
b1111 ,
1#
#880000
0#
b110 (
b1010100 '
#885000
1#
#886000
b101 $
b101 )
b101 +
#890000
b111 (
b1010101 '
0#
#895000
b101 "
b101 *
b101 !
b101 ,
1#
#897000
b0 "
b0 *
0%
b1000 $
b1000 )
b1000 +
#900000
b1000 (
b1010110 '
0#
#905000
b0 !
b0 ,
1#
#908000
b10 $
b10 )
b10 +
#910000
b1011 $
b1011 )
b1011 +
b0 (
b1010111 '
0#
#915000
1#
#920000
b1101 $
b1101 )
b1101 +
0#
b1011000 '
#925000
1#
#930000
0#
b110 (
b1011001 '
#935000
1#
#936000
b1 $
b1 )
b1 +
#940000
b1 (
b1011010 '
0#
#941000
b1011 $
b1011 )
b1011 +
#945000
1#
#950000
0#
b111 (
b1011011 '
#955000
1#
#957000
1%
b110 $
b110 )
b110 +
#960000
b100 (
b1011100 '
0#
#964000
b100 $
b100 )
b100 +
#965000
b100 "
b100 *
b100 !
b100 ,
1#
#970000
0#
b1011101 '
#974000
b0 "
b0 *
0%
b10 $
b10 )
b10 +
#975000
b0 !
b0 ,
1#
#980000
0#
b1 (
b1011110 '
#981000
1%
b101 $
b101 )
b101 +
#985000
b101 "
b101 *
b101 !
b101 ,
1#
#990000
0#
b110 (
b1011111 '
#995000
1#
#996000
b0 "
b0 *
0%
b1 $
b1 )
b1 +
#1000000
b1100000 '
0#
#1005000
b0 !
b0 ,
1#
#1006000
1%
#1010000
0%
b1000 $
b1000 )
b1000 +
b0 (
b1100001 '
0#
#1015000
1#
#1020000
0#
b101 (
b1100010 '
#1025000
1#
b10 $
b10 )
b10 +
#1030000
0#
b11 (
b1100011 '
#1033000
1%
b101 $
b101 )
b101 +
#1035000
b101 "
b101 *
b101 !
b101 ,
1#
#1040000
0#
b1100100 '
