w3_sequential_logic/spsram/spsram.v
module spsram
#(
    parameter   BW_DATA = 32,
    parameter   BW_ADDR = 5
)
(
    input                   i_clk,
    input   [BW_DATA-1:0]   i_data,
    input   [BW_ADDR-1:0]   i_addr,
    input                   i_wen,
    input                   i_cen,
    input                   i_oen,
    output  [BW_DATA-1:0]   o_data
)

///// Memory Write //////////
reg [BW_DATA-1:0] mem[0:2**BW_ADDR-1];

always @(posedge i_clk) begin
    if(i_cen && i_wen) begin
        mem[i_addr] <= i_data;
    end
    else begin
        mem[i_addr] <= mem[i_addr];
    end
end

///// Memory Read //////////
`ifdef SPSRMA_ASYNC
    assign o_data   =  !i_oen            ? 'bz          :
                        i_cen && i_wen   ? mem[i_addr]  :
                        'bx;
`else
    reg [BW_DATA-1:0] o_data;
    always @(posedge i_clk) begin
        if(i_oen) begin
            if(i_cen && !i_wen) begin
                o_data <= mem[i_addr];
            end
            else begin
                o_data <= 'bx;
            end
        end
        else begin
            o_data <= 'bz;
        end
    end
`endif

endmodule

project_0/06_sram_extension/spsram_extension.v
`include "spsram.v"

module spsram_extension
(
    input                   i_clk,
    input   [63:0]		    i_data,
    input   [5:0]   		i_addr,
    input                   i_wen,
    input                   i_cen,
    input                   i_oen,
    output  [63:0]   		o_data
);

	wire	[3:0]			cen;
	wire	[3:0]			oen;

	assign cen[0] = i_cen && (!i_addr[5]) && (!i_addr[4]);
	assign cen[1] = i_cen && (!i_addr[5]) &&  (i_addr[4]);
	assign cen[2] = i_cen &&  (i_addr[5]) && (!i_addr[4]);
	assign cen[3] = i_cen &&  (i_addr[5]) &&  (i_addr[4]);

	assign oen[0] = i_oen && (!i_addr[5]) && (!i_addr[4]);
	assign oen[1] = i_oen && (!i_addr[5]) &&  (i_addr[4]);
	assign oen[2] = i_oen &&  (i_addr[5]) && (!i_addr[4]);
	assign oen[3] = i_oen &&  (i_addr[5]) &&  (i_addr[4]);




	spsram
	#(
		.BW_DATA			(32					),
		.BW_ADDR			(4					)
	)
	u_spsram0(
		.i_clk				(i_clk				),
		.i_data				(i_data[31:0]		),
		.i_addr				(i_addr[3:0]		),
		.i_wen				(i_wen				),
		.i_cen				(cen[0]				),
		.i_oen				(oen[0]				),
		.o_data				(o_data[31:0]		)
	);

		spsram
	#(
		.BW_DATA			(32					),
		.BW_ADDR			(4					)
	)
	u_spsram1(
		.i_clk				(i_clk				),
		.i_data				(i_data[63:32]		),
		.i_addr				(i_addr[3:0]		),
		.i_wen				(i_wen				),
		.i_cen				(cen[0]				),
		.i_oen				(oen[0]				),
		.o_data				(o_data[63:32]		)
	);

	spsram
	#(
		.BW_DATA			(32					),
		.BW_ADDR			(4					)
	)
	u_spsram2(
		.i_clk				(i_clk				),
		.i_data				(i_data[31:0]		),
		.i_addr				(i_addr[3:0]		),
		.i_wen				(i_wen				),
		.i_cen				(cen[1]				),
		.i_oen				(oen[1]				),
		.o_data				(o_data[31:0]		)
	);

		spsram
	#(
		.BW_DATA			(32					),
		.BW_ADDR			(4					)
	)
	u_spsram3(
		.i_clk				(i_clk				),
		.i_data				(i_data[63:32]		),
		.i_addr				(i_addr[3:0]		),
		.i_wen				(i_wen				),
		.i_cen				(cen[1]				),
		.i_oen				(oen[1]				),
		.o_data				(o_data[63:32]		)
	);

	spsram
	#(
		.BW_DATA			(32					),
		.BW_ADDR			(4					)
	)
	u_spsram4(
		.i_clk				(i_clk				),
		.i_data				(i_data[31:0]		),
		.i_addr				(i_addr[3:0]		),
		.i_wen				(i_wen				),
		.i_cen				(cen[2]				),
		.i_oen				(oen[2]				),
		.o_data				(o_data[31:0]		)
	);

		spsram
	#(
		.BW_DATA			(32					),
		.BW_ADDR			(4					)
	)
	u_spsram5(
		.i_clk				(i_clk				),
		.i_data				(i_data[63:32]		),
		.i_addr				(i_addr[3:0]		),
		.i_wen				(i_wen				),
		.i_cen				(cen[2]				),
		.i_oen				(oen[2]				),
		.o_data				(o_data[63:32]		)
	);

	spsram
	#(
		.BW_DATA			(32					),
		.BW_ADDR			(4					)
	)
	u_spsram6(
		.i_clk				(i_clk				),
		.i_data				(i_data[31:0]		),
		.i_addr				(i_addr[3:0]		),
		.i_wen				(i_wen				),
		.i_cen				(cen[3]				),
		.i_oen				(oen[3]				),
		.o_data				(o_data[31:0]		)
	);

		spsram
	#(
		.BW_DATA			(32					),
		.BW_ADDR			(4					)
	)
	u_spsram7(
		.i_clk				(i_clk				),
		.i_data				(i_data[63:32]		),
		.i_addr				(i_addr[3:0]		),
		.i_wen				(i_wen				),
		.i_cen				(cen[3]				),
		.i_oen				(oen[3]				),
		.o_data				(o_data[63:32]		)
	);

	endmodule

project_0/06_sram_extension/spsram_extension_tb.v
//-------------------------------------
// Define Global Variables
// ------------------------------------
`define CLKFREQ     100
`define SIMCYCLE    64

//`define SPSRAM_ASYNC

//-------------------------------------
// Includes
// ------------------------------------
`include "spsram_extension.v"

module spsram_extension_tb;
//-------------------------------------
// DUT Signals & Instantiate
// ------------------------------------
	reg                   	i_clk;
	reg   [63:0]		    i_data;
	reg    [5:0]   			i_addr;
	reg                   	i_wen;
	reg                   	i_cen;
	reg                   	i_oen;
	wire  [63:0]   			o_data;

	spsram_extension
	u_spsram_extension(
		.i_clk				(i_clk				),
		.i_data				(i_data				),
		.i_addr				(i_addr				),
		.i_wen				(i_wen				),
		.i_cen				(i_cen				),
		.i_oen				(i_oen				),
		.o_data				(o_data				)
	);



//---------------------------------------------------
// Clock
//---------------------------------------------------
always #(500/`CLKFREQ) i_clk = ~i_clk;

//---------------------------------------------------
// Tasks
//---------------------------------------------------
reg     [8*32-1:0]  taskState;

task init;
    begin
		taskState = "Init";
        i_clk   = 0;
        i_data  = 0;
        i_addr  = 0;
        i_wen   = 0;
        i_cen   = 0;
        i_oen   = 0;
    end
endtask

task memWR;
    input   [5:0]  ti_addr;
    input   [63:0]  ti_data;
    begin
        @(negedge i_clk) begin
            taskState   = "WR";
            i_data      = ti_data;
            i_addr      = ti_addr;
            i_wen       = 1'b1;
            i_cen       = 1'b1;
            i_oen       = 1'b0;
        end
    end
endtask

task memRD;
    input   [5:0]  ti_addr;
    begin
        @(negedge i_clk) begin
            taskState   = "RD";
            i_addr      = ti_addr;
            i_wen       = 1'b0;
            i_cen       = 1'b1;
            i_oen       = 1'b1;
        end
    end
endtask
//---------------------------------------------------
// Test Stimulus
//---------------------------------------------------
integer  i, j;
initial begin
    init();
    #(4*100/`CLKFREQ);

    for(i = 0; i < `SIMCYCLE; i++) begin
       memWR(i, 1'b1 << i);
    end
    for(i = 0; i < `SIMCYCLE; i++) begin
       memRD(i);
    end
	#100;
    $finish;
end

//---------------------------------------------------
// Dump VCD
//---------------------------------------------------

reg [8*32-1:0] vcd_file;
initial begin
    if($value$plusargs("vcd_file=%s", vcd_file)) begin
        $dumpfile(vcd_file);
        $dumpvars;
    end
    else begin
        $dumpfile("spsram_extension_tb.vcd");
        $dumpvars;     
    end
end

endmodule

project_0/06_sram_extension/vcd/spsram_extension.vcd
$date
	Tue Jul  2 15:54:02 2024
$end
$version
	Icarus Verilog
$end
$timescale
	1ps
$end
$scope module spsram_extension_tb $end
$var wire 64 ! o_data [63:0] $end
$var reg 6 " i_addr [5:0] $end
$var reg 1 # i_cen $end
$var reg 1 $ i_clk $end
$var reg 64 % i_data [63:0] $end
$var reg 1 & i_oen $end
$var reg 1 ' i_wen $end
$var reg 256 ( taskState [255:0] $end
$var reg 256 ) vcd_file [255:0] $end
$var integer 32 * i [31:0] $end
$scope module u_spsram_extension $end
$var wire 6 + i_addr [5:0] $end
$var wire 1 # i_cen $end
$var wire 1 $ i_clk $end
$var wire 64 , i_data [63:0] $end
$var wire 1 & i_oen $end
$var wire 1 ' i_wen $end
$var wire 64 - o_data [63:0] $end
$var wire 4 . oen [3:0] $end
$var wire 4 / cen [3:0] $end
$scope module u_spsram0 $end
$var wire 4 0 i_addr [3:0] $end
$var wire 1 1 i_cen $end
$var wire 1 $ i_clk $end
$var wire 32 2 i_data [31:0] $end
$var wire 1 3 i_oen $end
$var wire 1 ' i_wen $end
$var reg 32 4 o_data [31:0] $end
$upscope $end
$scope module u_spsram1 $end
$var wire 4 5 i_addr [3:0] $end
$var wire 1 6 i_cen $end
$var wire 1 $ i_clk $end
$var wire 32 7 i_data [31:0] $end
$var wire 1 8 i_oen $end
$var wire 1 ' i_wen $end
$var reg 32 9 o_data [31:0] $end
$upscope $end
$scope module u_spsram2 $end
$var wire 4 : i_addr [3:0] $end
$var wire 1 ; i_cen $end
$var wire 1 $ i_clk $end
$var wire 32 < i_data [31:0] $end
$var wire 1 = i_oen $end
$var wire 1 ' i_wen $end
$var reg 32 > o_data [31:0] $end
$upscope $end
$scope module u_spsram3 $end
$var wire 4 ? i_addr [3:0] $end
$var wire 1 @ i_cen $end
$var wire 1 $ i_clk $end
$var wire 32 A i_data [31:0] $end
$var wire 1 B i_oen $end
$var wire 1 ' i_wen $end
$var reg 32 C o_data [31:0] $end
$upscope $end
$scope module u_spsram4 $end
$var wire 4 D i_addr [3:0] $end
$var wire 1 E i_cen $end
$var wire 1 $ i_clk $end
$var wire 32 F i_data [31:0] $end
$var wire 1 G i_oen $end
$var wire 1 ' i_wen $end
$var reg 32 H o_data [31:0] $end
$upscope $end
$scope module u_spsram5 $end
$var wire 4 I i_addr [3:0] $end
$var wire 1 J i_cen $end
$var wire 1 $ i_clk $end
$var wire 32 K i_data [31:0] $end
$var wire 1 L i_oen $end
$var wire 1 ' i_wen $end
$var reg 32 M o_data [31:0] $end
$upscope $end
$scope module u_spsram6 $end
$var wire 4 N i_addr [3:0] $end
$var wire 1 O i_cen $end
$var wire 1 $ i_clk $end
$var wire 32 P i_data [31:0] $end
$var wire 1 Q i_oen $end
$var wire 1 ' i_wen $end
$var reg 32 R o_data [31:0] $end
$upscope $end
$scope module u_spsram7 $end
$var wire 4 S i_addr [3:0] $end
$var wire 1 T i_cen $end
$var wire 1 $ i_clk $end
$var wire 32 U i_data [31:0] $end
$var wire 1 V i_oen $end
$var wire 1 ' i_wen $end
$var reg 32 W o_data [31:0] $end
$upscope $end
$upscope $end
$scope task init $end
$upscope $end
$scope task memRD $end
$var reg 6 X ti_addr [5:0] $end
$upscope $end
$scope task memWR $end
$var reg 6 Y ti_addr [5:0] $end
$var reg 64 Z ti_data [63:0] $end
$upscope $end
$upscope $end
$enddefinitions $end
#0
$dumpvars
bx Z
bx Y
bx X
bx W
0V
b0 U
0T
b0 S
bx R
0Q
b0 P
0O
b0 N
bx M
0L
b0 K
0J
b0 I
bx H
0G
b0 F
0E
b0 D
bx C
0B
b0 A
0@
b0 ?
bx >
0=
b0 <
0;
b0 :
bx 9
08
b0 7
06
b0 5
bx 4
03
b0 2
01
b0 0
b0 /
b0 .
bx -
b0 ,
b0 +
bx *
b10111000101111011101100110001101100100001011110111001101110000011100110111001001100001011011010101111101100101011110000111010001100101011011100111001101101001011011110110111000101110011101100110001101100100 )
b1001001011011100110100101110100 (
0'
0&
b0 %
0$
0#
b0 "
bx !
$end
#4000
b1 Z
b0 Y
b0 *
#5000
bz 4
bz !
bz -
bz 9
bz >
bz C
bz H
bz M
bz R
bz W
1$
#10000
11
16
b1 /
b1 2
b1 <
b1 F
b1 P
b10 Z
b1 Y
b1 *
1#
1'
b1 %
b1 ,
b101011101010010 (
0$
#15000
1$
#20000
b1 0
b1 5
b1 :
b1 ?
b1 D
b1 I
b1 N
b1 S
b10 2
b10 <
b10 F
b10 P
b100 Z
b10 Y
b10 *
b1 "
b1 +
b10 %
b10 ,
0$
#25000
1$
#30000
b10 0
b10 5
b10 :
b10 ?
b10 D
b10 I
b10 N
b10 S
b100 2
b100 <
b100 F
b100 P
b1000 Z
b11 Y
b11 *
b10 "
b10 +
b100 %
b100 ,
0$
#35000
1$
#40000
b11 0
b11 5
b11 :
b11 ?
b11 D
b11 I
b11 N
b11 S
b1000 2
b1000 <
b1000 F
b1000 P
b10000 Z
b100 Y
b100 *
b11 "
b11 +
b1000 %
b1000 ,
0$
#45000
1$
#50000
b100 0
b100 5
b100 :
b100 ?
b100 D
b100 I
b100 N
b100 S
b10000 2
b10000 <
b10000 F
b10000 P
b100000 Z
b101 Y
b101 *
b100 "
b100 +
b10000 %
b10000 ,
0$
#55000
1$
#60000
b101 0
b101 5
b101 :
b101 ?
b101 D
b101 I
b101 N
b101 S
b100000 2
b100000 <
b100000 F
b100000 P
b1000000 Z
b110 Y
b110 *
b101 "
b101 +
b100000 %
b100000 ,
0$
#65000
1$
#70000
b110 0
b110 5
b110 :
b110 ?
b110 D
b110 I
b110 N
b110 S
b1000000 2
b1000000 <
b1000000 F
b1000000 P
b10000000 Z
b111 Y
b111 *
b110 "
b110 +
b1000000 %
b1000000 ,
0$
#75000
1$
#80000
b111 0
b111 5
b111 :
b111 ?
b111 D
b111 I
b111 N
b111 S
b10000000 2
b10000000 <
b10000000 F
b10000000 P
b100000000 Z
b1000 Y
b1000 *
b111 "
b111 +
b10000000 %
b10000000 ,
0$
#85000
1$
#90000
b1000 0
b1000 5
b1000 :
b1000 ?
b1000 D
b1000 I
b1000 N
b1000 S
b100000000 2
b100000000 <
b100000000 F
b100000000 P
b1000000000 Z
b1001 Y
b1001 *
b1000 "
b1000 +
b100000000 %
b100000000 ,
0$
#95000
1$
#100000
b1001 0
b1001 5
b1001 :
b1001 ?
b1001 D
b1001 I
b1001 N
b1001 S
b1000000000 2
b1000000000 <
b1000000000 F
b1000000000 P
b10000000000 Z
b1010 Y
b1010 *
b1001 "
b1001 +
b1000000000 %
b1000000000 ,
0$
#105000
1$
#110000
b1010 0
b1010 5
b1010 :
b1010 ?
b1010 D
b1010 I
b1010 N
b1010 S
b10000000000 2
b10000000000 <
b10000000000 F
b10000000000 P
b100000000000 Z
b1011 Y
b1011 *
b1010 "
b1010 +
b10000000000 %
b10000000000 ,
0$
#115000
1$
#120000
b1011 0
b1011 5
b1011 :
b1011 ?
b1011 D
b1011 I
b1011 N
b1011 S
b100000000000 2
b100000000000 <
b100000000000 F
b100000000000 P
b1000000000000 Z
b1100 Y
b1100 *
b1011 "
b1011 +
b100000000000 %
b100000000000 ,
0$
#125000
1$
#130000
b1100 0
b1100 5
b1100 :
b1100 ?
b1100 D
b1100 I
b1100 N
b1100 S
b1000000000000 2
b1000000000000 <
b1000000000000 F
b1000000000000 P
b10000000000000 Z
b1101 Y
b1101 *
b1100 "
b1100 +
b1000000000000 %
b1000000000000 ,
0$
#135000
1$
#140000
b1101 0
b1101 5
b1101 :
b1101 ?
b1101 D
b1101 I
b1101 N
b1101 S
b10000000000000 2
b10000000000000 <
b10000000000000 F
b10000000000000 P
b100000000000000 Z
b1110 Y
b1110 *
b1101 "
b1101 +
b10000000000000 %
b10000000000000 ,
0$
#145000
1$
#150000
b1110 0
b1110 5
b1110 :
b1110 ?
b1110 D
b1110 I
b1110 N
b1110 S
b100000000000000 2
b100000000000000 <
b100000000000000 F
b100000000000000 P
b1000000000000000 Z
b1111 Y
b1111 *
b1110 "
b1110 +
b100000000000000 %
b100000000000000 ,
0$
#155000
1$
#160000
b1111 0
b1111 5
b1111 :
b1111 ?
b1111 D
b1111 I
b1111 N
b1111 S
b1000000000000000 2
b1000000000000000 <
b1000000000000000 F
b1000000000000000 P
b10000000000000000 Z
b10000 Y
b10000 *
b1111 "
b1111 +
b1000000000000000 %
b1000000000000000 ,
0$
#165000
1$
#170000
01
06
1;
1@
b10 /
b0 0
b0 5
b0 :
b0 ?
b0 D
b0 I
b0 N
b0 S
b10000000000000000 2
b10000000000000000 <
b10000000000000000 F
b10000000000000000 P
b100000000000000000 Z
b10001 Y
b10001 *
b10000 "
b10000 +
b10000000000000000 %
b10000000000000000 ,
0$
#175000
1$
#180000
b1 0
b1 5
b1 :
b1 ?
b1 D
b1 I
b1 N
b1 S
b100000000000000000 2
b100000000000000000 <
b100000000000000000 F
b100000000000000000 P
b1000000000000000000 Z
b10010 Y
b10010 *
b10001 "
b10001 +
b100000000000000000 %
b100000000000000000 ,
0$
#185000
1$
#190000
b10 0
b10 5
b10 :
b10 ?
b10 D
b10 I
b10 N
b10 S
b1000000000000000000 2
b1000000000000000000 <
b1000000000000000000 F
b1000000000000000000 P
b10000000000000000000 Z
b10011 Y
b10011 *
b10010 "
b10010 +
b1000000000000000000 %
b1000000000000000000 ,
0$
#195000
1$
#200000
b11 0
b11 5
b11 :
b11 ?
b11 D
b11 I
b11 N
b11 S
b10000000000000000000 2
b10000000000000000000 <
b10000000000000000000 F
b10000000000000000000 P
b100000000000000000000 Z
b10100 Y
b10100 *
b10011 "
b10011 +
b10000000000000000000 %
b10000000000000000000 ,
0$
#205000
1$
#210000
b100 0
b100 5
b100 :
b100 ?
b100 D
b100 I
b100 N
b100 S
b100000000000000000000 2
b100000000000000000000 <
b100000000000000000000 F
b100000000000000000000 P
b1000000000000000000000 Z
b10101 Y
b10101 *
b10100 "
b10100 +
b100000000000000000000 %
b100000000000000000000 ,
0$
#215000
1$
#220000
b101 0
b101 5
b101 :
b101 ?
b101 D
b101 I
b101 N
b101 S
b1000000000000000000000 2
b1000000000000000000000 <
b1000000000000000000000 F
b1000000000000000000000 P
b10000000000000000000000 Z
b10110 Y
b10110 *
b10101 "
b10101 +
b1000000000000000000000 %
b1000000000000000000000 ,
0$
#225000
1$
#230000
b110 0
b110 5
b110 :
b110 ?
b110 D
b110 I
b110 N
b110 S
b10000000000000000000000 2
b10000000000000000000000 <
b10000000000000000000000 F
b10000000000000000000000 P
b100000000000000000000000 Z
b10111 Y
b10111 *
b10110 "
b10110 +
b10000000000000000000000 %
b10000000000000000000000 ,
0$
#235000
1$
#240000
b111 0
b111 5
b111 :
b111 ?
b111 D
b111 I
b111 N
b111 S
b100000000000000000000000 2
b100000000000000000000000 <
b100000000000000000000000 F
b100000000000000000000000 P
b1000000000000000000000000 Z
b11000 Y
b11000 *
b10111 "
b10111 +
b100000000000000000000000 %
b100000000000000000000000 ,
0$
#245000
1$
#250000
b1000 0
b1000 5
b1000 :
b1000 ?
b1000 D
b1000 I
b1000 N
b1000 S
b1000000000000000000000000 2
b1000000000000000000000000 <
b1000000000000000000000000 F
b1000000000000000000000000 P
b10000000000000000000000000 Z
b11001 Y
b11001 *
b11000 "
b11000 +
b1000000000000000000000000 %
b1000000000000000000000000 ,
0$
#255000
1$
#260000
b1001 0
b1001 5
b1001 :
b1001 ?
b1001 D
b1001 I
b1001 N
b1001 S
b10000000000000000000000000 2
b10000000000000000000000000 <
b10000000000000000000000000 F
b10000000000000000000000000 P
b100000000000000000000000000 Z
b11010 Y
b11010 *
b11001 "
b11001 +
b10000000000000000000000000 %
b10000000000000000000000000 ,
0$
#265000
1$
#270000
b1010 0
b1010 5
b1010 :
b1010 ?
b1010 D
b1010 I
b1010 N
b1010 S
b100000000000000000000000000 2
b100000000000000000000000000 <
b100000000000000000000000000 F
b100000000000000000000000000 P
b1000000000000000000000000000 Z
b11011 Y
b11011 *
b11010 "
b11010 +
b100000000000000000000000000 %
b100000000000000000000000000 ,
0$
#275000
1$
#280000
b1011 0
b1011 5
b1011 :
b1011 ?
b1011 D
b1011 I
b1011 N
b1011 S
b1000000000000000000000000000 2
b1000000000000000000000000000 <
b1000000000000000000000000000 F
b1000000000000000000000000000 P
b10000000000000000000000000000 Z
b11100 Y
b11100 *
b11011 "
b11011 +
b1000000000000000000000000000 %
b1000000000000000000000000000 ,
0$
#285000
1$
#290000
b1100 0
b1100 5
b1100 :
b1100 ?
b1100 D
b1100 I
b1100 N
b1100 S
b10000000000000000000000000000 2
b10000000000000000000000000000 <
b10000000000000000000000000000 F
b10000000000000000000000000000 P
b100000000000000000000000000000 Z
b11101 Y
b11101 *
b11100 "
b11100 +
b10000000000000000000000000000 %
b10000000000000000000000000000 ,
0$
#295000
1$
#300000
b1101 0
b1101 5
b1101 :
b1101 ?
b1101 D
b1101 I
b1101 N
b1101 S
b100000000000000000000000000000 2
b100000000000000000000000000000 <
b100000000000000000000000000000 F
b100000000000000000000000000000 P
b1000000000000000000000000000000 Z
b11110 Y
b11110 *
b11101 "
b11101 +
b100000000000000000000000000000 %
b100000000000000000000000000000 ,
0$
#305000
1$
#310000
b1110 0
b1110 5
b1110 :
b1110 ?
b1110 D
b1110 I
b1110 N
b1110 S
b1000000000000000000000000000000 2
b1000000000000000000000000000000 <
b1000000000000000000000000000000 F
b1000000000000000000000000000000 P
b10000000000000000000000000000000 Z
b11111 Y
b11111 *
b11110 "
b11110 +
b1000000000000000000000000000000 %
b1000000000000000000000000000000 ,
0$
#315000
1$
#320000
b1111 0
b1111 5
b1111 :
b1111 ?
b1111 D
b1111 I
b1111 N
b1111 S
b10000000000000000000000000000000 2
b10000000000000000000000000000000 <
b10000000000000000000000000000000 F
b10000000000000000000000000000000 P
b100000000000000000000000000000000 Z
b100000 Y
b100000 *
b11111 "
b11111 +
b10000000000000000000000000000000 %
b10000000000000000000000000000000 ,
0$
#325000
1$
#330000
1E
1J
01
06
0;
0@
b100 /
b0 0
b0 5
b0 :
b0 ?
b0 D
b0 I
b0 N
b0 S
b0 2
b1 7
b0 <
b1 A
b0 F
b1 K
b0 P
b1 U
b1000000000000000000000000000000000 Z
b100001 Y
b100001 *
b100000 "
b100000 +
b100000000000000000000000000000000 %
b100000000000000000000000000000000 ,
0$
#335000
1$
#340000
b1 0
b1 5
b1 :
b1 ?
b1 D
b1 I
b1 N
b1 S
b10 7
b10 A
b10 K
b10 U
b10000000000000000000000000000000000 Z
b100010 Y
b100010 *
b100001 "
b100001 +
b1000000000000000000000000000000000 %
b1000000000000000000000000000000000 ,
0$
#345000
1$
#350000
b10 0
b10 5
b10 :
b10 ?
b10 D
b10 I
b10 N
b10 S
b100 7
b100 A
b100 K
b100 U
b100000000000000000000000000000000000 Z
b100011 Y
b100011 *
b100010 "
b100010 +
b10000000000000000000000000000000000 %
b10000000000000000000000000000000000 ,
0$
#355000
1$
#360000
b11 0
b11 5
b11 :
b11 ?
b11 D
b11 I
b11 N
b11 S
b1000 7
b1000 A
b1000 K
b1000 U
b1000000000000000000000000000000000000 Z
b100100 Y
b100100 *
b100011 "
b100011 +
b100000000000000000000000000000000000 %
b100000000000000000000000000000000000 ,
0$
#365000
1$
#370000
b100 0
b100 5
b100 :
b100 ?
b100 D
b100 I
b100 N
b100 S
b10000 7
b10000 A
b10000 K
b10000 U
b10000000000000000000000000000000000000 Z
b100101 Y
b100101 *
b100100 "
b100100 +
b1000000000000000000000000000000000000 %
b1000000000000000000000000000000000000 ,
0$
#375000
1$
#380000
b101 0
b101 5
b101 :
b101 ?
b101 D
b101 I
b101 N
b101 S
b100000 7
b100000 A
b100000 K
b100000 U
b100000000000000000000000000000000000000 Z
b100110 Y
b100110 *
b100101 "
b100101 +
b10000000000000000000000000000000000000 %
b10000000000000000000000000000000000000 ,
0$
#385000
1$
#390000
b110 0
b110 5
b110 :
b110 ?
b110 D
b110 I
b110 N
b110 S
b1000000 7
b1000000 A
b1000000 K
b1000000 U
b1000000000000000000000000000000000000000 Z
b100111 Y
b100111 *
b100110 "
b100110 +
b100000000000000000000000000000000000000 %
b100000000000000000000000000000000000000 ,
0$
#395000
1$
#400000
b111 0
b111 5
b111 :
b111 ?
b111 D
b111 I
b111 N
b111 S
b10000000 7
b10000000 A
b10000000 K
b10000000 U
b10000000000000000000000000000000000000000 Z
b101000 Y
b101000 *
b100111 "
b100111 +
b1000000000000000000000000000000000000000 %
b1000000000000000000000000000000000000000 ,
0$
#405000
1$
#410000
b1000 0
b1000 5
b1000 :
b1000 ?
b1000 D
b1000 I
b1000 N
b1000 S
b100000000 7
b100000000 A
b100000000 K
b100000000 U
b100000000000000000000000000000000000000000 Z
b101001 Y
b101001 *
b101000 "
b101000 +
b10000000000000000000000000000000000000000 %
b10000000000000000000000000000000000000000 ,
0$
#415000
1$
#420000
b1001 0
b1001 5
b1001 :
b1001 ?
b1001 D
b1001 I
b1001 N
b1001 S
b1000000000 7
b1000000000 A
b1000000000 K
b1000000000 U
b1000000000000000000000000000000000000000000 Z
b101010 Y
b101010 *
b101001 "
b101001 +
b100000000000000000000000000000000000000000 %
b100000000000000000000000000000000000000000 ,
0$
#425000
1$
#430000
b1010 0
b1010 5
b1010 :
b1010 ?
b1010 D
b1010 I
b1010 N
b1010 S
b10000000000 7
b10000000000 A
b10000000000 K
b10000000000 U
b10000000000000000000000000000000000000000000 Z
b101011 Y
b101011 *
b101010 "
b101010 +
b1000000000000000000000000000000000000000000 %
b1000000000000000000000000000000000000000000 ,
0$
#435000
1$
#440000
b1011 0
b1011 5
b1011 :
b1011 ?
b1011 D
b1011 I
b1011 N
b1011 S
b100000000000 7
b100000000000 A
b100000000000 K
b100000000000 U
b100000000000000000000000000000000000000000000 Z
b101100 Y
b101100 *
b101011 "
b101011 +
b10000000000000000000000000000000000000000000 %
b10000000000000000000000000000000000000000000 ,
0$
#445000
1$
#450000
b1100 0
b1100 5
b1100 :
b1100 ?
b1100 D
b1100 I
b1100 N
b1100 S
b1000000000000 7
b1000000000000 A
b1000000000000 K
b1000000000000 U
b1000000000000000000000000000000000000000000000 Z
b101101 Y
b101101 *
b101100 "
b101100 +
b100000000000000000000000000000000000000000000 %
b100000000000000000000000000000000000000000000 ,
0$
#455000
1$
#460000
b1101 0
b1101 5
b1101 :
b1101 ?
b1101 D
b1101 I
b1101 N
b1101 S
b10000000000000 7
b10000000000000 A
b10000000000000 K
b10000000000000 U
b10000000000000000000000000000000000000000000000 Z
b101110 Y
b101110 *
b101101 "
b101101 +
b1000000000000000000000000000000000000000000000 %
b1000000000000000000000000000000000000000000000 ,
0$
#465000
1$
#470000
b1110 0
b1110 5
b1110 :
b1110 ?
b1110 D
b1110 I
b1110 N
b1110 S
b100000000000000 7
b100000000000000 A
b100000000000000 K
b100000000000000 U
b100000000000000000000000000000000000000000000000 Z
b101111 Y
b101111 *
b101110 "
b101110 +
b10000000000000000000000000000000000000000000000 %
b10000000000000000000000000000000000000000000000 ,
0$
#475000
1$
#480000
b1111 0
b1111 5
b1111 :
b1111 ?
b1111 D
b1111 I
b1111 N
b1111 S
b1000000000000000 7
b1000000000000000 A
b1000000000000000 K
b1000000000000000 U
b1000000000000000000000000000000000000000000000000 Z
b110000 Y
b110000 *
b101111 "
b101111 +
b100000000000000000000000000000000000000000000000 %
b100000000000000000000000000000000000000000000000 ,
0$
#485000
1$
#490000
0E
0J
1O
1T
b1000 /
b0 0
b0 5
b0 :
b0 ?
b0 D
b0 I
b0 N
b0 S
b10000000000000000 7
b10000000000000000 A
b10000000000000000 K
b10000000000000000 U
b10000000000000000000000000000000000000000000000000 Z
b110001 Y
b110001 *
b110000 "
b110000 +
b1000000000000000000000000000000000000000000000000 %
b1000000000000000000000000000000000000000000000000 ,
0$
#495000
1$
#500000
b1 0
b1 5
b1 :
b1 ?
b1 D
b1 I
b1 N
b1 S
b100000000000000000 7
b100000000000000000 A
b100000000000000000 K
b100000000000000000 U
b100000000000000000000000000000000000000000000000000 Z
b110010 Y
b110010 *
b110001 "
b110001 +
b10000000000000000000000000000000000000000000000000 %
b10000000000000000000000000000000000000000000000000 ,
0$
#505000
1$
#510000
b10 0
b10 5
b10 :
b10 ?
b10 D
b10 I
b10 N
b10 S
b1000000000000000000 7
b1000000000000000000 A
b1000000000000000000 K
b1000000000000000000 U
b1000000000000000000000000000000000000000000000000000 Z
b110011 Y
b110011 *
b110010 "
b110010 +
b100000000000000000000000000000000000000000000000000 %
b100000000000000000000000000000000000000000000000000 ,
0$
#515000
1$
#520000
b11 0
b11 5
b11 :
b11 ?
b11 D
b11 I
b11 N
b11 S
b10000000000000000000 7
b10000000000000000000 A
b10000000000000000000 K
b10000000000000000000 U
b10000000000000000000000000000000000000000000000000000 Z
b110100 Y
b110100 *
b110011 "
b110011 +
b1000000000000000000000000000000000000000000000000000 %
b1000000000000000000000000000000000000000000000000000 ,
0$
#525000
1$
#530000
b100 0
b100 5
b100 :
b100 ?
b100 D
b100 I
b100 N
b100 S
b100000000000000000000 7
b100000000000000000000 A
b100000000000000000000 K
b100000000000000000000 U
b100000000000000000000000000000000000000000000000000000 Z
b110101 Y
b110101 *
b110100 "
b110100 +
b10000000000000000000000000000000000000000000000000000 %
b10000000000000000000000000000000000000000000000000000 ,
0$
#535000
1$
#540000
b101 0
b101 5
b101 :
b101 ?
b101 D
b101 I
b101 N
b101 S
b1000000000000000000000 7
b1000000000000000000000 A
b1000000000000000000000 K
b1000000000000000000000 U
b1000000000000000000000000000000000000000000000000000000 Z
b110110 Y
b110110 *
b110101 "
b110101 +
b100000000000000000000000000000000000000000000000000000 %
b100000000000000000000000000000000000000000000000000000 ,
0$
#545000
1$
#550000
b110 0
b110 5
b110 :
b110 ?
b110 D
b110 I
b110 N
b110 S
b10000000000000000000000 7
b10000000000000000000000 A
b10000000000000000000000 K
b10000000000000000000000 U
b10000000000000000000000000000000000000000000000000000000 Z
b110111 Y
b110111 *
b110110 "
b110110 +
b1000000000000000000000000000000000000000000000000000000 %
b1000000000000000000000000000000000000000000000000000000 ,
0$
#555000
1$
#560000
b111 0
b111 5
b111 :
b111 ?
b111 D
b111 I
b111 N
b111 S
b100000000000000000000000 7
b100000000000000000000000 A
b100000000000000000000000 K
b100000000000000000000000 U
b100000000000000000000000000000000000000000000000000000000 Z
b111000 Y
b111000 *
b110111 "
b110111 +
b10000000000000000000000000000000000000000000000000000000 %
b10000000000000000000000000000000000000000000000000000000 ,
0$
#565000
1$
