projects/w3_sequential_logic/regfile/regfile.v
module regfile
#(
	parameter	MIF_FILE	= "regfile.mif",
    parameter   BW_DATA 	= 32,
    parameter   BW_ADDR 	= 5
)
(
    input                   i_clk,
    input                   i_rf_wr_en,
    input   [BW_ADDR-1:0]   i_rf_wr_addr,
    input   [BW_DATA-1:0]   i_rf_wr_data,
    input   [BW_ADDR-1:0]   i_rf_rd_addr0,
    input   [BW_ADDR-1:0]   i_rf_rd_addr1,
    output  [BW_DATA-1:0]   o_rf_rd_data0,
    output  [BW_DATA-1:0]   o_rf_rd_data1
);

    reg     [BW_DATA-1:0]   rf_arr[0:2**BW_ADDR-1];

    assign  o_rf_rd_data0   = rf_arr[i_rf_rd_addr0];
    assign  o_rf_rd_data1   = rf_arr[i_rf_rd_addr1];
	`ifdef MEM_INIT
		initial begin
			$readmemh(MIF_FILE, rf_arr);
		end
	`endif

    always @(posedge i_clk) begin
        if(i_rf_wr_en) begin
            rf_arr[i_rf_wr_addr] <= i_rf_wr_data;
        end
        else begin
            rf_arr[i_rf_wr_addr] <= rf_arr[i_rf_wr_addr];
        end
    end

	endmodule

projects/w3_sequential_logic/regfile/regfile_tb.v
//-------------------------------------
// Define Global Variables
// ------------------------------------
`define CLKFREQ     100
`define BW_DATA     16
`define BW_ADDR     4
`define SIMCYCLE    2**`BW_ADDR
`define MEM_INIT

//-------------------------------------
// Includes
// ------------------------------------
`include "regfile.v"

module regfile_tb;
//-------------------------------------
// DUT Signals & Instantiate
// ------------------------------------

    reg                     i_clk;
    reg                     i_rf_wr_en;
    reg   [`BW_ADDR-1:0]    i_rf_wr_addr;
    reg   [`BW_DATA-1:0]    i_rf_wr_data;
    reg   [`BW_ADDR-1:0]    i_rf_rd_addr0;
    reg   [`BW_ADDR-1:0]    i_rf_rd_addr1;
    wire  [`BW_DATA-1:0]    o_rf_rd_data0;
    wire  [`BW_DATA-1:0]    o_rf_rd_data1;


regfile
#(
    .BW_DATA        (   `BW_DATA        ),
    .BW_ADDR        (   `BW_ADDR        )
)
u_regfile(
    .i_clk          (   i_clk           ),
    .i_rf_wr_en     (   i_rf_wr_en      ),
    .i_rf_wr_addr   (   i_rf_wr_addr    ),
    .i_rf_wr_data   (   i_rf_wr_data    ),
    .i_rf_rd_addr0  (   i_rf_rd_addr0   ),
    .i_rf_rd_addr1  (   i_rf_rd_addr1   ),
    .o_rf_rd_data0  (   o_rf_rd_data0   ),
    .o_rf_rd_data1  (   o_rf_rd_data1   )
);


//---------------------------------------------------
// Clock
//---------------------------------------------------
always #(500/`CLKFREQ) i_clk = ~i_clk;

//---------------------------------------------------
// Tasks
//---------------------------------------------------
reg     [8*32-1:0]  taskState;

task init;
    begin
        i_clk           = 0;
        i_rf_wr_en      = 0;
        i_rf_wr_addr    = 0;
        i_rf_wr_data    = 0;
        i_rf_rd_addr0   = 0;
        i_rf_rd_addr1   = 0;
    end
endtask

task regWR;
    input   [`BW_ADDR-1:0]  ti_rf_wr_addr;
    input   [`BW_DATA-1:0]  ti_rf_wr_data;
    begin
        @(negedge i_clk) begin
            taskState   = "WR";
            i_rf_wr_data    = ti_rf_wr_data;
            i_rf_wr_addr    = ti_rf_wr_addr; 
            i_rf_wr_en  	= 1'b1;
        end
    end
endtask

task regRD;
    input   [`BW_ADDR-1:0]  ti_rf_rd_addr0;
    input   [`BW_ADDR-1:0]  ti_rf_rd_addr1;

    begin
        @(negedge i_clk) begin
            taskState       = "RD";
            i_rf_rd_addr0   = ti_rf_rd_addr0;
            i_rf_rd_addr1   = ti_rf_rd_addr1;
            i_rf_wr_en      = 1'b0;
        end
    end
endtask


task regRD0;
    input   [`BW_ADDR-1:0]  ti_rf_rd_addr0;

    begin
        @(negedge i_clk) begin
            taskState       = "RD0";
            i_rf_rd_addr0   = ti_rf_rd_addr0;
            i_rf_wr_en      = 1'b0;
        end
    end
endtask


task regRD1;
    input   [`BW_ADDR-1:0]  ti_rf_rd_addr1;

    begin
        @(negedge i_clk) begin
            taskState       = "RD1";
            i_rf_rd_addr1   = ti_rf_rd_addr1;
            i_rf_wr_en      = 1'b0;
        end
    end
endtask


//---------------------------------------------------
// Test Stimulus
//---------------------------------------------------
integer  i, j;
initial begin
    init();
    #(4*1000/`CLKFREQ);

    for(i = 0; i < `SIMCYCLE; i++) begin
        regWR(i, 2**i);
    end
    for(i = 0; i < `SIMCYCLE; i++) begin
        regRD0(i);
		#(1000/`CLKFREQ);
        regRD1(i);
    end
    for(i = 0; i < `SIMCYCLE; i++) begin
        regWR(i, $urandom_range(0, 2**`BW_DATA-1));
        regRD(i, i);
    end
    $finish;
end

//---------------------------------------------------
// Dump VCD
//---------------------------------------------------

reg [8*32-1:0] vcd_file;
initial begin
    if($value$plusargs("vcd_file=%s", vcd_file)) begin
        $dumpfile(vcd_file);
        $dumpvars;
        for(i = 0; i < 2**`BW_ADDR; i++) begin
            $dumpvars(0, u_regfile.rf_arr[i]);
        end
        $dumpvars;
    end
    else begin
        $dumpfile("regile_tb.vcd");
        $dumpvars;     
    end
end

endmodule

projects/w3_sequential_logic/regfile/vcd/regfile.vcd
$date
	Wed Jun 26 16:11:14 2024
$end
$version
	Icarus Verilog
$end
$timescale
	1ps
$end
$scope module regfile_tb $end
$var wire 16 ! o_rf_rd_data1 [15:0] $end
$var wire 16 " o_rf_rd_data0 [15:0] $end
$var reg 1 # i_clk $end
$var reg 4 $ i_rf_rd_addr0 [3:0] $end
$var reg 4 % i_rf_rd_addr1 [3:0] $end
$var reg 4 & i_rf_wr_addr [3:0] $end
$var reg 16 ' i_rf_wr_data [15:0] $end
$var reg 1 ( i_rf_wr_en $end
$var reg 256 ) taskState [255:0] $end
$var reg 256 * vcd_file [255:0] $end
$var integer 32 + i [31:0] $end
$scope module u_regfile $end
$var wire 1 # i_clk $end
$var wire 4 , i_rf_rd_addr0 [3:0] $end
$var wire 4 - i_rf_rd_addr1 [3:0] $end
$var wire 4 . i_rf_wr_addr [3:0] $end
$var wire 16 / i_rf_wr_data [15:0] $end
$var wire 1 ( i_rf_wr_en $end
$var wire 16 0 o_rf_rd_data0 [15:0] $end
$var wire 16 1 o_rf_rd_data1 [15:0] $end
$upscope $end
$scope task init $end
$upscope $end
$scope task regRD $end
$var reg 4 2 ti_rf_rd_addr0 [3:0] $end
$var reg 4 3 ti_rf_rd_addr1 [3:0] $end
$upscope $end
$scope task regRD0 $end
$var reg 4 4 ti_rf_rd_addr0 [3:0] $end
$upscope $end
$scope task regRD1 $end
$var reg 4 5 ti_rf_rd_addr1 [3:0] $end
$upscope $end
$scope task regWR $end
$var reg 4 6 ti_rf_wr_addr [3:0] $end
$var reg 16 7 ti_rf_wr_data [15:0] $end
$upscope $end
$upscope $end
$scope module regfile_tb $end
$scope module u_regfile $end
$var reg 16 8 \rf_arr[0] [15:0] $end
$upscope $end
$upscope $end
$scope module regfile_tb $end
$scope module u_regfile $end
$var reg 16 9 \rf_arr[1] [15:0] $end
$upscope $end
$upscope $end
$scope module regfile_tb $end
$scope module u_regfile $end
$var reg 16 : \rf_arr[2] [15:0] $end
$upscope $end
$upscope $end
$scope module regfile_tb $end
$scope module u_regfile $end
$var reg 16 ; \rf_arr[3] [15:0] $end
$upscope $end
$upscope $end
$scope module regfile_tb $end
$scope module u_regfile $end
$var reg 16 < \rf_arr[4] [15:0] $end
$upscope $end
$upscope $end
$scope module regfile_tb $end
$scope module u_regfile $end
$var reg 16 = \rf_arr[5] [15:0] $end
$upscope $end
$upscope $end
$scope module regfile_tb $end
$scope module u_regfile $end
$var reg 16 > \rf_arr[6] [15:0] $end
$upscope $end
$upscope $end
$scope module regfile_tb $end
$scope module u_regfile $end
$var reg 16 ? \rf_arr[7] [15:0] $end
$upscope $end
$upscope $end
$scope module regfile_tb $end
$scope module u_regfile $end
$var reg 16 @ \rf_arr[8] [15:0] $end
$upscope $end
$upscope $end
$scope module regfile_tb $end
$scope module u_regfile $end
$var reg 16 A \rf_arr[9] [15:0] $end
$upscope $end
$upscope $end
$scope module regfile_tb $end
$scope module u_regfile $end
$var reg 16 B \rf_arr[10] [15:0] $end
$upscope $end
$upscope $end
$scope module regfile_tb $end
$scope module u_regfile $end
$var reg 16 C \rf_arr[11] [15:0] $end
$upscope $end
$upscope $end
$scope module regfile_tb $end
$scope module u_regfile $end
$var reg 16 D \rf_arr[12] [15:0] $end
$upscope $end
$upscope $end
$scope module regfile_tb $end
$scope module u_regfile $end
$var reg 16 E \rf_arr[13] [15:0] $end
$upscope $end
$upscope $end
$scope module regfile_tb $end
$scope module u_regfile $end
$var reg 16 F \rf_arr[14] [15:0] $end
$upscope $end
$upscope $end
$scope module regfile_tb $end
$scope module u_regfile $end
$var reg 16 G \rf_arr[15] [15:0] $end
$upscope $end
$upscope $end
$scope module regfile_tb $end
$scope module u_regfile $end
$upscope $end
$scope task init $end
$upscope $end
$scope task regRD $end
$upscope $end
$scope task regRD0 $end
$upscope $end
$scope task regRD1 $end
$upscope $end
$scope task regWR $end
$upscope $end
$upscope $end
$enddefinitions $end
#0
$dumpvars
b1111 G
b1110 F
b1101 E
b1100 D
b1011 C
b1010 B
b1001 A
b1000 @
b111 ?
b110 >
b101 =
b100 <
b11 ;
b10 :
b1 9
b0 8
bx 7
bx 6
bx 5
bx 4
bx 3
bx 2
b0 1
b0 0
b0 /
b0 .
b0 -
b0 ,
b10000 +
b10111000101111011101100110001101100100001011110111001001100101011001110110011001101001011011000110010100101110011101100110001101100100 *
bx )
0(
b0 '
b0 &
b0 %
b0 $
0#
b0 "
b0 !
$end
#5000
b0 8
1#
#10000
0#
#15000
b0 8
1#
#20000
0#
#25000
b0 8
1#
#30000
0#
#35000
b0 8
1#
#40000
1(
b1 '
b1 /
b101011101010010 )
0#
b10 7
b1 6
b1 +
#45000
b1 8
b1 "
b1 0
b1 !
b1 1
1#
#50000
b100 7
b10 6
b10 +
b1 &
b1 .
b10 '
b10 /
0#
#55000
b10 9
1#
#60000
b1000 7
b11 6
b11 +
b10 &
b10 .
b100 '
b100 /
0#
#65000
b100 :
1#
#70000
b10000 7
b100 6
b100 +
b11 &
b11 .
b1000 '
b1000 /
0#
#75000
b1000 ;
1#
#80000
b100000 7
b101 6
b101 +
b100 &
b100 .
b10000 '
b10000 /
0#
#85000
b10000 <
1#
#90000
b1000000 7
b110 6
b110 +
b101 &
b101 .
b100000 '
b100000 /
0#
#95000
b100000 =
1#
#100000
b10000000 7
b111 6
b111 +
b110 &
b110 .
b1000000 '
b1000000 /
0#
#105000
b1000000 >
1#
#110000
b100000000 7
b1000 6
b1000 +
b111 &
b111 .
b10000000 '
b10000000 /
0#
#115000
b10000000 ?
1#
#120000
b1000000000 7
b1001 6
b1001 +
b1000 &
b1000 .
b100000000 '
b100000000 /
0#
#125000
b100000000 @
1#
#130000
b10000000000 7
b1010 6
b1010 +
b1001 &
b1001 .
b1000000000 '
b1000000000 /
0#
#135000
b1000000000 A
1#
#140000
b100000000000 7
b1011 6
b1011 +
b1010 &
b1010 .
b10000000000 '
b10000000000 /
0#
#145000
b10000000000 B
1#
#150000
b1000000000000 7
b1100 6
b1100 +
b1011 &
b1011 .
b100000000000 '
b100000000000 /
0#
#155000
b100000000000 C
1#
#160000
b10000000000000 7
b1101 6
b1101 +
b1100 &
b1100 .
b1000000000000 '
b1000000000000 /
0#
#165000
b1000000000000 D
1#
#170000
b100000000000000 7
b1110 6
b1110 +
b1101 &
b1101 .
b10000000000000 '
b10000000000000 /
0#
#175000
b10000000000000 E
1#
#180000
b1000000000000000 7
b1111 6
b1111 +
b1110 &
b1110 .
b100000000000000 '
b100000000000000 /
0#
#185000
b100000000000000 F
1#
#190000
b0 4
b0 +
b1111 &
b1111 .
b1000000000000000 '
b1000000000000000 /
0#
#195000
b1000000000000000 G
1#
#200000
0(
b10100100100010000110000 )
0#
#205000
b1000000000000000 G
1#
#210000
b1 4
b1 +
b10100100100010000110001 )
0#
b0 5
#215000
b1000000000000000 G
1#
#220000
b10 "
b10 0
b1 $
b1 ,
b10100100100010000110000 )
0#
#225000
b1000000000000000 G
1#
#230000
b10 4
b10 +
b10 !
b10 1
b1 %
b1 -
b10100100100010000110001 )
0#
b1 5
#235000
b1000000000000000 G
1#
#240000
b100 "
b100 0
b10 $
b10 ,
b10100100100010000110000 )
0#
#245000
b1000000000000000 G
1#
#250000
b11 4
b11 +
b100 !
b100 1
b10 %
b10 -
b10100100100010000110001 )
0#
b10 5
#255000
b1000000000000000 G
1#
#260000
b1000 "
b1000 0
b11 $
b11 ,
b10100100100010000110000 )
0#
#265000
b1000000000000000 G
1#
#270000
b100 4
b100 +
b1000 !
b1000 1
b11 %
b11 -
b10100100100010000110001 )
0#
b11 5
#275000
b1000000000000000 G
1#
#280000
b10000 "
b10000 0
b100 $
b100 ,
b10100100100010000110000 )
0#
#285000
b1000000000000000 G
1#
#290000
b101 4
b101 +
b10000 !
b10000 1
b100 %
b100 -
b10100100100010000110001 )
0#
b100 5
#295000
b1000000000000000 G
1#
#300000
b100000 "
b100000 0
b101 $
b101 ,
b10100100100010000110000 )
0#
#305000
b1000000000000000 G
1#
#310000
b110 4
b110 +
b100000 !
b100000 1
b101 %
b101 -
b10100100100010000110001 )
0#
b101 5
#315000
b1000000000000000 G
1#
#320000
b1000000 "
b1000000 0
b110 $
b110 ,
b10100100100010000110000 )
0#
#325000
b1000000000000000 G
1#
#330000
b111 4
b111 +
b1000000 !
b1000000 1
b110 %
b110 -
b10100100100010000110001 )
0#
b110 5
#335000
b1000000000000000 G
1#
#340000
b10000000 "
b10000000 0
b111 $
b111 ,
b10100100100010000110000 )
0#
#345000
b1000000000000000 G
1#
#350000
b1000 4
b1000 +
b10000000 !
b10000000 1
b111 %
b111 -
b10100100100010000110001 )
0#
b111 5
#355000
b1000000000000000 G
1#
#360000
b100000000 "
b100000000 0
b1000 $
b1000 ,
b10100100100010000110000 )
0#
#365000
b1000000000000000 G
1#
#370000
b1001 4
b1001 +
b100000000 !
b100000000 1
b1000 %
b1000 -
b10100100100010000110001 )
0#
b1000 5
#375000
b1000000000000000 G
1#
#380000
b1000000000 "
b1000000000 0
b1001 $
b1001 ,
b10100100100010000110000 )
0#
#385000
b1000000000000000 G
1#
#390000
b1010 4
b1010 +
b1000000000 !
b1000000000 1
b1001 %
b1001 -
b10100100100010000110001 )
0#
b1001 5
#395000
b1000000000000000 G
1#
#400000
b10000000000 "
b10000000000 0
b1010 $
b1010 ,
b10100100100010000110000 )
0#
#405000
b1000000000000000 G
1#
#410000
b1011 4
b1011 +
b10000000000 !
b10000000000 1
b1010 %
b1010 -
b10100100100010000110001 )
0#
b1010 5
#415000
b1000000000000000 G
1#
#420000
b100000000000 "
b100000000000 0
b1011 $
b1011 ,
b10100100100010000110000 )
0#
#425000
b1000000000000000 G
1#
#430000
b1100 4
b1100 +
b100000000000 !
b100000000000 1
b1011 %
b1011 -
b10100100100010000110001 )
0#
b1011 5
#435000
b1000000000000000 G
1#
#440000
b1000000000000 "
b1000000000000 0
b1100 $
b1100 ,
b10100100100010000110000 )
0#
#445000
b1000000000000000 G
1#
#450000
b1101 4
b1101 +
b1000000000000 !
b1000000000000 1
b1100 %
b1100 -
b10100100100010000110001 )
0#
b1100 5
#455000
b1000000000000000 G
1#
#460000
b10000000000000 "
b10000000000000 0
b1101 $
b1101 ,
b10100100100010000110000 )
0#
#465000
b1000000000000000 G
1#
#470000
b1110 4
b1110 +
b10000000000000 !
b10000000000000 1
b1101 %
b1101 -
b10100100100010000110001 )
0#
b1101 5
#475000
b1000000000000000 G
1#
#480000
b100000000000000 "
b100000000000000 0
b1110 $
b1110 ,
b10100100100010000110000 )
0#
#485000
b1000000000000000 G
1#
#490000
b1111 4
b1111 +
b100000000000000 !
b100000000000000 1
b1110 %
b1110 -
b10100100100010000110001 )
0#
b1110 5
#495000
b1000000000000000 G
1#
#500000
b1000000000000000 "
b1000000000000000 0
b1111 $
b1111 ,
b10100100100010000110000 )
0#
#505000
b1000000000000000 G
1#
#510000
b1001001000010101 7
b0 6
b0 +
b1000000000000000 !
b1000000000000000 1
b1111 %
b1111 -
b10100100100010000110001 )
0#
b1111 5
#515000
b1000000000000000 G
1#
#520000
b0 3
b0 2
1(
b0 &
b0 .
b1001001000010101 '
b1001001000010101 /
b101011101010010 )
0#
#525000
b1001001000010101 8
1#
#530000
b100000010001001 7
b1 6
b1 +
0(
b1001001000010101 !
b1001001000010101 1
b0 %
b0 -
b1001001000010101 "
b1001001000010101 0
b0 $
b0 ,
b101001001000100 )
0#
#535000
b1001001000010101 8
1#
#540000
b1 3
b1 2
1(
b1 &
b1 .
b100000010001001 '
b100000010001001 /
b101011101010010 )
0#
#545000
b100000010001001 9
1#
#550000
b10010000100 7
b10 6
b10 +
0(
b100000010001001 !
b100000010001001 1
b1 %
b1 -
b100000010001001 "
b100000010001001 0
b1 $
b1 ,
b101001001000100 )
0#
#555000
b100000010001001 9
1#
#560000
b10 3
b10 2
1(
b10 &
b10 .
b10010000100 '
b10010000100 /
b101011101010010 )
0#
#565000
b10010000100 :
1#
#570000
b11000111110000 7
b11 6
b11 +
0(
b10010000100 !
b10010000100 1
b10 %
b10 -
b10010000100 "
b10010000100 0
b10 $
b10 ,
b101001001000100 )
0#
#575000
b10010000100 :
1#
#580000
b11 3
b11 2
1(
b11 &
b11 .
b11000111110000 '
b11000111110000 /
b101011101010010 )
0#
#585000
b11000111110000 ;
1#
#590000
b1000011010111001 7
b100 6
b100 +
0(
b11000111110000 !
b11000111110000 1
b11 %
b11 -
b11000111110000 "
b11000111110000 0
b11 $
b11 ,
b101001001000100 )
0#
#595000
b11000111110000 ;
1#
#600000
b100 3
b100 2
1(
b100 &
b100 .
b1000011010111001 '
b1000011010111001 /
b101011101010010 )
0#
#605000
b1000011010111001 <
1#
#610000
b1100011011011111 7
b101 6
b101 +
0(
b1000011010111001 !
b1000011010111001 1
b100 %
b100 -
b1000011010111001 "
b1000011010111001 0
b100 $
b100 ,
b101001001000100 )
0#
#615000
b1000011010111001 <
1#
#620000
b101 3
b101 2
1(
b101 &
b101 .
b1100011011011111 '
b1100011011011111 /
b101011101010010 )
0#
#625000
b1100011011011111 =
1#
#630000
b11001011000010 7
b110 6
b110 +
0(
b1100011011011111 !
b1100011011011111 1
b101 %
b101 -
b1100011011011111 "
b1100011011011111 0
b101 $
b101 ,
b101001001000100 )
0#
#635000
b1100011011011111 =
1#
#640000
b110 3
b110 2
1(
b110 &
b110 .
b11001011000010 '
b11001011000010 /
b101011101010010 )
0#
#645000
b11001011000010 >
1#
#650000
b100100110111 7
b111 6
b111 +
0(
b11001011000010 !
b11001011000010 1
b110 %
b110 -
b11001011000010 "
b11001011000010 0
b110 $
b110 ,
b101001001000100 )
0#
#655000
b11001011000010 >
1#
#660000
b111 3
b111 2
1(
b111 &
b111 .
b100100110111 '
b100100110111 /
b101011101010010 )
0#
#665000
b100100110111 ?
1#
#670000
b1000000011110011 7
b1000 6
b1000 +
0(
b100100110111 !
b100100110111 1
b111 %
b111 -
b100100110111 "
b100100110111 0
b111 $
b111 ,
b101001001000100 )
0#
#675000
b100100110111 ?
1#
#680000
b1000 3
b1000 2
1(
b1000 &
b1000 .
b1000000011110011 '
b1000000011110011 /
b101011101010010 )
0#
#685000
b1000000011110011 @
1#
#690000
b1000011011010111 7
b1001 6
b1001 +
0(
b1000000011110011 !
b1000000011110011 1
b1000 %
b1000 -
b1000000011110011 "
b1000000011110011 0
b1000 $
b1000 ,
b101001001000100 )
0#
#695000
b1000000011110011 @
1#
#700000
b1001 3
b1001 2
1(
b1001 &
b1001 .
b1000011011010111 '
b1000011011010111 /
b101011101010010 )
0#
#705000
b1000011011010111 A
1#
#710000
b1011101100100011 7
b1010 6
b1010 +
0(
b1000011011010111 !
b1000011011010111 1
b1001 %
b1001 -
b1000011011010111 "
b1000011011010111 0
b1001 $
b1001 ,
b101001001000100 )
0#
#715000
b1000011011010111 A
1#
#720000
b1010 3
b1010 2
1(
b1010 &
b1010 .
b1011101100100011 '
b1011101100100011 /
b101011101010010 )
0#
#725000
b1011101100100011 B
1#
#730000
b1001111010001101 7
b1011 6
b1011 +
0(
b1011101100100011 !
b1011101100100011 1
b1010 %
b1010 -
b1011101100100011 "
b1011101100100011 0
b1010 $
b1010 ,
b101001001000100 )
0#
#735000
b1011101100100011 B
1#
#740000
b1011 3
b1011 2
1(
b1011 &
b1011 .
b1001111010001101 '
b1001111010001101 /
b101011101010010 )
0#
#745000
b1001111010001101 C
1#
#750000
b1111011011010100 7
b1100 6
b1100 +
0(
b1001111010001101 !
b1001111010001101 1
b1011 %
b1011 -
b1001111010001101 "
b1001111010001101 0
b1011 $
b1011 ,
b101001001000100 )
0#
#755000
b1001111010001101 C
1#
#760000
b1100 3
b1100 2
1(
b1100 &
b1100 .
b1111011011010100 '
b1111011011010100 /
b101011101010010 )
0#
#765000
b1111011011010100 D
1#
#770000
b1100011000101101 7
b1101 6
b1101 +
0(
b1111011011010100 !
b1111011011010100 1
b1100 %
b1100 -
b1111011011010100 "
b1111011011010100 0
b1100 $
b1100 ,
b101001001000100 )
0#
#775000
b1111011011010100 D
1#
#780000
b1101 3
b1101 2
1(
b1101 &
b1101 .
b1100011000101101 '
b1100011000101101 /
b101011101010010 )
0#
#785000
b1100011000101101 E
1#
#790000
b1111110011111101 7
b1110 6
b1110 +
0(
b1100011000101101 !
b1100011000101101 1
b1101 %
b1101 -
b1100011000101101 "
b1100011000101101 0
b1101 $
b1101 ,
b101001001000100 )
0#
#795000
b1100011000101101 E
1#
#800000
b1110 3
b1110 2
1(
b1110 &
b1110 .
b1111110011111101 '
b1111110011111101 /
b101011101010010 )
0#
#805000
b1111110011111101 F
1#
#810000
b110001100110111 7
b1111 6
b1111 +
0(
b1111110011111101 !
b1111110011111101 1
b1110 %
b1110 -
b1111110011111101 "
b1111110011111101 0
b1110 $
b1110 ,
b101001001000100 )
0#
#815000
b1111110011111101 F
1#
#820000
b1111 3
b1111 2
1(
b1111 &
b1111 .
b110001100110111 '
b110001100110111 /
b101011101010010 )
0#
#825000
b110001100110111 G
1#
#830000
b10000 +
0(
b110001100110111 !
b110001100110111 1
b1111 %
b1111 -
b110001100110111 "
b110001100110111 0
b1111 $
b1111 ,
b101001001000100 )
0#
